Workbook

Sheet HOW TO PLAY
A1: HOW TO PLAY — and what you are actually testing
A4: WHY THIS EXISTS
B5: Every system in the design brief assumes one thing is true: that nudging an invisible system and watching the consequences arrive four to eight seasons later, in a country you did not target, is FUN. Nothing written so far proves that. This workbook is the cheapest possible test of it. Ten years, one homeland, eight regions, nine tools.
B6: If forty seasons of this is tense and legible and you want a forty-first, the design is sound and worth building. If it feels like filling in a tax return, the core loop needs rework and you have found that out in an afternoon instead of a year.
A8: THE SETUP
B9: You direct a national environmental warfare programme, 1946-1955. Your homeland is the North American Plains: a wheat and maize exporter. Your budget comes from two places — a share of homeland farm revenue, and an appropriation driven by MANDATE, which rises when the world's weather looks frightening.
B10: Read that last part again. A calm world defunds you.
A12: HOW A SEASON WORKS
A13: 1. Look | B13: Read the row above. What landed? Which region is worst hit? What happened to the grain price and your revenue?
A14: 2. Commit | B14: On the current row, choose up to two operations from the dropdowns in columns D and F, and a target region in E and G where the tool needs one. Set containment spend in H.
A15: 3. Resolve | B15: The row fills in. Most of what you just ordered will NOT appear this season — check the lag in CAPABILITIES.
A16: 4. Move down | B16: One row at a time. Do not scroll ahead and do not undo. Playing it honestly is the whole experiment.
A18: THE FOUR THINGS TO WATCH
A19: Treasury (I) | B19: Runs out and you cannot act. Ops are expensive; containment is worse.
A20: Mandate (J) | B20: Rises with global weather severity. This is your appropriation. It is also the trap.
A21: Price / Revenue (M, N) | B21: You export wheat. Someone else's failed harvest is your windfall. Someone else's bumper crop is your problem. This is the whole economic game.
A22: Dossier (Q, R) | B22: Hidden accumulation of evidence. You never see the number in the real game — only column R. At 200 you are exposed and the run is over.
A24: WHAT TO TRY
A25: The obvious play | B25: Cloud Seeding on your homeland every season. Watch what it costs you and what it fails to achieve.
A26: The real play | B26: Find a region that competes with you in wheat. Look up its teleconnections in GRAPH. Move the driver, not the region — it is slower, but the anomaly arrives looking like climate.
A27: The elegant play | B27: Wait. Watch the ENSO column in CLIMATE. When a strong natural swing is already coming, act into it: your anomaly hides inside the envelope and your signature multiplier collapses. Patience is a mechanic.
A28: Fire Enablement | B28: Only fully effective if the target was already dry last season. Build the drought first, then ignite. This is the composite mechanic in miniature and it is the most interesting tool in the catalogue.
A29: The energy ledger | B29: Ocean Thermal, Aerosol and ENSO Forcing all DISPLACE — check the CAPABILITIES sheet. What you move surfaces somewhere else, several seasons later, with the opposite sign. This is where the game bites.
A31: WHAT TO RECORD
B32: Keep a note beside you. After every season write one line: what you expected, and what happened. At the end, count how many times those two matched. If it is near zero, the model is noise and the player cannot learn it. If it is near forty, it is too legible and there is no tension. Somewhere in the middle is a game.
B33: Also record: which season was the most fun, and why. That answer is worth more than the rest of this workbook.
A35: WHAT THIS IS NOT
B36: Not balanced. Not a spec. Not a model of the real climate — the graph is real in its RELATIONSHIPS and invented in its NUMBERS. Every value on ASSUMPTIONS is a guess. Change them freely; that is what they are for.
A38: SHEETS
A39: PLAY | B39: Where you play. Blue cells are yours.
A40: CLIMATE | B40: The natural background. In the real game this is observed ENSO/IOD/Atlantic SST data.
A41: REGIONS | B41: Nodes: crop, supply weight, yield sensitivity, variance envelope.
A42: GRAPH | B42: Edges: coefficients and lags. Real climatology, invented magnitudes.
A43: CAPABILITIES | B43: The nine tools and their parameters.
A44: ASSUMPTIONS | B44: Every dial in the model, plus the exposure ladder.
A45: ENGINE | B45: The resolution maths. Computed; do not edit.

Sheet PLAY
A1: FORCE MAJEURE — CORE LOOP PROTOTYPE
A2: You are the Directorate. 1946-1955. Homeland: North American Plains (wheat and maize exporter).
A4: THE ONLY QUESTION THIS PROTOTYPE ASKS: is it fun to nudge an invisible system and watch the consequences arrive four to eight seasons later in the wrong country? Fill the four BLUE columns, one season at a time, top to bottom. Do not read ahead. Read HOW TO PLAY first.
A7: t | B7: Year | C7: Qtr | D7: OPERATION A | E7: Target region | F7: OPERATION B | G7: Target region | H7: Containment $ | I7: Treasury | J7: Mandate | K7: Homeland yield | L7: World supply | M7: Grain price | N7: Revenue | O7: Worst-hit region | P7: its yield | Q7: Dossier | R7: WHAT YOU ARE TOLD | S7: STATUS
A8: 1 | B8: =CLIMATE!B8 -> 1946 | C8: =CLIMATE!C8 -> Winter | D8: Cloud Seeding | E8: Sahel | F8: — none — | H8: 0 | I8: =ENGINE!$BO8 -> 89.874567 | J8: =ENGINE!$BK8 -> 29.792581 | K8: =ENGINE!$AY8 -> 100 | L8: =ENGINE!$BG8 -> 95.596576 | M8: =ENGINE!$BH8 -> 108.44357 | N8: =ENGINE!$BI8 -> 92.177032 | O8: =INDEX(REGIONS!$B$7:$B$14,MATCH(MIN(ENGINE!$AY8:$BF8),ENGINE!$AY8:$BF8,0)) -> Eastern Australia | P8: =MIN(ENGINE!$AY8:$BF8) -> 77.41562 | Q8: =ENGINE!$BQ8 -> 0 | R8: =INDEX(ASSUMPTIONS!$B$28:$B$34,MATCH(ENGINE!$BQ8,ASSUMPTIONS!$A$28:$A$34,1)) -> Nothing. No one is looking. | S8: =IF(ENGINE!$BQ8>=200,"EXPOSED — run over",IF(ENGINE!$BO8<0,"INSOLVENT — programme suspended",IF(AND($A8>8,ENGINE!$BK8<=ASSUMPTIONS!$B$12+1),"Committee is asking what you are for","running"))) -> running
A9: 2 | B9: =CLIMATE!B9 -> 1946 | C9: =CLIMATE!C9 -> Spring | D9: — none — | F9: — none — | H9: 0 | I9: =ENGINE!$BO9 -> 98.833468 | J9: =ENGINE!$BK9 -> 33.286162 | K9: =ENGINE!$AY9 -> 100 | L9: =ENGINE!$BG9 -> 95.885337 | M9: =ENGINE!$BH9 -> 107.85643 | N9: =ENGINE!$BI9 -> 91.677966 | O9: =INDEX(REGIONS!$B$7:$B$14,MATCH(MIN(ENGINE!$AY9:$BF9),ENGINE!$AY9:$BF9,0)) -> Eastern Australia | P9: =MIN(ENGINE!$AY9:$BF9) -> 74.55822 | Q9: =ENGINE!$BQ9 -> 2.1120288 | R9: =INDEX(ASSUMPTIONS!$B$28:$B$34,MATCH(ENGINE!$BQ9,ASSUMPTIONS!$A$28:$A$34,1)) -> Nothing. No one is looking. | S9: =IF(ENGINE!$BQ9>=200,"EXPOSED — run over",IF(ENGINE!$BO9<0,"INSOLVENT — programme suspended",IF(AND($A9>8,ENGINE!$BK9<=ASSUMPTIONS!$B$12+1),"Committee is asking what you are for","running"))) -> running
A10: 3 | B10: =CLIMATE!B10 -> 1946 | C10: =CLIMATE!C10 -> Summer | D10: — none — | F10: — none — | H10: 0 | I10: =ENGINE!$BO10 -> 106.64558 | J10: =ENGINE!$BK10 -> 31.854718 | K10: =ENGINE!$AY10 -> 100 | L10: =ENGINE!$BG10 -> 95.206901 | M10: =ENGINE!$BH10 -> 109.24381 | N10: =ENGINE!$BI10 -> 92.857236 | O10: =INDEX(REGIONS!$B$7:$B$14,MATCH(MIN(ENGINE!$AY10:$BF10),ENGINE!$AY10:$BF10,0)) -> Eastern Australia | P10: =MIN(ENGINE!$AY10:$BF10) -> 73.23508 | Q10: =ENGINE!$BQ10 -> 2.0275477 | R10: =INDEX(ASSUMPTIONS!$B$28:$B$34,MATCH(ENGINE!$BQ10,ASSUMPTIONS!$A$28:$A$34,1)) -> Nothing. No one is looking. | S10: =IF(ENGINE!$BQ10>=200,"EXPOSED — run over",IF(ENGINE!$BO10<0,"INSOLVENT — programme suspended",IF(AND($A10>8,ENGINE!$BK10<=ASSUMPTIONS!$B$12+1),"Committee is asking what you are for","running"))) -> running
A11: 4 | B11: =CLIMATE!B11 -> 1946 | C11: =CLIMATE!C11 -> Autumn | D11: — none — | F11: — none — | H11: 0 | I11: =ENGINE!$BO11 -> 112.37145 | J11: =ENGINE!$BK11 -> 29.505952 | K11: =ENGINE!$AY11 -> 100 | L11: =ENGINE!$BG11 -> 95.07593 | M11: =ENGINE!$BH11 -> 109.51484 | N11: =ENGINE!$BI11 -> 93.08761 | O11: =INDEX(REGIONS!$B$7:$B$14,MATCH(MIN(ENGINE!$AY11:$BF11),ENGINE!$AY11:$BF11,0)) -> Sahel | P11: =MIN(ENGINE!$AY11:$BF11) -> 86.90328 | Q11: =ENGINE!$BQ11 -> 1.9464458 | R11: =INDEX(ASSUMPTIONS!$B$28:$B$34,MATCH(ENGINE!$BQ11,ASSUMPTIONS!$A$28:$A$34,1)) -> Nothing. No one is looking. | S11: =IF(ENGINE!$BQ11>=200,"EXPOSED — run over",IF(ENGINE!$BO11<0,"INSOLVENT — programme suspended",IF(AND($A11>8,ENGINE!$BK11<=ASSUMPTIONS!$B$12+1),"Committee is asking what you are for","running"))) -> running
A12: 5 | B12: =CLIMATE!B12 -> 1947 | C12: =CLIMATE!C12 -> Winter | D12: — none — | F12: — none — | H12: 0 | I12: =ENGINE!$BO12 -> 117.20732 | J12: =ENGINE!$BK12 -> 28.68355 | K12: =ENGINE!$AY12 -> 97.1832 | L12: =ENGINE!$BG12 -> 94.283402 | M12: =ENGINE!$BH12 -> 111.17741 | N12: =ENGINE!$BI12 -> 91.838901 | O12: =INDEX(REGIONS!$B$7:$B$14,MATCH(MIN(ENGINE!$AY12:$BF12),ENGINE!$AY12:$BF12,0)) -> Horn of Africa | P12: =MIN(ENGINE!$AY12:$BF12) -> 80.6744 | Q12: =ENGINE!$BQ12 -> 1.8685879 | R12: =INDEX(ASSUMPTIONS!$B$28:$B$34,MATCH(ENGINE!$BQ12,ASSUMPTIONS!$A$28:$A$34,1)) -> Nothing. No one is looking. | S12: =IF(ENGINE!$BQ12>=200,"EXPOSED — run over",IF(ENGINE!$BO12<0,"INSOLVENT — programme suspended",IF(AND($A12>8,ENGINE!$BK12<=ASSUMPTIONS!$B$12+1),"Committee is asking what you are for","running"))) -> running
A13: 6 | B13: =CLIMATE!B13 -> 1947 | C13: =CLIMATE!C13 -> Spring | D13: — none — | F13: — none — | H13: 0 | I13: =ENGINE!$BO13 -> 124.66196 | J13: =ENGINE!$BK13 -> 31.399228 | K13: =ENGINE!$AY13 -> 98.3774 | L13: =ENGINE!$BG13 -> 94.099619 | M13: =ENGINE!$BH13 -> 111.56856 | N13: =ENGINE!$BI13 -> 93.294515 | O13: =INDEX(REGIONS!$B$7:$B$14,MATCH(MIN(ENGINE!$AY13:$BF13),ENGINE!$AY13:$BF13,0)) -> South Asia | P13: =MIN(ENGINE!$AY13:$BF13) -> 84.95392 | Q13: =ENGINE!$BQ13 -> 1.7938444 | R13: =INDEX(ASSUMPTIONS!$B$28:$B$34,MATCH(ENGINE!$BQ13,ASSUMPTIONS!$A$28:$A$34,1)) -> Nothing. No one is looking. | S13: =IF(ENGINE!$BQ13>=200,"EXPOSED — run over",IF(ENGINE!$BO13<0,"INSOLVENT — programme suspended",IF(AND($A13>8,ENGINE!$BK13<=ASSUMPTIONS!$B$12+1),"Committee is asking what you are for","running"))) -> running
A14: 7 | B14: =CLIMATE!B14 -> 1947 | C14: =CLIMATE!C14 -> Summer | D14: — none — | F14: — none — | H14: 0 | I14: =ENGINE!$BO14 -> 128.56502 | J14: =ENGINE!$BK14 -> 28.037191 | K14: =ENGINE!$AY14 -> 100 | L14: =ENGINE!$BG14 -> 97.530471 | M14: =ENGINE!$BH14 -> 104.60379 | N14: =ENGINE!$BI14 -> 88.913221 | O14: =INDEX(REGIONS!$B$7:$B$14,MATCH(MIN(ENGINE!$AY14:$BF14),ENGINE!$AY14:$BF14,0)) -> Eastern Australia | P14: =MIN(ENGINE!$AY14:$BF14) -> 84.12414 | Q14: =ENGINE!$BQ14 -> 1.7220906 | R14: =INDEX(ASSUMPTIONS!$B$28:$B$34,MATCH(ENGINE!$BQ14,ASSUMPTIONS!$A$28:$A$34,1)) -> Nothing. No one is looking. | S14: =IF(ENGINE!$BQ14>=200,"EXPOSED — run over",IF(ENGINE!$BO14<0,"INSOLVENT — programme suspended",IF(AND($A14>8,ENGINE!$BK14<=ASSUMPTIONS!$B$12+1),"Committee is asking what you are for","running"))) -> running
A15: 8 | B15: =CLIMATE!B15 -> 1947 | C15: =CLIMATE!C15 -> Autumn | D15: — none — | F15: — none — | H15: 0 | I15: =ENGINE!$BO15 -> 132.12531 | J15: =ENGINE!$BK15 -> 28 | K15: =ENGINE!$AY15 -> 97.543 | L15: =ENGINE!$BG15 -> 97.776814 | M15: =ENGINE!$BH15 -> 104.12989 | N15: =ENGINE!$BI15 -> 86.335706 | O15: =INDEX(REGIONS!$B$7:$B$14,MATCH(MIN(ENGINE!$AY15:$BF15),ENGINE!$AY15:$BF15,0)) -> Southeast Asia | P15: =MIN(ENGINE!$AY15:$BF15) -> 94.60384 | Q15: =ENGINE!$BQ15 -> 1.653207 | R15: =INDEX(ASSUMPTIONS!$B$28:$B$34,MATCH(ENGINE!$BQ15,ASSUMPTIONS!$A$28:$A$34,1)) -> Nothing. No one is looking. | S15: =IF(ENGINE!$BQ15>=200,"EXPOSED — run over",IF(ENGINE!$BO15<0,"INSOLVENT — programme suspended",IF(AND($A15>8,ENGINE!$BK15<=ASSUMPTIONS!$B$12+1),"Committee is asking what you are for","running"))) -> running
A16: 9 | B16: =CLIMATE!B16 -> 1948 | C16: =CLIMATE!C16 -> Winter | D16: — none — | F16: — none — | H16: 0 | I16: =ENGINE!$BO16 -> 136.70419 | J16: =ENGINE!$BK16 -> 29.17999 | K16: =ENGINE!$AY16 -> 100 | L16: =ENGINE!$BG16 -> 99.36897 | M16: =ENGINE!$BH16 -> 101.14597 | N16: =ENGINE!$BI16 -> 85.974075 | O16: =INDEX(REGIONS!$B$7:$B$14,MATCH(MIN(ENGINE!$AY16:$BF16),ENGINE!$AY16:$BF16,0)) -> Black Sea Steppe | P16: =MIN(ENGINE!$AY16:$BF16) -> 96.05606 | Q16: =ENGINE!$BQ16 -> 1.5870787 | R16: =INDEX(ASSUMPTIONS!$B$28:$B$34,MATCH(ENGINE!$BQ16,ASSUMPTIONS!$A$28:$A$34,1)) -> Nothing. No one is looking. | S16: =IF(ENGINE!$BQ16>=200,"EXPOSED — run over",IF(ENGINE!$BO16<0,"INSOLVENT — programme suspended",IF(AND($A16>8,ENGINE!$BK16<=ASSUMPTIONS!$B$12+1),"Committee is asking what you are for","running"))) -> running
A17: 10 | B17: =CLIMATE!B17 -> 1948 | C17: =CLIMATE!C17 -> Spring | D17: — none — | F17: — none — | H17: 0 | I17: =ENGINE!$BO17 -> 149.4067 | J17: =ENGINE!$BK17 -> 38.180086 | K17: =ENGINE!$AY17 -> 100 | L17: =ENGINE!$BG17 -> 99.243176 | M17: =ENGINE!$BH17 -> 101.37686 | N17: =ENGINE!$BI17 -> 86.170328 | O17: =INDEX(REGIONS!$B$7:$B$14,MATCH(MIN(ENGINE!$AY17:$BF17),ENGINE!$AY17:$BF17,0)) -> La Plata Basin | P17: =MIN(ENGINE!$AY17:$BF17) -> 96.696 | Q17: =ENGINE!$BQ17 -> 1.5235956 | R17: =INDEX(ASSUMPTIONS!$B$28:$B$34,MATCH(ENGINE!$BQ17,ASSUMPTIONS!$A$28:$A$34,1)) -> Nothing. No one is looking. | S17: =IF(ENGINE!$BQ17>=200,"EXPOSED — run over",IF(ENGINE!$BO17<0,"INSOLVENT — programme suspended",IF(AND($A17>8,ENGINE!$BK17<=ASSUMPTIONS!$B$12+1),"Committee is asking what you are for","running"))) -> running
A18: 11 | B18: =CLIMATE!B18 -> 1948 | C18: =CLIMATE!C18 -> Summer | D18: — none — | F18: — none — | H18: 0 | I18: =ENGINE!$BO18 -> 156.00786 | J18: =ENGINE!$BK18 -> 31.712149 | K18: =ENGINE!$AY18 -> 92.8992 | L18: =ENGINE!$BG18 -> 96.729292 | M18: =ENGINE!$BH18 -> 106.16848 | N18: =ENGINE!$BI18 -> 83.835215 | O18: =INDEX(REGIONS!$B$7:$B$14,MATCH(MIN(ENGINE!$AY18:$BF18),ENGINE!$AY18:$BF18,0)) -> La Plata Basin | P18: =MIN(ENGINE!$AY18:$BF18) -> 89.402 | Q18: =ENGINE!$BQ18 -> 1.4626518 | R18: =INDEX(ASSUMPTIONS!$B$28:$B$34,MATCH(ENGINE!$BQ18,ASSUMPTIONS!$A$28:$A$34,1)) -> Nothing. No one is looking. | S18: =IF(ENGINE!$BQ18>=200,"EXPOSED — run over",IF(ENGINE!$BO18<0,"INSOLVENT — programme suspended",IF(AND($A18>8,ENGINE!$BK18<=ASSUMPTIONS!$B$12+1),"Committee is asking what you are for","running"))) -> running
A19: 12 | B19: =CLIMATE!B19 -> 1948 | C19: =CLIMATE!C19 -> Autumn | D19: — none — | F19: — none — | H19: 0 | I19: =ENGINE!$BO19 -> 159.30489 | J19: =ENGINE!$BK19 -> 28 | K19: =ENGINE!$AY19 -> 96.255 | L19: =ENGINE!$BG19 -> 98.45526 | M19: =ENGINE!$BH19 -> 102.84186 | N19: =ENGINE!$BI19 -> 84.141871 | O19: =INDEX(REGIONS!$B$7:$B$14,MATCH(MIN(ENGINE!$AY19:$BF19),ENGINE!$AY19:$BF19,0)) -> Horn of Africa | P19: =MIN(ENGINE!$AY19:$BF19) -> 95.19016 | Q19: =ENGINE!$BQ19 -> 1.4041457 | R19: =INDEX(ASSUMPTIONS!$B$28:$B$34,MATCH(ENGINE!$BQ19,ASSUMPTIONS!$A$28:$A$34,1)) -> Nothing. No one is looking. | S19: =IF(ENGINE!$BQ19>=200,"EXPOSED — run over",IF(ENGINE!$BO19<0,"INSOLVENT — programme suspended",IF(AND($A19>8,ENGINE!$BK19<=ASSUMPTIONS!$B$12+1),"Committee is asking what you are for","running"))) -> Committee is asking what you are for
A20: 13 | B20: =CLIMATE!B20 -> 1949 | C20: =CLIMATE!C20 -> Winter | D20: — none — | F20: — none — | H20: 0 | I20: =ENGINE!$BO20 -> 162.98667 | J20: =ENGINE!$BK20 -> 28 | K20: =ENGINE!$AY20 -> 94.946 | L20: =ENGINE!$BG20 -> 95.700012 | M20: =ENGINE!$BH20 -> 108.23268 | N20: =ENGINE!$BI20 -> 87.348211 | O20: =INDEX(REGIONS!$B$7:$B$14,MATCH(MIN(ENGINE!$AY20:$BF20),ENGINE!$AY20:$BF20,0)) -> Horn of Africa | P20: =MIN(ENGINE!$AY20:$BF20) -> 81.93272 | Q20: =ENGINE!$BQ20 -> 1.3479799 | R20: =INDEX(ASSUMPTIONS!$B$28:$B$34,MATCH(ENGINE!$BQ20,ASSUMPTIONS!$A$28:$A$34,1)) -> Nothing. No one is looking. | S20: =IF(ENGINE!$BQ20>=200,"EXPOSED — run over",IF(ENGINE!$BO20<0,"INSOLVENT — programme suspended",IF(AND($A20>8,ENGINE!$BK20<=ASSUMPTIONS!$B$12+1),"Committee is asking what you are for","running"))) -> Committee is asking what you are for
... A47: 40 | B47: =CLIMATE!B47 -> 1955 | C47: =CLIMATE!C47 -> Autumn | D47: — none — | F47: — none — | H47: 0 | I47: =ENGINE!$BO47 -> 300.58709 | J47: =ENGINE!$BK47 -> 30.77116 | K47: =ENGINE!$AY47 -> 98.0386 | L47: =ENGINE!$BG47 -> 95.43899 | M47: =ENGINE!$BH47 -> 108.76608 | N47: =ENGINE!$BI47 -> 90.637834 | O47: =INDEX(REGIONS!$B$7:$B$14,MATCH(MIN(ENGINE!$AY47:$BF47),ENGINE!$AY47:$BF47,0)) -> Horn of Africa | P47: =MIN(ENGINE!$AY47:$BF47) -> 78.72616 | Q47: =ENGINE!$BQ47 -> 0.44772021 | R47: =INDEX(ASSUMPTIONS!$B$28:$B$34,MATCH(ENGINE!$BQ47,ASSUMPTIONS!$A$28:$A$34,1)) -> Nothing. No one is looking. | S47: =IF(ENGINE!$BQ47>=200,"EXPOSED — run over",IF(ENGINE!$BO47<0,"INSOLVENT — programme suspended",IF(AND($A47>8,ENGINE!$BK47<=ASSUMPTIONS!$B$12+1),"Committee is asking what you are for","running"))) -> running

Sheet CLIMATE
A1: CLIMATE SUBSTRATE — natural background variability
A3: Natural driver values and per-region weather noise. In the real game these come from observed records (ONI/ENSO 1950-present, IOD, Atlantic SST, ERA5 reanalysis). Here they are a deterministic stand-in so runs are replayable. BLUE = editable input.
A6: Season | B6: Year | C6: Qtr | D6: ENSO (natural) | E6: IOD (natural) | F6: NATL (natural) | G6: GLOBAL (natural) | H6: noise: North American Plains | I6: noise: Black Sea Steppe | J6: noise: La Plata Basin | K6: noise: South Asia | L6: noise: Southeast Asia | M6: noise: Eastern Australia | N6: noise: Sahel | O6: noise: Horn of Africa
A8: 1 | B8: 1946 | C8: Winter | D8: 1.297 | E8: 0.371 | F8: 0.215 | G8: 0 | H8: 0.2 | I8: 0.224 | J8: 0.153 | K8: 0.013 | L8: 0.338 | M8: 0.149 | N8: -0.04 | O8: -0.225
A9: 2 | B9: 1946 | C9: Spring | D9: 1.188 | E9: 0.084 | F9: 0.074 | G9: 0 | H9: 0.039 | I9: 0.012 | J9: 0.408 | K9: 0.272 | L9: 0.129 | M9: -0.008 | N9: -0.135 | O9: -0.253
A10: 3 | B10: 1946 | C10: Summer | D10: 0.675 | E10: -0.667 | F10: 0.024 | G10: 0 | H10: 0.311 | I10: 0.284 | J10: 0.237 | K10: 0.194 | L10: 0.165 | M10: -0.351 | N10: -0.354 | O10: -0.348
A11: 4 | B11: 1946 | C11: Autumn | D11: 0.489 | E11: -1.236 | F11: 0.309 | G11: 0 | H11: 0.091 | I11: -0.198 | J11: 0.033 | K11: -0.214 | L11: 0.055 | M11: -0.163 | N11: -0.372 | O11: -0.074
A12: 5 | B12: 1947 | C12: Winter | D12: 0.702 | E12: -0.658 | F12: 0.547 | G12: 0 | H12: -0.329 | I12: -0.241 | J12: -0.129 | K12: -0.001 | L12: -0.362 | M12: -0.217 | N12: -0.068 | O12: -0.417
A13: 6 | B13: 1947 | C13: Spring | D13: 0.229 | E13: 0.532 | F13: 0.941 | G13: 0 | H13: -0.121 | I13: -0.057 | J13: 0.015 | K13: -0.409 | L13: -0.331 | M13: -0.252 | N13: -0.174 | O13: -0.096
A14: 7 | B14: 1947 | C14: Summer | D14: 0.048 | E14: 0.464 | F14: 0.385 | G14: 0 | H14: 0.057 | I14: -0.119 | J14: -0.298 | K14: 0.02 | L14: -0.162 | M14: -0.347 | N14: -0.032 | O14: -0.218
A15: 8 | B15: 1947 | C15: Autumn | D15: -0.85 | E15: 0.368 | F15: 0.602 | G15: 0 | H15: 0.061 | I15: -0.135 | J15: 0.168 | K15: -0.028 | L15: -0.224 | M15: 0.079 | N15: -0.117 | O15: 0.187
A16: 9 | B16: 1948 | C16: Winter | D16: -1.58 | E16: 0.727 | F16: 0.214 | G16: 0 | H16: 0.41 | I16: -0.045 | J16: 0.002 | K16: 0.051 | L16: 0.101 | M16: 0.153 | N16: 0.206 | O16: 0.26
A17: 10 | B17: 1948 | C17: Spring | D17: -1.107 | E17: 0.664 | F17: 0.327 | G17: 0 | H17: 0.43 | I17: 0.313 | J17: 0.189 | K17: 0.06 | L17: 0.429 | M17: 0.298 | N17: 0.167 | O17: 0.036
A18: 11 | B18: 1948 | C18: Summer | D18: -0.472 | E18: -0.06 | F18: 0.552 | G18: 0 | H18: -0.127 | I18: -0.034 | J18: 0.033 | K18: 0.085 | L18: 0.126 | M18: 0.161 | N18: 0.192 | O18: 0.22
A19: 12 | B19: 1948 | C19: Autumn | D19: -0.054 | E19: -0.885 | F19: 0.401 | G19: 0 | H19: 0.052 | I19: -0.058 | J19: 0.312 | K19: 0.161 | L19: -0.008 | M19: 0.311 | N19: 0.121 | O19: 0.424
... A47: 40 | B47: 1955 | C47: Autumn | D47: -0.249 | E47: -1.197 | F47: -0.122 | G47: 0 | H47: 0.116 | I47: -0.25 | J47: -0.287 | K47: 0.036 | L47: -0.254 | M47: -0.287 | N47: -0.006 | O47: 0.194

Sheet REGIONS
A1: REGION NODES
A3: Each region is a node on the teleconnection graph. SIGMA is the natural variance envelope — the width of 'could have happened anyway'. It widens every season (see ASSUMPTIONS) as the baseline destabilises, which is why deniability gets cheaper the longer you play.
A6: # | B6: Region | C6: Primary crop | D6: Global supply weight (%) | E6: Yield sensitivity | F6: Sigma (base envelope) | G6: Homeland?
A7: 1 | B7: North American Plains | C7: Wheat / Maize | D7: 20 | E7: 1 | F7: 0.8 | G7: YES
A8: 2 | B8: Black Sea Steppe | C8: Wheat | D8: 16 | E8: 1.1 | F8: 0.9
A9: 3 | B9: La Plata Basin | C9: Soy / Maize | D9: 15 | E9: 1 | F9: 0.9
A10: 4 | B10: South Asia | C10: Rice / Wheat | D10: 18 | E10: 1.2 | F10: 0.7
A11: 5 | B11: Southeast Asia | C11: Rice | D11: 12 | E11: 1.1 | F11: 0.7
A12: 6 | B12: Eastern Australia | C12: Wheat | D12: 7 | E12: 1.3 | F12: 1.1
A13: 7 | B13: Sahel | C13: Millet | D13: 6 | E13: 1.4 | F13: 1.2
A14: 8 | B14: Horn of Africa | C14: Maize | D14: 6 | E14: 1.4 | F14: 1.2
B16: TOTAL | D16: =SUM(D7:D14) -> 100

Sheet GRAPH
A1: TELECONNECTION GRAPH — coefficients and lags
A3: Edges of the causal graph. Coefficient = how strongly a driver moves a region's moisture anomaly. Lag = seasons before it lands. Relationships are drawn from real climatology (El Nino drying Australia and SE Asia, warm North Atlantic wetting the Sahel, IOD driving the Horn). In the full game the player begins seeing roughly 20% of these edges and reveals the rest through research.
A7: COEFFICIENTS
B8: North American Plains | C8: Black Sea Steppe | D8: La Plata Basin | E8: South Asia | F8: Southeast Asia | G8: Eastern Australia | H8: Sahel | I8: Horn of Africa
A9: ENSO | B9: 0.2 | C9: -0.1 | D9: 0.5 | E9: -0.5 | F9: -0.7 | G9: -0.9 | H9: -0.3 | I9: 0.6
A10: IOD | B10: 0 | C10: 0 | D10: 0 | E10: 0.3 | F10: -0.2 | G10: -0.6 | H10: 0.1 | I10: 0.8
A11: NATL | B11: -0.3 | C11: -0.2 | D11: 0 | E11: 0.2 | F11: 0 | G11: 0 | H11: 0.7 | I11: 0.2
A12: GLOBAL | B12: -0.45 | C12: -0.4 | D12: -0.35 | E12: -0.5 | F12: -0.4 | G12: -0.3 | H12: -0.55 | I12: -0.5
A15: LAGS (seasons)
B16: North American Plains | C16: Black Sea Steppe | D16: La Plata Basin | E16: South Asia | F16: Southeast Asia | G16: Eastern Australia | H16: Sahel | I16: Horn of Africa
A17: ENSO | B17: 2 | C17: 3 | D17: 2 | E17: 1 | F17: 1 | G17: 1 | H17: 2 | I17: 2
A18: IOD | B18: 1 | C18: 1 | D18: 1 | E18: 1 | F18: 1 | G18: 1 | H18: 2 | I18: 1
A19: NATL | B19: 2 | C19: 3 | D19: 1 | E19: 2 | F19: 1 | G19: 1 | H19: 2 | I19: 3
A20: GLOBAL | B20: 3 | C20: 3 | D20: 3 | E20: 4 | F20: 3 | G20: 3 | H20: 4 | I20: 4

Sheet CAPABILITIES
A1: CAPABILITY CATALOGUE
A3: The tools. SIGNATURE is attribution added per use, before the envelope multiplier — an operation that produces an outcome far outside a region's natural range costs far more than its base signature. DISPLACES is the energy ledger: what you move has to surface somewhere else, later.
A6: Capability | B6: Type | C6: Fixed target | D6: Magnitude | E6: Lag (seasons) | F6: Signature | G6: Cost | H6: Displaces to | I6: Disp. factor | J6: Disp. extra lag | K6: Needs drought | L6: Resilience +
A7: — none — | B7: NONE | D7: 0 | E7: 0 | F7: 0 | G7: 0 | I7: 0 | J7: 0 | K7: N | L7: 0
A8: Cloud Seeding | B8: REGION | D8: 0.7 | E8: 1 | F8: 2 | G8: 6 | I8: 0 | J8: 0 | K8: N | L8: 0
A9: Watershed Interference | B9: REGION | D9: -0.9 | E9: 2 | F9: 4 | G9: 14 | I9: 0 | J9: 0 | K9: N | L9: 0
A10: Fire Enablement | B10: REGION | D10: -1.2 | E10: 1 | F10: 2 | G10: 9 | I10: 0 | J10: 0 | K10: Y | L10: 0
A11: Adaptation Investment | B11: REGION | D11: 0 | E11: 0 | F11: 0 | G11: 18 | I11: 0 | J11: 0 | K11: N | L11: 12
A12: Ocean Thermal Forcing | B12: DRIVER | C12: NATL | D12: 1.1 | E12: 4 | F12: 7 | G12: 26 | H12: IOD | I12: -0.4 | J12: 4 | K12: N | L12: 0
A13: Stratospheric Aerosol Inj. | B13: DRIVER | C13: GLOBAL | D13: 1.3 | E13: 3 | F13: 9 | G13: 32 | H13: NATL | I13: -0.5 | J13: 4 | K13: N | L13: 0
A14: ENSO Forcing | B14: DRIVER | C14: ENSO | D14: 1.6 | E14: 6 | F14: 12 | G14: 45 | H14: NATL | I14: -0.6 | J14: 5 | K14: N | L14: 0
A15: Ionospheric Coupling [T3] | B15: REGION | D15: -2.5 | E15: 1 | F15: 30 | G15: 60 | I15: 0 | J15: 0 | K15: N | L15: 0

Sheet ASSUMPTIONS
A1: TUNING ASSUMPTIONS
A3: Every number the model uses that is not a region, edge, or capability. These are the dials. All are guesses — that is what the prototype is for.
A6: Assumption | B6: Value | C6: Note
A7: Drought yield penalty per unit anomaly | B7: 14 | C7: Yield lost per 1.0 of negative moisture anomaly, x region sensitivity
A8: Flood yield penalty per unit anomaly | B8: 8 | C8: Applied only above +1.2 anomaly
A9: Flood threshold | B9: 1.2 | C9: Anomaly above which excess water starts destroying yield
A10: Price elasticity exponent | B10: 1.8 | C10: Global price = 100 x (baseline supply / actual supply) ^ this
A11: Homeland revenue scale | B11: 0.85 | C11: Converts yield x price into budget units
A12: Mandate base | B12: 28 | C12: Political capital floor with a calm world
A13: Mandate per unit global severity | B13: 42 | C13: THE DARK ENGINE: fear funds you
A14: Mandate cap | B14: 100
A15: Budget from revenue | B15: 0.12 | C15: Share of homeland revenue reaching the programme
A16: Budget from mandate | B16: 0.9 | C16: Appropriation driven by perceived threat
A17: Containment efficiency | B17: 0.9 | C17: Dossier points removed per unit of containment spend
A18: Dossier decay per season | B18: 0.04 | C18: Institutional forgetting
A19: Envelope widening per season | B19: 0.006 | C19: Sigma grows as the baseline destabilises
A20: Dry precondition threshold | B20: -0.5 | C20: Prior-season anomaly below this makes Fire Enablement fully effective
A21: Dry precondition penalty | B21: 0.25 | C21: Effectiveness multiplier when the precondition is unmet
A22: Envelope multiplier weight | B22: 0.8 | C22: How hard an outside-envelope outcome amplifies signature
A23: Programme overhead per season | B23: 32 | C23: Fixed running cost. A calm world barely covers it — this is the obsolescence pressure
A24: Severity threshold (x sigma) | B24: 0.75 | C24: Anomaly must exceed this fraction of the envelope to read as a disaster
A25: Starting treasury | B25: 90 | C25: Opening balance, 1946
A26: EXPOSURE LADDER
A27: Dossier at or above | B27: What you are told
A28: 0 | B28: Nothing. No one is looking.
A29: 25 | B29: A graduate student publishes an odd residual. Nobody cites it.
A30: 50 | B30: A wire journalist files an inquiry with the ministry.
A31: 80 | B31: An academic consortium announces an attribution study.
A32: 115 | B32: A rival service names your programme in a classified brief.
A33: 155 | B33: Formal international investigation. Inspectors requested.
A34: 200 | B34: EXPOSED — the record is public and it is yours.

Sheet ENGINE
A1: RESOLUTION ENGINE — do not edit; everything here is computed
A3: Enter operations on PLAY. This sheet propagates them through the graph, resolves yields, prices, budget and attribution.
A7: t | B7: Year | C7: OpA type | D7: OpA target | E7: OpA mag | F7: OpA lag | G7: OpA sig | H7: OpA cost | I7: OpA disp tgt | J7: OpA disp mag | K7: OpA disp lag | L7: OpA resil | M7: OpB type | N7: OpB target | O7: OpB mag | P7: OpB lag | Q7: OpB sig | R7: OpB cost | S7: OpB disp tgt | T7: OpB disp mag | U7: OpB disp lag | V7: OpB resil | W7: ENSO total | X7: IOD total | Y7: NATL total | Z7: GLOBAL total | AA7: Anom: North American Plains | AB7: Anom: Black Sea Steppe | AC7: Anom: La Plata Basin | AD7: Anom: South Asia | AE7: Anom: Southeast Asia | AF7: Anom: Eastern Australia | AG7: Anom: Sahel | AH7: Anom: Horn of Africa | AI7: Sigma: North American Plains | AJ7: Sigma: Black Sea Steppe | AK7: Sigma: La Plata Basin | AL7: Sigma: South Asia | AM7: Sigma: Southeast Asia | AN7: Sigma: Eastern Australia | AO7: Sigma: Sahel | AP7: Sigma: Horn of Africa | AQ7: Resil: North American Plains | AR7: Resil: Black Sea Steppe | AS7: Resil: La Plata Basin | AT7: Resil: South Asia | AU7: Resil: Southeast Asia | AV7: Resil: Eastern Australia | AW7: Resil: Sahel | AX7: Resil: Horn of Africa | AY7: Yield: North American Plains | AZ7: Yield: Black Sea Steppe | BA7: Yield: La Plata Basin | BB7: Yield: South Asia | BC7: Yield: Southeast Asia | BD7: Yield: Eastern Australia | BE7: Yield: Sahel | BF7: Yield: Horn of Africa | BG7: Global supply | BH7: Price index | BI7: Homeland revenue | BJ7: Global severity | BK7: Mandate | BL7: Ops spend | BM7: Containment | BN7: Budget in | BO7: Treasury | BP7: Attribution + | BQ7: Dossier
A8: 1 | B8: =CLIMATE!B8 -> 1946 | C8: =IFERROR(INDEX(CAPABILITIES!$B$7:$B$15,MATCH(PLAY!$D8,CAPABILITIES!$A$7:$A$15,0)),"NONE") -> REGION | D8: =IFERROR(IF(INDEX(CAPABILITIES!$B$7:$B$15,MATCH(PLAY!$D8,CAPABILITIES!$A$7:$A$15,0))="DRIVER",INDEX(CAPABILITIES!$C$7:$C$15,MATCH(PLAY!$D8,CAPABILITIES!$A$7:$A$15,0)),PLAY!$E8),"") -> Sahel | E8: =IFERROR(INDEX(CAPABILITIES!$D$7:$D$15,MATCH(PLAY!$D8,CAPABILITIES!$A$7:$A$15,0))*IF(INDEX(CAPABILITIES!$K$7:$K$15,MATCH(PLAY!$D8,CAPABILITIES!$A$7:$A$15,0))="Y",IF(0<ASSUMPTIONS!$B$20,1,ASSUMPTIONS!$B$21),1),0) -> 0.7 | F8: =IFERROR(INDEX(CAPABILITIES!$E$7:$E$15,MATCH(PLAY!$D8,CAPABILITIES!$A$7:$A$15,0)),0) -> 1 | G8: =IFERROR(INDEX(CAPABILITIES!$F$7:$F$15,MATCH(PLAY!$D8,CAPABILITIES!$A$7:$A$15,0)),0) -> 2 | H8: =IFERROR(INDEX(CAPABILITIES!$G$7:$G$15,MATCH(PLAY!$D8,CAPABILITIES!$A$7:$A$15,0)),0) -> 6 | I8: =IFERROR(INDEX(CAPABILITIES!$H$7:$H$15,MATCH(PLAY!$D8,CAPABILITIES!$A$7:$A$15,0)),"") -> 0 | J8: =IFERROR(INDEX(CAPABILITIES!$D$7:$D$15,MATCH(PLAY!$D8,CAPABILITIES!$A$7:$A$15,0))*INDEX(CAPABILITIES!$I$7:$I$15,MATCH(PLAY!$D8,CAPABILITIES!$A$7:$A$15,0)),0) -> 0 | K8: =IFERROR(INDEX(CAPABILITIES!$E$7:$E$15,MATCH(PLAY!$D8,CAPABILITIES!$A$7:$A$15,0))+INDEX(CAPABILITIES!$J$7:$J$15,MATCH(PLAY!$D8,CAPABILITIES!$A$7:$A$15,0)),0) -> 1 | L8: =IFERROR(INDEX(CAPABILITIES!$L$7:$L$15,MATCH(PLAY!$D8,CAPABILITIES!$A$7:$A$15,0)),0) -> 0 | M8: =IFERROR(INDEX(CAPABILITIES!$B$7:$B$15,MATCH(PLAY!$F8,CAPABILITIES!$A$7:$A$15,0)),"NONE") -> NONE | N8: =IFERROR(IF(INDEX(CAPABILITIES!$B$7:$B$15,MATCH(PLAY!$F8,CAPABILITIES!$A$7:$A$15,0))="DRIVER",INDEX(CAPABILITIES!$C$7:$C$15,MATCH(PLAY!$F8,CAPABILITIES!$A$7:$A$15,0)),PLAY!$G8),"") -> 0 | O8: =IFERROR(INDEX(CAPABILITIES!$D$7:$D$15,MATCH(PLAY!$F8,CAPABILITIES!$A$7:$A$15,0))*IF(INDEX(CAPABILITIES!$K$7:$K$15,MATCH(PLAY!$F8,CAPABILITIES!$A$7:$A$15,0))="Y",IF(0<ASSUMPTIONS!$B$20,1,ASSUMPTIONS!$B$21),1),0) -> 0 | P8: =IFERROR(INDEX(CAPABILITIES!$E$7:$E$15,MATCH(PLAY!$F8,CAPABILITIES!$A$7:$A$15,0)),0) -> 0 | Q8: =IFERROR(INDEX(CAPABILITIES!$F$7:$F$15,MATCH(PLAY!$F8,CAPABILITIES!$A$7:$A$15,0)),0) -> 0 | R8: =IFERROR(INDEX(CAPABILITIES!$G$7:$G$15,MATCH(PLAY!$F8,CAPABILITIES!$A$7:$A$15,0)),0) -> 0 | S8: =IFERROR(INDEX(CAPABILITIES!$H$7:$H$15,MATCH(PLAY!$F8,CAPABILITIES!$A$7:$A$15,0)),"") -> 0 | T8: =IFERROR(INDEX(CAPABILITIES!$D$7:$D$15,MATCH(PLAY!$F8,CAPABILITIES!$A$7:$A$15,0))*INDEX(CAPABILITIES!$I$7:$I$15,MATCH(PLAY!$F8,CAPABILITIES!$A$7:$A$15,0)),0) -> 0 | U8: =IFERROR(INDEX(CAPABILITIES!$E$7:$E$15,MATCH(PLAY!$F8,CAPABILITIES!$A$7:$A$15,0))+INDEX(CAPABILITIES!$J$7:$J$15,MATCH(PLAY!$F8,CAPABILITIES!$A$7:$A$15,0)),0) -> 0 | V8: =IFERROR(INDEX(CAPABILITIES!$L$7:$L$15,MATCH(PLAY!$F8,CAPABILITIES!$A$7:$A$15,0)),0) -> 0 | W8: =CLIMATE!D8 -> 1.297 | X8: =CLIMATE!E8 -> 0.371 | Y8: =CLIMATE!F8 -> 0.215 | Z8: =CLIMATE!G8 -> 0 | AA8: =CLIMATE!H8+IFERROR(INDEX($W$8:$W$47,$A8-GRAPH!B17),0)*GRAPH!B9+IFERROR(INDEX($X$8:$X$47,$A8-GRAPH!B18),0)*GRAPH!B10+IFERROR(INDEX($Y$8:$Y$47,$A8-GRAPH!B19),0)*GRAPH!B11+IFERROR(INDEX($Z$8:$Z$47,$A8-GRAPH!B20),0)*GRAPH!B12 -> 0.2 | AB8: =CLIMATE!I8+IFERROR(INDEX($W$8:$W$47,$A8-GRAPH!C17),0)*GRAPH!C9+IFERROR(INDEX($X$8:$X$47,$A8-GRAPH!C18),0)*GRAPH!C10+IFERROR(INDEX($Y$8:$Y$47,$A8-GRAPH!C19),0)*GRAPH!C11+IFERROR(INDEX($Z$8:$Z$47,$A8-GRAPH!C20),0)*GRAPH!C12 -> 0.224 | AC8: =CLIMATE!J8+IFERROR(INDEX($W$8:$W$47,$A8-GRAPH!D17),0)*GRAPH!D9+IFERROR(INDEX($X$8:$X$47,$A8-GRAPH!D18),0)*GRAPH!D10+IFERROR(INDEX($Y$8:$Y$47,$A8-GRAPH!D19),0)*GRAPH!D11+IFERROR(INDEX($Z$8:$Z$47,$A8-GRAPH!D20),0)*GRAPH!D12 -> 0.153 | AD8: =CLIMATE!K8+IFERROR(INDEX($W$8:$W$47,$A8-GRAPH!E17),0)*GRAPH!E9+IFERROR(INDEX($X$8:$X$47,$A8-GRAPH!E18),0)*GRAPH!E10+IFERROR(INDEX($Y$8:$Y$47,$A8-GRAPH!E19),0)*GRAPH!E11+IFERROR(INDEX($Z$8:$Z$47,$A8-GRAPH!E20),0)*GRAPH!E12 -> -0.5242 | AE8: =CLIMATE!L8+IFERROR(INDEX($W$8:$W$47,$A8-GRAPH!F17),0)*GRAPH!F9+IFERROR(INDEX($X$8:$X$47,$A8-GRAPH!F18),0)*GRAPH!F10+IFERROR(INDEX($Y$8:$Y$47,$A8-GRAPH!F19),0)*GRAPH!F11+IFERROR(INDEX($Z$8:$Z$47,$A8-GRAPH!F20),0)*GRAPH!F12 -> -0.6441 | AF8: =CLIMATE!M8+IFERROR(INDEX($W$8:$W$47,$A8-GRAPH!G17),0)*GRAPH!G9+IFERROR(INDEX($X$8:$X$47,$A8-GRAPH!G18),0)*GRAPH!G10+IFERROR(INDEX($Y$8:$Y$47,$A8-GRAPH!G19),0)*GRAPH!G11+IFERROR(INDEX($Z$8:$Z$47,$A8-GRAPH!G20),0)*GRAPH!G12 -> -1.2409 | AG8: =CLIMATE!N8+IFERROR(INDEX($W$8:$W$47,$A8-GRAPH!H17),0)*GRAPH!H9+IFERROR(INDEX($X$8:$X$47,$A8-GRAPH!H18),0)*GRAPH!H10+IFERROR(INDEX($Y$8:$Y$47,$A8-GRAPH!H19),0)*GRAPH!H11+IFERROR(INDEX($Z$8:$Z$47,$A8-GRAPH!H20),0)*GRAPH!H12 -> -0.04 | AH8: =CLIMATE!O8+IFERROR(INDEX($W$8:$W$47,$A8-GRAPH!I17),0)*GRAPH!I9+IFERROR(INDEX($X$8:$X$47,$A8-GRAPH!I18),0)*GRAPH!I10+IFERROR(INDEX($Y$8:$Y$47,$A8-GRAPH!I19),0)*GRAPH!I11+IFERROR(INDEX($Z$8:$Z$47,$A8-GRAPH!I20),0)*GRAPH!I12 -> 0.0718 | AI8: =REGIONS!$F$7*(1+ASSUMPTIONS!$B$19*$A8) -> 0.8048 | AJ8: =REGIONS!$F$8*(1+ASSUMPTIONS!$B$19*$A8) -> 0.9054 | AK8: =REGIONS!$F$9*(1+ASSUMPTIONS!$B$19*$A8) -> 0.9054 | AL8: =REGIONS!$F$10*(1+ASSUMPTIONS!$B$19*$A8) -> 0.7042 | AM8: =REGIONS!$F$11*(1+ASSUMPTIONS!$B$19*$A8) -> 0.7042 | AN8: =REGIONS!$F$12*(1+ASSUMPTIONS!$B$19*$A8) -> 1.1066 | AO8: =REGIONS!$F$13*(1+ASSUMPTIONS!$B$19*$A8) -> 1.2072 | AP8: =REGIONS!$F$14*(1+ASSUMPTIONS!$B$19*$A8) -> 1.2072 | AQ8: =SUMPRODUCT(($D$8:$D$47=REGIONS!$B$7)*($A$8:$A$47<=$A8)*$L$8:$L$47)+SUMPRODUCT(($N$8:$N$47=REGIONS!$B$7)*($A$8:$A$47<=$A8)*$V$8:$V$47) -> 0 | AR8: =SUMPRODUCT(($D$8:$D$47=REGIONS!$B$8)*($A$8:$A$47<=$A8)*$L$8:$L$47)+SUMPRODUCT(($N$8:$N$47=REGIONS!$B$8)*($A$8:$A$47<=$A8)*$V$8:$V$47) -> 0 | AS8: =SUMPRODUCT(($D$8:$D$47=REGIONS!$B$9)*($A$8:$A$47<=$A8)*$L$8:$L$47)+SUMPRODUCT(($N$8:$N$47=REGIONS!$B$9)*($A$8:$A$47<=$A8)*$V$8:$V$47) -> 0 | AT8: =SUMPRODUCT(($D$8:$D$47=REGIONS!$B$10)*($A$8:$A$47<=$A8)*$L$8:$L$47)+SUMPRODUCT(($N$8:$N$47=REGIONS!$B$10)*($A$8:$A$47<=$A8)*$V$8:$V$47) -> 0 | AU8: =SUMPRODUCT(($D$8:$D$47=REGIONS!$B$11)*($A$8:$A$47<=$A8)*$L$8:$L$47)+SUMPRODUCT(($N$8:$N$47=REGIONS!$B$11)*($A$8:$A$47<=$A8)*$V$8:$V$47) -> 0 | AV8: =SUMPRODUCT(($D$8:$D$47=REGIONS!$B$12)*($A$8:$A$47<=$A8)*$L$8:$L$47)+SUMPRODUCT(($N$8:$N$47=REGIONS!$B$12)*($A$8:$A$47<=$A8)*$V$8:$V$47) -> 0 | AW8: =SUMPRODUCT(($D$8:$D$47=REGIONS!$B$13)*($A$8:$A$47<=$A8)*$L$8:$L$47)+SUMPRODUCT(($N$8:$N$47=REGIONS!$B$13)*($A$8:$A$47<=$A8)*$V$8:$V$47) -> 0 | AX8: =SUMPRODUCT(($D$8:$D$47=REGIONS!$B$14)*($A$8:$A$47<=$A8)*$L$8:$L$47)+SUMPRODUCT(($N$8:$N$47=REGIONS!$B$14)*($A$8:$A$47<=$A8)*$V$8:$V$47) -> 0 | AY8: =MAX(0,MIN(135,100-(MAX(0,-$AA8)*REGIONS!$E$7*ASSUMPTIONS!$B$7+MAX(0,$AA8-ASSUMPTIONS!$B$9)*REGIONS!$E$7*ASSUMPTIONS!$B$8)*(1-$AQ8/100))) -> 100 | AZ8: =MAX(0,MIN(135,100-(MAX(0,-$AB8)*REGIONS!$E$8*ASSUMPTIONS!$B$7+MAX(0,$AB8-ASSUMPTIONS!$B$9)*REGIONS!$E$8*ASSUMPTIONS!$B$8)*(1-$AR8/100))) -> 100 | BA8: =MAX(0,MIN(135,100-(MAX(0,-$AC8)*REGIONS!$E$9*ASSUMPTIONS!$B$7+MAX(0,$AC8-ASSUMPTIONS!$B$9)*REGIONS!$E$9*ASSUMPTIONS!$B$8)*(1-$AS8/100))) -> 100 | BB8: =MAX(0,MIN(135,100-(MAX(0,-$AD8)*REGIONS!$E$10*ASSUMPTIONS!$B$7+MAX(0,$AD8-ASSUMPTIONS!$B$9)*REGIONS!$E$10*ASSUMPTIONS!$B$8)*(1-$AT8/100))) -> 91.19344 | BC8: =MAX(0,MIN(135,100-(MAX(0,-$AE8)*REGIONS!$E$11*ASSUMPTIONS!$B$7+MAX(0,$AE8-ASSUMPTIONS!$B$9)*REGIONS!$E$11*ASSUMPTIONS!$B$8)*(1-$AU8/100))) -> 90.08086 | BD8: =MAX(0,MIN(135,100-(MAX(0,-$AF8)*REGIONS!$E$12*ASSUMPTIONS!$B$7+MAX(0,$AF8-ASSUMPTIONS!$B$9)*REGIONS!$E$12*ASSUMPTIONS!$B$8)*(1-$AV8/100))) -> 77.41562 | BE8: =MAX(0,MIN(135,100-(MAX(0,-$AG8)*REGIONS!$E$13*ASSUMPTIONS!$B$7+MAX(0,$AG8-ASSUMPTIONS!$B$9)*REGIONS!$E$13*ASSUMPTIONS!$B$8)*(1-$AW8/100))) -> 99.216 | BF8: =MAX(0,MIN(135,100-(MAX(0,-$AH8)*REGIONS!$E$14*ASSUMPTIONS!$B$7+MAX(0,$AH8-ASSUMPTIONS!$B$9)*REGIONS!$E$14*ASSUMPTIONS!$B$8)*(1-$AX8/100))) -> 100 | BG8: =$AY8*REGIONS!$D$7/100+$AZ8*REGIONS!$D$8/100+$BA8*REGIONS!$D$9/100+$BB8*REGIONS!$D$10/100+$BC8*REGIONS!$D$11/100+$BD8*REGIONS!$D$12/100+$BE8*REGIONS!$D$13/100+$BF8*REGIONS!$D$14/100 -> 95.596576 | BH8: =100*(100/MAX(1,$BG8))^ASSUMPTIONS!$B$10 -> 108.44357 | BI8: =$AY8*$BH8/100*ASSUMPTIONS!$B$11 -> 92.177032 | BJ8: =MAX(0,ABS($AA8)-$AI8*ASSUMPTIONS!$B$24)*REGIONS!$D$7/100+MAX(0,ABS($AB8)-$AJ8*ASSUMPTIONS!$B$24)*REGIONS!$D$8/100+MAX(0,ABS($AC8)-$AK8*ASSUMPTIONS!$B$24)*REGIONS!$D$9/100+MAX(0,ABS($AD8)-$AL8*ASSUMPTIONS!$B$24)*REGIONS!$D$10/100+MAX(0,ABS($AE8)-$AM8*ASSUMPTIONS!$B$24)*REGIONS!$D$11/100+MAX(0,ABS($AF8)-$AN8*ASSUMPTIONS!$B$24)*REGIONS!$D$12/100+MAX(0,ABS($AG8)-$AO8*ASSUMPTIONS!$B$24)*REGIONS!$D$13/100+MAX(0,ABS($AH8)-$AP8*ASSUMPTIONS!$B$24)*REGIONS!$D$14/100 -> 0.0426805 | BK8: =MIN(ASSUMPTIONS!$B$14,ASSUMPTIONS!$B$12+$BJ8*ASSUMPTIONS!$B$13) -> 29.792581 | BL8: =$H8+$R8 -> 6 | BM8: =PLAY!$H8 -> 0 | BN8: =$BI8*ASSUMPTIONS!$B$15+$BK8*ASSUMPTIONS!$B$16 -> 37.874567 | BO8: =ASSUMPTIONS!$B$25+$BN8-$BL8-$BM8-ASSUMPTIONS!$B$23 -> 89.874567 | BP8: =(0+0)*(1+ASSUMPTIONS!$B$22*(MAX(0,ABS($AA8)/$AI8-1)+MAX(0,ABS($AB8)/$AJ8-1)+MAX(0,ABS($AC8)/$AK8-1)+MAX(0,ABS($AD8)/$AL8-1)+MAX(0,ABS($AE8)/$AM8-1)+MAX(0,ABS($AF8)/$AN8-1)+MAX(0,ABS($AG8)/$AO8-1)+MAX(0,ABS($AH8)/$AP8-1))/8) -> 0 | BQ8: =MAX(0,0*(1-ASSUMPTIONS!$B$18)+$BP8-$BM8*ASSUMPTIONS!$B$17) -> 0
A9: 2 | B9: =CLIMATE!B9 -> 1946 | C9: =IFERROR(INDEX(CAPABILITIES!$B$7:$B$15,MATCH(PLAY!$D9,CAPABILITIES!$A$7:$A$15,0)),"NONE") -> NONE | D9: =IFERROR(IF(INDEX(CAPABILITIES!$B$7:$B$15,MATCH(PLAY!$D9,CAPABILITIES!$A$7:$A$15,0))="DRIVER",INDEX(CAPABILITIES!$C$7:$C$15,MATCH(PLAY!$D9,CAPABILITIES!$A$7:$A$15,0)),PLAY!$E9),"") -> 0 | E9: =IFERROR(INDEX(CAPABILITIES!$D$7:$D$15,MATCH(PLAY!$D9,CAPABILITIES!$A$7:$A$15,0))*IF(INDEX(CAPABILITIES!$K$7:$K$15,MATCH(PLAY!$D9,CAPABILITIES!$A$7:$A$15,0))="Y",IF(IFERROR(INDEX($AA8:$AH8,MATCH(PLAY!$E9,REGIONS!$B$7:$B$14,0)),0)<ASSUMPTIONS!$B$20,1,ASSUMPTIONS!$B$21),1),0) -> 0 | F9: =IFERROR(INDEX(CAPABILITIES!$E$7:$E$15,MATCH(PLAY!$D9,CAPABILITIES!$A$7:$A$15,0)),0) -> 0 | G9: =IFERROR(INDEX(CAPABILITIES!$F$7:$F$15,MATCH(PLAY!$D9,CAPABILITIES!$A$7:$A$15,0)),0) -> 0 | H9: =IFERROR(INDEX(CAPABILITIES!$G$7:$G$15,MATCH(PLAY!$D9,CAPABILITIES!$A$7:$A$15,0)),0) -> 0 | I9: =IFERROR(INDEX(CAPABILITIES!$H$7:$H$15,MATCH(PLAY!$D9,CAPABILITIES!$A$7:$A$15,0)),"") -> 0 | J9: =IFERROR(INDEX(CAPABILITIES!$D$7:$D$15,MATCH(PLAY!$D9,CAPABILITIES!$A$7:$A$15,0))*INDEX(CAPABILITIES!$I$7:$I$15,MATCH(PLAY!$D9,CAPABILITIES!$A$7:$A$15,0)),0) -> 0 | K9: =IFERROR(INDEX(CAPABILITIES!$E$7:$E$15,MATCH(PLAY!$D9,CAPABILITIES!$A$7:$A$15,0))+INDEX(CAPABILITIES!$J$7:$J$15,MATCH(PLAY!$D9,CAPABILITIES!$A$7:$A$15,0)),0) -> 0 | L9: =IFERROR(INDEX(CAPABILITIES!$L$7:$L$15,MATCH(PLAY!$D9,CAPABILITIES!$A$7:$A$15,0)),0) -> 0 | M9: =IFERROR(INDEX(CAPABILITIES!$B$7:$B$15,MATCH(PLAY!$F9,CAPABILITIES!$A$7:$A$15,0)),"NONE") -> NONE | N9: =IFERROR(IF(INDEX(CAPABILITIES!$B$7:$B$15,MATCH(PLAY!$F9,CAPABILITIES!$A$7:$A$15,0))="DRIVER",INDEX(CAPABILITIES!$C$7:$C$15,MATCH(PLAY!$F9,CAPABILITIES!$A$7:$A$15,0)),PLAY!$G9),"") -> 0 | O9: =IFERROR(INDEX(CAPABILITIES!$D$7:$D$15,MATCH(PLAY!$F9,CAPABILITIES!$A$7:$A$15,0))*IF(INDEX(CAPABILITIES!$K$7:$K$15,MATCH(PLAY!$F9,CAPABILITIES!$A$7:$A$15,0))="Y",IF(IFERROR(INDEX($AA8:$AH8,MATCH(PLAY!$G9,REGIONS!$B$7:$B$14,0)),0)<ASSUMPTIONS!$B$20,1,ASSUMPTIONS!$B$21),1),0) -> 0 | P9: =IFERROR(INDEX(CAPABILITIES!$E$7:$E$15,MATCH(PLAY!$F9,CAPABILITIES!$A$7:$A$15,0)),0) -> 0 | Q9: =IFERROR(INDEX(CAPABILITIES!$F$7:$F$15,MATCH(PLAY!$F9,CAPABILITIES!$A$7:$A$15,0)),0) -> 0 | R9: =IFERROR(INDEX(CAPABILITIES!$G$7:$G$15,MATCH(PLAY!$F9,CAPABILITIES!$A$7:$A$15,0)),0) -> 0 | S9: =IFERROR(INDEX(CAPABILITIES!$H$7:$H$15,MATCH(PLAY!$F9,CAPABILITIES!$A$7:$A$15,0)),"") -> 0 | T9: =IFERROR(INDEX(CAPABILITIES!$D$7:$D$15,MATCH(PLAY!$F9,CAPABILITIES!$A$7:$A$15,0))*INDEX(CAPABILITIES!$I$7:$I$15,MATCH(PLAY!$F9,CAPABILITIES!$A$7:$A$15,0)),0) -> 0 | U9: =IFERROR(INDEX(CAPABILITIES!$E$7:$E$15,MATCH(PLAY!$F9,CAPABILITIES!$A$7:$A$15,0))+INDEX(CAPABILITIES!$J$7:$J$15,MATCH(PLAY!$F9,CAPABILITIES!$A$7:$A$15,0)),0) -> 0 | V9: =IFERROR(INDEX(CAPABILITIES!$L$7:$L$15,MATCH(PLAY!$F9,CAPABILITIES!$A$7:$A$15,0)),0) -> 0 | W9: =CLIMATE!D9+SUMPRODUCT(($D$8:$D$8="ENSO")*($F$8:$F$8+$A$8:$A$8=$A9)*$E$8:$E$8)+SUMPRODUCT(($I$8:$I$8="ENSO")*($K$8:$K$8+$A$8:$A$8=$A9)*$J$8:$J$8)+SUMPRODUCT(($N$8:$N$8="ENSO")*($P$8:$P$8+$A$8:$A$8=$A9)*$O$8:$O$8)+SUMPRODUCT(($S$8:$S$8="ENSO")*($U$8:$U$8+$A$8:$A$8=$A9)*$T$8:$T$8) -> 1.188 | X9: =CLIMATE!E9+SUMPRODUCT(($D$8:$D$8="IOD")*($F$8:$F$8+$A$8:$A$8=$A9)*$E$8:$E$8)+SUMPRODUCT(($I$8:$I$8="IOD")*($K$8:$K$8+$A$8:$A$8=$A9)*$J$8:$J$8)+SUMPRODUCT(($N$8:$N$8="IOD")*($P$8:$P$8+$A$8:$A$8=$A9)*$O$8:$O$8)+SUMPRODUCT(($S$8:$S$8="IOD")*($U$8:$U$8+$A$8:$A$8=$A9)*$T$8:$T$8) -> 0.084 | Y9: =CLIMATE!F9+SUMPRODUCT(($D$8:$D$8="NATL")*($F$8:$F$8+$A$8:$A$8=$A9)*$E$8:$E$8)+SUMPRODUCT(($I$8:$I$8="NATL")*($K$8:$K$8+$A$8:$A$8=$A9)*$J$8:$J$8)+SUMPRODUCT(($N$8:$N$8="NATL")*($P$8:$P$8+$A$8:$A$8=$A9)*$O$8:$O$8)+SUMPRODUCT(($S$8:$S$8="NATL")*($U$8:$U$8+$A$8:$A$8=$A9)*$T$8:$T$8) -> 0.074 | Z9: =CLIMATE!G9+SUMPRODUCT(($D$8:$D$8="GLOBAL")*($F$8:$F$8+$A$8:$A$8=$A9)*$E$8:$E$8)+SUMPRODUCT(($I$8:$I$8="GLOBAL")*($K$8:$K$8+$A$8:$A$8=$A9)*$J$8:$J$8)+SUMPRODUCT(($N$8:$N$8="GLOBAL")*($P$8:$P$8+$A$8:$A$8=$A9)*$O$8:$O$8)+SUMPRODUCT(($S$8:$S$8="GLOBAL")*($U$8:$U$8+$A$8:$A$8=$A9)*$T$8:$T$8) -> 0 | AA9: =CLIMATE!H9+IFERROR(INDEX($W$8:$W$47,$A9-GRAPH!B17),0)*GRAPH!B9+IFERROR(INDEX($X$8:$X$47,$A9-GRAPH!B18),0)*GRAPH!B10+IFERROR(INDEX($Y$8:$Y$47,$A9-GRAPH!B19),0)*GRAPH!B11+IFERROR(INDEX($Z$8:$Z$47,$A9-GRAPH!B20),0)*GRAPH!B12+SUMPRODUCT(($D$8:$D$8=REGIONS!$B$7)*($F$8:$F$8+$A$8:$A$8=$A9)*$E$8:$E$8)+SUMPRODUCT(($N$8:$N$8=REGIONS!$B$7)*($P$8:$P$8+$A$8:$A$8=$A9)*$O$8:$O$8) -> 0.2544 | AB9: =CLIMATE!I9+IFERROR(INDEX($W$8:$W$47,$A9-GRAPH!C17),0)*GRAPH!C9+IFERROR(INDEX($X$8:$X$47,$A9-GRAPH!C18),0)*GRAPH!C10+IFERROR(INDEX($Y$8:$Y$47,$A9-GRAPH!C19),0)*GRAPH!C11+IFERROR(INDEX($Z$8:$Z$47,$A9-GRAPH!C20),0)*GRAPH!C12+SUMPRODUCT(($D$8:$D$8=REGIONS!$B$8)*($F$8:$F$8+$A$8:$A$8=$A9)*$E$8:$E$8)+SUMPRODUCT(($N$8:$N$8=REGIONS!$B$8)*($P$8:$P$8+$A$8:$A$8=$A9)*$O$8:$O$8) -> 0.012 | AC9: =CLIMATE!J9+IFERROR(INDEX($W$8:$W$47,$A9-GRAPH!D17),0)*GRAPH!D9+IFERROR(INDEX($X$8:$X$47,$A9-GRAPH!D18),0)*GRAPH!D10+IFERROR(INDEX($Y$8:$Y$47,$A9-GRAPH!D19),0)*GRAPH!D11+IFERROR(INDEX($Z$8:$Z$47,$A9-GRAPH!D20),0)*GRAPH!D12+SUMPRODUCT(($D$8:$D$8=REGIONS!$B$9)*($F$8:$F$8+$A$8:$A$8=$A9)*$E$8:$E$8)+SUMPRODUCT(($N$8:$N$8=REGIONS!$B$9)*($P$8:$P$8+$A$8:$A$8=$A9)*$O$8:$O$8) -> 1.002 | AD9: =CLIMATE!K9+IFERROR(INDEX($W$8:$W$47,$A9-GRAPH!E17),0)*GRAPH!E9+IFERROR(INDEX($X$8:$X$47,$A9-GRAPH!E18),0)*GRAPH!E10+IFERROR(INDEX($Y$8:$Y$47,$A9-GRAPH!E19),0)*GRAPH!E11+IFERROR(INDEX($Z$8:$Z$47,$A9-GRAPH!E20),0)*GRAPH!E12+SUMPRODUCT(($D$8:$D$8=REGIONS!$B$10)*($F$8:$F$8+$A$8:$A$8=$A9)*$E$8:$E$8)+SUMPRODUCT(($N$8:$N$8=REGIONS!$B$10)*($P$8:$P$8+$A$8:$A$8=$A9)*$O$8:$O$8) -> -0.2504 | AE9: =CLIMATE!L9+IFERROR(INDEX($W$8:$W$47,$A9-GRAPH!F17),0)*GRAPH!F9+IFERROR(INDEX($X$8:$X$47,$A9-GRAPH!F18),0)*GRAPH!F10+IFERROR(INDEX($Y$8:$Y$47,$A9-GRAPH!F19),0)*GRAPH!F11+IFERROR(INDEX($Z$8:$Z$47,$A9-GRAPH!F20),0)*GRAPH!F12+SUMPRODUCT(($D$8:$D$8=REGIONS!$B$11)*($F$8:$F$8+$A$8:$A$8=$A9)*$E$8:$E$8)+SUMPRODUCT(($N$8:$N$8=REGIONS!$B$11)*($P$8:$P$8+$A$8:$A$8=$A9)*$O$8:$O$8) -> -0.8531 | AF9: =CLIMATE!M9+IFERROR(INDEX($W$8:$W$47,$A9-GRAPH!G17),0)*GRAPH!G9+IFERROR(INDEX($X$8:$X$47,$A9-GRAPH!G18),0)*GRAPH!G10+IFERROR(INDEX($Y$8:$Y$47,$A9-GRAPH!G19),0)*GRAPH!G11+IFERROR(INDEX($Z$8:$Z$47,$A9-GRAPH!G20),0)*GRAPH!G12+SUMPRODUCT(($D$8:$D$8=REGIONS!$B$12)*($F$8:$F$8+$A$8:$A$8=$A9)*$E$8:$E$8)+SUMPRODUCT(($N$8:$N$8=REGIONS!$B$12)*($P$8:$P$8+$A$8:$A$8=$A9)*$O$8:$O$8) -> -1.3979 | AG9: =CLIMATE!N9+IFERROR(INDEX($W$8:$W$47,$A9-GRAPH!H17),0)*GRAPH!H9+IFERROR(INDEX($X$8:$X$47,$A9-GRAPH!H18),0)*GRAPH!H10+IFERROR(INDEX($Y$8:$Y$47,$A9-GRAPH!H19),0)*GRAPH!H11+IFERROR(INDEX($Z$8:$Z$47,$A9-GRAPH!H20),0)*GRAPH!H12+SUMPRODUCT(($D$8:$D$8=REGIONS!$B$13)*($F$8:$F$8+$A$8:$A$8=$A9)*$E$8:$E$8)+SUMPRODUCT(($N$8:$N$8=REGIONS!$B$13)*($P$8:$P$8+$A$8:$A$8=$A9)*$O$8:$O$8) -> 0.2688 | AH9: =CLIMATE!O9+IFERROR(INDEX($W$8:$W$47,$A9-GRAPH!I17),0)*GRAPH!I9+IFERROR(INDEX($X$8:$X$47,$A9-GRAPH!I18),0)*GRAPH!I10+IFERROR(INDEX($Y$8:$Y$47,$A9-GRAPH!I19),0)*GRAPH!I11+IFERROR(INDEX($Z$8:$Z$47,$A9-GRAPH!I20),0)*GRAPH!I12+SUMPRODUCT(($D$8:$D$8=REGIONS!$B$14)*($F$8:$F$8+$A$8:$A$8=$A9)*$E$8:$E$8)+SUMPRODUCT(($N$8:$N$8=REGIONS!$B$14)*($P$8:$P$8+$A$8:$A$8=$A9)*$O$8:$O$8) -> 0.7566 | AI9: =REGIONS!$F$7*(1+ASSUMPTIONS!$B$19*$A9) -> 0.8096 | AJ9: =REGIONS!$F$8*(1+ASSUMPTIONS!$B$19*$A9) -> 0.9108 | AK9: =REGIONS!$F$9*(1+ASSUMPTIONS!$B$19*$A9) -> 0.9108 | AL9: =REGIONS!$F$10*(1+ASSUMPTIONS!$B$19*$A9) -> 0.7084 | AM9: =REGIONS!$F$11*(1+ASSUMPTIONS!$B$19*$A9) -> 0.7084 | AN9: =REGIONS!$F$12*(1+ASSUMPTIONS!$B$19*$A9) -> 1.1132 | AO9: =REGIONS!$F$13*(1+ASSUMPTIONS!$B$19*$A9) -> 1.2144 | AP9: =REGIONS!$F$14*(1+ASSUMPTIONS!$B$19*$A9) -> 1.2144 | AQ9: =SUMPRODUCT(($D$8:$D$47=REGIONS!$B$7)*($A$8:$A$47<=$A9)*$L$8:$L$47)+SUMPRODUCT(($N$8:$N$47=REGIONS!$B$7)*($A$8:$A$47<=$A9)*$V$8:$V$47) -> 0 | AR9: =SUMPRODUCT(($D$8:$D$47=REGIONS!$B$8)*($A$8:$A$47<=$A9)*$L$8:$L$47)+SUMPRODUCT(($N$8:$N$47=REGIONS!$B$8)*($A$8:$A$47<=$A9)*$V$8:$V$47) -> 0 | AS9: =SUMPRODUCT(($D$8:$D$47=REGIONS!$B$9)*($A$8:$A$47<=$A9)*$L$8:$L$47)+SUMPRODUCT(($N$8:$N$47=REGIONS!$B$9)*($A$8:$A$47<=$A9)*$V$8:$V$47) -> 0 | AT9: =SUMPRODUCT(($D$8:$D$47=REGIONS!$B$10)*($A$8:$A$47<=$A9)*$L$8:$L$47)+SUMPRODUCT(($N$8:$N$47=REGIONS!$B$10)*($A$8:$A$47<=$A9)*$V$8:$V$47) -> 0 | AU9: =SUMPRODUCT(($D$8:$D$47=REGIONS!$B$11)*($A$8:$A$47<=$A9)*$L$8:$L$47)+SUMPRODUCT(($N$8:$N$47=REGIONS!$B$11)*($A$8:$A$47<=$A9)*$V$8:$V$47) -> 0 | AV9: =SUMPRODUCT(($D$8:$D$47=REGIONS!$B$12)*($A$8:$A$47<=$A9)*$L$8:$L$47)+SUMPRODUCT(($N$8:$N$47=REGIONS!$B$12)*($A$8:$A$47<=$A9)*$V$8:$V$47) -> 0 | AW9: =SUMPRODUCT(($D$8:$D$47=REGIONS!$B$13)*($A$8:$A$47<=$A9)*$L$8:$L$47)+SUMPRODUCT(($N$8:$N$47=REGIONS!$B$13)*($A$8:$A$47<=$A9)*$V$8:$V$47) -> 0 | AX9: =SUMPRODUCT(($D$8:$D$47=REGIONS!$B$14)*($A$8:$A$47<=$A9)*$L$8:$L$47)+SUMPRODUCT(($N$8:$N$47=REGIONS!$B$14)*($A$8:$A$47<=$A9)*$V$8:$V$47) -> 0 | AY9: =MAX(0,MIN(135,100-(MAX(0,-$AA9)*REGIONS!$E$7*ASSUMPTIONS!$B$7+MAX(0,$AA9-ASSUMPTIONS!$B$9)*REGIONS!$E$7*ASSUMPTIONS!$B$8)*(1-$AQ9/100))) -> 100 | AZ9: =MAX(0,MIN(135,100-(MAX(0,-$AB9)*REGIONS!$E$8*ASSUMPTIONS!$B$7+MAX(0,$AB9-ASSUMPTIONS!$B$9)*REGIONS!$E$8*ASSUMPTIONS!$B$8)*(1-$AR9/100))) -> 100 | BA9: =MAX(0,MIN(135,100-(MAX(0,-$AC9)*REGIONS!$E$9*ASSUMPTIONS!$B$7+MAX(0,$AC9-ASSUMPTIONS!$B$9)*REGIONS!$E$9*ASSUMPTIONS!$B$8)*(1-$AS9/100))) -> 100 | BB9: =MAX(0,MIN(135,100-(MAX(0,-$AD9)*REGIONS!$E$10*ASSUMPTIONS!$B$7+MAX(0,$AD9-ASSUMPTIONS!$B$9)*REGIONS!$E$10*ASSUMPTIONS!$B$8)*(1-$AT9/100))) -> 95.79328 | BC9: =MAX(0,MIN(135,100-(MAX(0,-$AE9)*REGIONS!$E$11*ASSUMPTIONS!$B$7+MAX(0,$AE9-ASSUMPTIONS!$B$9)*REGIONS!$E$11*ASSUMPTIONS!$B$8)*(1-$AU9/100))) -> 86.86226 | BD9: =MAX(0,MIN(135,100-(MAX(0,-$AF9)*REGIONS!$E$12*ASSUMPTIONS!$B$7+MAX(0,$AF9-ASSUMPTIONS!$B$9)*REGIONS!$E$12*ASSUMPTIONS!$B$8)*(1-$AV9/100))) -> 74.55822 | BE9: =MAX(0,MIN(135,100-(MAX(0,-$AG9)*REGIONS!$E$13*ASSUMPTIONS!$B$7+MAX(0,$AG9-ASSUMPTIONS!$B$9)*REGIONS!$E$13*ASSUMPTIONS!$B$8)*(1-$AW9/100))) -> 100 | BF9: =MAX(0,MIN(135,100-(MAX(0,-$AH9)*REGIONS!$E$14*ASSUMPTIONS!$B$7+MAX(0,$AH9-ASSUMPTIONS!$B$9)*REGIONS!$E$14*ASSUMPTIONS!$B$8)*(1-$AX9/100))) -> 100 | BG9: =$AY9*REGIONS!$D$7/100+$AZ9*REGIONS!$D$8/100+$BA9*REGIONS!$D$9/100+$BB9*REGIONS!$D$10/100+$BC9*REGIONS!$D$11/100+$BD9*REGIONS!$D$12/100+$BE9*REGIONS!$D$13/100+$BF9*REGIONS!$D$14/100 -> 95.885337 | BH9: =100*(100/MAX(1,$BG9))^ASSUMPTIONS!$B$10 -> 107.85643 | BI9: =$AY9*$BH9/100*ASSUMPTIONS!$B$11 -> 91.677966 | BJ9: =MAX(0,ABS($AA9)-$AI9*ASSUMPTIONS!$B$24)*REGIONS!$D$7/100+MAX(0,ABS($AB9)-$AJ9*ASSUMPTIONS!$B$24)*REGIONS!$D$8/100+MAX(0,ABS($AC9)-$AK9*ASSUMPTIONS!$B$24)*REGIONS!$D$9/100+MAX(0,ABS($AD9)-$AL9*ASSUMPTIONS!$B$24)*REGIONS!$D$10/100+MAX(0,ABS($AE9)-$AM9*ASSUMPTIONS!$B$24)*REGIONS!$D$11/100+MAX(0,ABS($AF9)-$AN9*ASSUMPTIONS!$B$24)*REGIONS!$D$12/100+MAX(0,ABS($AG9)-$AO9*ASSUMPTIONS!$B$24)*REGIONS!$D$13/100+MAX(0,ABS($AH9)-$AP9*ASSUMPTIONS!$B$24)*REGIONS!$D$14/100 -> 0.125861 | BK9: =MIN(ASSUMPTIONS!$B$14,ASSUMPTIONS!$B$12+$BJ9*ASSUMPTIONS!$B$13) -> 33.286162 | BL9: =$H9+$R9 -> 0 | BM9: =PLAY!$H9 -> 0 | BN9: =$BI9*ASSUMPTIONS!$B$15+$BK9*ASSUMPTIONS!$B$16 -> 40.958902 | BO9: =$BO8+$BN9-$BL9-$BM9-ASSUMPTIONS!$B$23 -> 98.833468 | BP9: =(SUMPRODUCT(($F$8:$F$8+$A$8:$A$8=$A9)*($C$8:$C$8<>"NONE")*$G$8:$G$8)+SUMPRODUCT(($P$8:$P$8+$A$8:$A$8=$A9)*($M$8:$M$8<>"NONE")*$Q$8:$Q$8))*(1+ASSUMPTIONS!$B$22*(MAX(0,ABS($AA9)/$AI9-1)+MAX(0,ABS($AB9)/$AJ9-1)+MAX(0,ABS($AC9)/$AK9-1)+MAX(0,ABS($AD9)/$AL9-1)+MAX(0,ABS($AE9)/$AM9-1)+MAX(0,ABS($AF9)/$AN9-1)+MAX(0,ABS($AG9)/$AO9-1)+MAX(0,ABS($AH9)/$AP9-1))/8) -> 2.1120288 | BQ9: =MAX(0,$BQ8*(1-ASSUMPTIONS!$B$18)+$BP9-$BM9*ASSUMPTIONS!$B$17) -> 2.1120288
A10: 3 | B10: =CLIMATE!B10 -> 1946 | C10: =IFERROR(INDEX(CAPABILITIES!$B$7:$B$15,MATCH(PLAY!$D10,CAPABILITIES!$A$7:$A$15,0)),"NONE") -> NONE | D10: =IFERROR(IF(INDEX(CAPABILITIES!$B$7:$B$15,MATCH(PLAY!$D10,CAPABILITIES!$A$7:$A$15,0))="DRIVER",INDEX(CAPABILITIES!$C$7:$C$15,MATCH(PLAY!$D10,CAPABILITIES!$A$7:$A$15,0)),PLAY!$E10),"") -> 0 | E10: =IFERROR(INDEX(CAPABILITIES!$D$7:$D$15,MATCH(PLAY!$D10,CAPABILITIES!$A$7:$A$15,0))*IF(INDEX(CAPABILITIES!$K$7:$K$15,MATCH(PLAY!$D10,CAPABILITIES!$A$7:$A$15,0))="Y",IF(IFERROR(INDEX($AA9:$AH9,MATCH(PLAY!$E10,REGIONS!$B$7:$B$14,0)),0)<ASSUMPTIONS!$B$20,1,ASSUMPTIONS!$B$21),1),0) -> 0 | F10: =IFERROR(INDEX(CAPABILITIES!$E$7:$E$15,MATCH(PLAY!$D10,CAPABILITIES!$A$7:$A$15,0)),0) -> 0 | G10: =IFERROR(INDEX(CAPABILITIES!$F$7:$F$15,MATCH(PLAY!$D10,CAPABILITIES!$A$7:$A$15,0)),0) -> 0 | H10: =IFERROR(INDEX(CAPABILITIES!$G$7:$G$15,MATCH(PLAY!$D10,CAPABILITIES!$A$7:$A$15,0)),0) -> 0 | I10: =IFERROR(INDEX(CAPABILITIES!$H$7:$H$15,MATCH(PLAY!$D10,CAPABILITIES!$A$7:$A$15,0)),"") -> 0 | J10: =IFERROR(INDEX(CAPABILITIES!$D$7:$D$15,MATCH(PLAY!$D10,CAPABILITIES!$A$7:$A$15,0))*INDEX(CAPABILITIES!$I$7:$I$15,MATCH(PLAY!$D10,CAPABILITIES!$A$7:$A$15,0)),0) -> 0 | K10: =IFERROR(INDEX(CAPABILITIES!$E$7:$E$15,MATCH(PLAY!$D10,CAPABILITIES!$A$7:$A$15,0))+INDEX(CAPABILITIES!$J$7:$J$15,MATCH(PLAY!$D10,CAPABILITIES!$A$7:$A$15,0)),0) -> 0 | L10: =IFERROR(INDEX(CAPABILITIES!$L$7:$L$15,MATCH(PLAY!$D10,CAPABILITIES!$A$7:$A$15,0)),0) -> 0 | M10: =IFERROR(INDEX(CAPABILITIES!$B$7:$B$15,MATCH(PLAY!$F10,CAPABILITIES!$A$7:$A$15,0)),"NONE") -> NONE | N10: =IFERROR(IF(INDEX(CAPABILITIES!$B$7:$B$15,MATCH(PLAY!$F10,CAPABILITIES!$A$7:$A$15,0))="DRIVER",INDEX(CAPABILITIES!$C$7:$C$15,MATCH(PLAY!$F10,CAPABILITIES!$A$7:$A$15,0)),PLAY!$G10),"") -> 0 | O10: =IFERROR(INDEX(CAPABILITIES!$D$7:$D$15,MATCH(PLAY!$F10,CAPABILITIES!$A$7:$A$15,0))*IF(INDEX(CAPABILITIES!$K$7:$K$15,MATCH(PLAY!$F10,CAPABILITIES!$A$7:$A$15,0))="Y",IF(IFERROR(INDEX($AA9:$AH9,MATCH(PLAY!$G10,REGIONS!$B$7:$B$14,0)),0)<ASSUMPTIONS!$B$20,1,ASSUMPTIONS!$B$21),1),0) -> 0 | P10: =IFERROR(INDEX(CAPABILITIES!$E$7:$E$15,MATCH(PLAY!$F10,CAPABILITIES!$A$7:$A$15,0)),0) -> 0 | Q10: =IFERROR(INDEX(CAPABILITIES!$F$7:$F$15,MATCH(PLAY!$F10,CAPABILITIES!$A$7:$A$15,0)),0) -> 0 | R10: =IFERROR(INDEX(CAPABILITIES!$G$7:$G$15,MATCH(PLAY!$F10,CAPABILITIES!$A$7:$A$15,0)),0) -> 0 | S10: =IFERROR(INDEX(CAPABILITIES!$H$7:$H$15,MATCH(PLAY!$F10,CAPABILITIES!$A$7:$A$15,0)),"") -> 0 | T10: =IFERROR(INDEX(CAPABILITIES!$D$7:$D$15,MATCH(PLAY!$F10,CAPABILITIES!$A$7:$A$15,0))*INDEX(CAPABILITIES!$I$7:$I$15,MATCH(PLAY!$F10,CAPABILITIES!$A$7:$A$15,0)),0) -> 0 | U10: =IFERROR(INDEX(CAPABILITIES!$E$7:$E$15,MATCH(PLAY!$F10,CAPABILITIES!$A$7:$A$15,0))+INDEX(CAPABILITIES!$J$7:$J$15,MATCH(PLAY!$F10,CAPABILITIES!$A$7:$A$15,0)),0) -> 0 | V10: =IFERROR(INDEX(CAPABILITIES!$L$7:$L$15,MATCH(PLAY!$F10,CAPABILITIES!$A$7:$A$15,0)),0) -> 0 | W10: =CLIMATE!D10+SUMPRODUCT(($D$8:$D$9="ENSO")*($F$8:$F$9+$A$8:$A$9=$A10)*$E$8:$E$9)+SUMPRODUCT(($I$8:$I$9="ENSO")*($K$8:$K$9+$A$8:$A$9=$A10)*$J$8:$J$9)+SUMPRODUCT(($N$8:$N$9="ENSO")*($P$8:$P$9+$A$8:$A$9=$A10)*$O$8:$O$9)+SUMPRODUCT(($S$8:$S$9="ENSO")*($U$8:$U$9+$A$8:$A$9=$A10)*$T$8:$T$9) -> 0.675 | X10: =CLIMATE!E10+SUMPRODUCT(($D$8:$D$9="IOD")*($F$8:$F$9+$A$8:$A$9=$A10)*$E$8:$E$9)+SUMPRODUCT(($I$8:$I$9="IOD")*($K$8:$K$9+$A$8:$A$9=$A10)*$J$8:$J$9)+SUMPRODUCT(($N$8:$N$9="IOD")*($P$8:$P$9+$A$8:$A$9=$A10)*$O$8:$O$9)+SUMPRODUCT(($S$8:$S$9="IOD")*($U$8:$U$9+$A$8:$A$9=$A10)*$T$8:$T$9) -> -0.667 | Y10: =CLIMATE!F10+SUMPRODUCT(($D$8:$D$9="NATL")*($F$8:$F$9+$A$8:$A$9=$A10)*$E$8:$E$9)+SUMPRODUCT(($I$8:$I$9="NATL")*($K$8:$K$9+$A$8:$A$9=$A10)*$J$8:$J$9)+SUMPRODUCT(($N$8:$N$9="NATL")*($P$8:$P$9+$A$8:$A$9=$A10)*$O$8:$O$9)+SUMPRODUCT(($S$8:$S$9="NATL")*($U$8:$U$9+$A$8:$A$9=$A10)*$T$8:$T$9) -> 0.024 | Z10: =CLIMATE!G10+SUMPRODUCT(($D$8:$D$9="GLOBAL")*($F$8:$F$9+$A$8:$A$9=$A10)*$E$8:$E$9)+SUMPRODUCT(($I$8:$I$9="GLOBAL")*($K$8:$K$9+$A$8:$A$9=$A10)*$J$8:$J$9)+SUMPRODUCT(($N$8:$N$9="GLOBAL")*($P$8:$P$9+$A$8:$A$9=$A10)*$O$8:$O$9)+SUMPRODUCT(($S$8:$S$9="GLOBAL")*($U$8:$U$9+$A$8:$A$9=$A10)*$T$8:$T$9) -> 0 | AA10: =CLIMATE!H10+IFERROR(INDEX($W$8:$W$47,$A10-GRAPH!B17),0)*GRAPH!B9+IFERROR(INDEX($X$8:$X$47,$A10-GRAPH!B18),0)*GRAPH!B10+IFERROR(INDEX($Y$8:$Y$47,$A10-GRAPH!B19),0)*GRAPH!B11+IFERROR(INDEX($Z$8:$Z$47,$A10-GRAPH!B20),0)*GRAPH!B12+SUMPRODUCT(($D$8:$D$9=REGIONS!$B$7)*($F$8:$F$9+$A$8:$A$9=$A10)*$E$8:$E$9)+SUMPRODUCT(($N$8:$N$9=REGIONS!$B$7)*($P$8:$P$9+$A$8:$A$9=$A10)*$O$8:$O$9) -> 0.5059 | AB10: =CLIMATE!I10+IFERROR(INDEX($W$8:$W$47,$A10-GRAPH!C17),0)*GRAPH!C9+IFERROR(INDEX($X$8:$X$47,$A10-GRAPH!C18),0)*GRAPH!C10+IFERROR(INDEX($Y$8:$Y$47,$A10-GRAPH!C19),0)*GRAPH!C11+IFERROR(INDEX($Z$8:$Z$47,$A10-GRAPH!C20),0)*GRAPH!C12+SUMPRODUCT(($D$8:$D$9=REGIONS!$B$8)*($F$8:$F$9+$A$8:$A$9=$A10)*$E$8:$E$9)+SUMPRODUCT(($N$8:$N$9=REGIONS!$B$8)*($P$8:$P$9+$A$8:$A$9=$A10)*$O$8:$O$9) -> 0.2117 | AC10: =CLIMATE!J10+IFERROR(INDEX($W$8:$W$47,$A10-GRAPH!D17),0)*GRAPH!D9+IFERROR(INDEX($X$8:$X$47,$A10-GRAPH!D18),0)*GRAPH!D10+IFERROR(INDEX($Y$8:$Y$47,$A10-GRAPH!D19),0)*GRAPH!D11+IFERROR(INDEX($Z$8:$Z$47,$A10-GRAPH!D20),0)*GRAPH!D12+SUMPRODUCT(($D$8:$D$9=REGIONS!$B$9)*($F$8:$F$9+$A$8:$A$9=$A10)*$E$8:$E$9)+SUMPRODUCT(($N$8:$N$9=REGIONS!$B$9)*($P$8:$P$9+$A$8:$A$9=$A10)*$O$8:$O$9) -> 0.8855 | AD10: =CLIMATE!K10+IFERROR(INDEX($W$8:$W$47,$A10-GRAPH!E17),0)*GRAPH!E9+IFERROR(INDEX($X$8:$X$47,$A10-GRAPH!E18),0)*GRAPH!E10+IFERROR(INDEX($Y$8:$Y$47,$A10-GRAPH!E19),0)*GRAPH!E11+IFERROR(INDEX($Z$8:$Z$47,$A10-GRAPH!E20),0)*GRAPH!E12+SUMPRODUCT(($D$8:$D$9=REGIONS!$B$10)*($F$8:$F$9+$A$8:$A$9=$A10)*$E$8:$E$9)+SUMPRODUCT(($N$8:$N$9=REGIONS!$B$10)*($P$8:$P$9+$A$8:$A$9=$A10)*$O$8:$O$9) -> -0.3318 | AE10: =CLIMATE!L10+IFERROR(INDEX($W$8:$W$47,$A10-GRAPH!F17),0)*GRAPH!F9+IFERROR(INDEX($X$8:$X$47,$A10-GRAPH!F18),0)*GRAPH!F10+IFERROR(INDEX($Y$8:$Y$47,$A10-GRAPH!F19),0)*GRAPH!F11+IFERROR(INDEX($Z$8:$Z$47,$A10-GRAPH!F20),0)*GRAPH!F12+SUMPRODUCT(($D$8:$D$9=REGIONS!$B$11)*($F$8:$F$9+$A$8:$A$9=$A10)*$E$8:$E$9)+SUMPRODUCT(($N$8:$N$9=REGIONS!$B$11)*($P$8:$P$9+$A$8:$A$9=$A10)*$O$8:$O$9) -> -0.6834 | AF10: =CLIMATE!M10+IFERROR(INDEX($W$8:$W$47,$A10-GRAPH!G17),0)*GRAPH!G9+IFERROR(INDEX($X$8:$X$47,$A10-GRAPH!G18),0)*GRAPH!G10+IFERROR(INDEX($Y$8:$Y$47,$A10-GRAPH!G19),0)*GRAPH!G11+IFERROR(INDEX($Z$8:$Z$47,$A10-GRAPH!G20),0)*GRAPH!G12+SUMPRODUCT(($D$8:$D$9=REGIONS!$B$12)*($F$8:$F$9+$A$8:$A$9=$A10)*$E$8:$E$9)+SUMPRODUCT(($N$8:$N$9=REGIONS!$B$12)*($P$8:$P$9+$A$8:$A$9=$A10)*$O$8:$O$9) -> -1.4706 | AG10: =CLIMATE!N10+IFERROR(INDEX($W$8:$W$47,$A10-GRAPH!H17),0)*GRAPH!H9+IFERROR(INDEX($X$8:$X$47,$A10-GRAPH!H18),0)*GRAPH!H10+IFERROR(INDEX($Y$8:$Y$47,$A10-GRAPH!H19),0)*GRAPH!H11+IFERROR(INDEX($Z$8:$Z$47,$A10-GRAPH!H20),0)*GRAPH!H12+SUMPRODUCT(($D$8:$D$9=REGIONS!$B$13)*($F$8:$F$9+$A$8:$A$9=$A10)*$E$8:$E$9)+SUMPRODUCT(($N$8:$N$9=REGIONS!$B$13)*($P$8:$P$9+$A$8:$A$9=$A10)*$O$8:$O$9) -> -0.5555 | AH10: =CLIMATE!O10+IFERROR(INDEX($W$8:$W$47,$A10-GRAPH!I17),0)*GRAPH!I9+IFERROR(INDEX($X$8:$X$47,$A10-GRAPH!I18),0)*GRAPH!I10+IFERROR(INDEX($Y$8:$Y$47,$A10-GRAPH!I19),0)*GRAPH!I11+IFERROR(INDEX($Z$8:$Z$47,$A10-GRAPH!I20),0)*GRAPH!I12+SUMPRODUCT(($D$8:$D$9=REGIONS!$B$14)*($F$8:$F$9+$A$8:$A$9=$A10)*$E$8:$E$9)+SUMPRODUCT(($N$8:$N$9=REGIONS!$B$14)*($P$8:$P$9+$A$8:$A$9=$A10)*$O$8:$O$9) -> 0.5022 | AI10: =REGIONS!$F$7*(1+ASSUMPTIONS!$B$19*$A10) -> 0.8144 | AJ10: =REGIONS!$F$8*(1+ASSUMPTIONS!$B$19*$A10) -> 0.9162 | AK10: =REGIONS!$F$9*(1+ASSUMPTIONS!$B$19*$A10) -> 0.9162 | AL10: =REGIONS!$F$10*(1+ASSUMPTIONS!$B$19*$A10) -> 0.7126 | AM10: =REGIONS!$F$11*(1+ASSUMPTIONS!$B$19*$A10) -> 0.7126 | AN10: =REGIONS!$F$12*(1+ASSUMPTIONS!$B$19*$A10) -> 1.1198 | AO10: =REGIONS!$F$13*(1+ASSUMPTIONS!$B$19*$A10) -> 1.2216 | AP10: =REGIONS!$F$14*(1+ASSUMPTIONS!$B$19*$A10) -> 1.2216 | AQ10: =SUMPRODUCT(($D$8:$D$47=REGIONS!$B$7)*($A$8:$A$47<=$A10)*$L$8:$L$47)+SUMPRODUCT(($N$8:$N$47=REGIONS!$B$7)*($A$8:$A$47<=$A10)*$V$8:$V$47) -> 0 | AR10: =SUMPRODUCT(($D$8:$D$47=REGIONS!$B$8)*($A$8:$A$47<=$A10)*$L$8:$L$47)+SUMPRODUCT(($N$8:$N$47=REGIONS!$B$8)*($A$8:$A$47<=$A10)*$V$8:$V$47) -> 0 | AS10: =SUMPRODUCT(($D$8:$D$47=REGIONS!$B$9)*($A$8:$A$47<=$A10)*$L$8:$L$47)+SUMPRODUCT(($N$8:$N$47=REGIONS!$B$9)*($A$8:$A$47<=$A10)*$V$8:$V$47) -> 0 | AT10: =SUMPRODUCT(($D$8:$D$47=REGIONS!$B$10)*($A$8:$A$47<=$A10)*$L$8:$L$47)+SUMPRODUCT(($N$8:$N$47=REGIONS!$B$10)*($A$8:$A$47<=$A10)*$V$8:$V$47) -> 0 | AU10: =SUMPRODUCT(($D$8:$D$47=REGIONS!$B$11)*($A$8:$A$47<=$A10)*$L$8:$L$47)+SUMPRODUCT(($N$8:$N$47=REGIONS!$B$11)*($A$8:$A$47<=$A10)*$V$8:$V$47) -> 0 | AV10: =SUMPRODUCT(($D$8:$D$47=REGIONS!$B$12)*($A$8:$A$47<=$A10)*$L$8:$L$47)+SUMPRODUCT(($N$8:$N$47=REGIONS!$B$12)*($A$8:$A$47<=$A10)*$V$8:$V$47) -> 0 | AW10: =SUMPRODUCT(($D$8:$D$47=REGIONS!$B$13)*($A$8:$A$47<=$A10)*$L$8:$L$47)+SUMPRODUCT(($N$8:$N$47=REGIONS!$B$13)*($A$8:$A$47<=$A10)*$V$8:$V$47) -> 0 | AX10: =SUMPRODUCT(($D$8:$D$47=REGIONS!$B$14)*($A$8:$A$47<=$A10)*$L$8:$L$47)+SUMPRODUCT(($N$8:$N$47=REGIONS!$B$14)*($A$8:$A$47<=$A10)*$V$8:$V$47) -> 0 | AY10: =MAX(0,MIN(135,100-(MAX(0,-$AA10)*REGIONS!$E$7*ASSUMPTIONS!$B$7+MAX(0,$AA10-ASSUMPTIONS!$B$9)*REGIONS!$E$7*ASSUMPTIONS!$B$8)*(1-$AQ10/100))) -> 100 | AZ10: =MAX(0,MIN(135,100-(MAX(0,-$AB10)*REGIONS!$E$8*ASSUMPTIONS!$B$7+MAX(0,$AB10-ASSUMPTIONS!$B$9)*REGIONS!$E$8*ASSUMPTIONS!$B$8)*(1-$AR10/100))) -> 100 | BA10: =MAX(0,MIN(135,100-(MAX(0,-$AC10)*REGIONS!$E$9*ASSUMPTIONS!$B$7+MAX(0,$AC10-ASSUMPTIONS!$B$9)*REGIONS!$E$9*ASSUMPTIONS!$B$8)*(1-$AS10/100))) -> 100 | BB10: =MAX(0,MIN(135,100-(MAX(0,-$AD10)*REGIONS!$E$10*ASSUMPTIONS!$B$7+MAX(0,$AD10-ASSUMPTIONS!$B$9)*REGIONS!$E$10*ASSUMPTIONS!$B$8)*(1-$AT10/100))) -> 94.42576 | BC10: =MAX(0,MIN(135,100-(MAX(0,-$AE10)*REGIONS!$E$11*ASSUMPTIONS!$B$7+MAX(0,$AE10-ASSUMPTIONS!$B$9)*REGIONS!$E$11*ASSUMPTIONS!$B$8)*(1-$AU10/100))) -> 89.47564 | BD10: =MAX(0,MIN(135,100-(MAX(0,-$AF10)*REGIONS!$E$12*ASSUMPTIONS!$B$7+MAX(0,$AF10-ASSUMPTIONS!$B$9)*REGIONS!$E$12*ASSUMPTIONS!$B$8)*(1-$AV10/100))) -> 73.23508 | BE10: =MAX(0,MIN(135,100-(MAX(0,-$AG10)*REGIONS!$E$13*ASSUMPTIONS!$B$7+MAX(0,$AG10-ASSUMPTIONS!$B$9)*REGIONS!$E$13*ASSUMPTIONS!$B$8)*(1-$AW10/100))) -> 89.1122 | BF10: =MAX(0,MIN(135,100-(MAX(0,-$AH10)*REGIONS!$E$14*ASSUMPTIONS!$B$7+MAX(0,$AH10-ASSUMPTIONS!$B$9)*REGIONS!$E$14*ASSUMPTIONS!$B$8)*(1-$AX10/100))) -> 100 | BG10: =$AY10*REGIONS!$D$7/100+$AZ10*REGIONS!$D$8/100+$BA10*REGIONS!$D$9/100+$BB10*REGIONS!$D$10/100+$BC10*REGIONS!$D$11/100+$BD10*REGIONS!$D$12/100+$BE10*REGIONS!$D$13/100+$BF10*REGIONS!$D$14/100 -> 95.206901 | BH10: =100*(100/MAX(1,$BG10))^ASSUMPTIONS!$B$10 -> 109.24381 | BI10: =$AY10*$BH10/100*ASSUMPTIONS!$B$11 -> 92.857236 | BJ10: =MAX(0,ABS($AA10)-$AI10*ASSUMPTIONS!$B$24)*REGIONS!$D$7/100+MAX(0,ABS($AB10)-$AJ10*ASSUMPTIONS!$B$24)*REGIONS!$D$8/100+MAX(0,ABS($AC10)-$AK10*ASSUMPTIONS!$B$24)*REGIONS!$D$9/100+MAX(0,ABS($AD10)-$AL10*ASSUMPTIONS!$B$24)*REGIONS!$D$10/100+MAX(0,ABS($AE10)-$AM10*ASSUMPTIONS!$B$24)*REGIONS!$D$11/100+MAX(0,ABS($AF10)-$AN10*ASSUMPTIONS!$B$24)*REGIONS!$D$12/100+MAX(0,ABS($AG10)-$AO10*ASSUMPTIONS!$B$24)*REGIONS!$D$13/100+MAX(0,ABS($AH10)-$AP10*ASSUMPTIONS!$B$24)*REGIONS!$D$14/100 -> 0.091779 | BK10: =MIN(ASSUMPTIONS!$B$14,ASSUMPTIONS!$B$12+$BJ10*ASSUMPTIONS!$B$13) -> 31.854718 | BL10: =$H10+$R10 -> 0 | BM10: =PLAY!$H10 -> 0 | BN10: =$BI10*ASSUMPTIONS!$B$15+$BK10*ASSUMPTIONS!$B$16 -> 39.812115 | BO10: =$BO9+$BN10-$BL10-$BM10-ASSUMPTIONS!$B$23 -> 106.64558 | BP10: =(SUMPRODUCT(($F$8:$F$9+$A$8:$A$9=$A10)*($C$8:$C$9<>"NONE")*$G$8:$G$9)+SUMPRODUCT(($P$8:$P$9+$A$8:$A$9=$A10)*($M$8:$M$9<>"NONE")*$Q$8:$Q$9))*(1+ASSUMPTIONS!$B$22*(MAX(0,ABS($AA10)/$AI10-1)+MAX(0,ABS($AB10)/$AJ10-1)+MAX(0,ABS($AC10)/$AK10-1)+MAX(0,ABS($AD10)/$AL10-1)+MAX(0,ABS($AE10)/$AM10-1)+MAX(0,ABS($AF10)/$AN10-1)+MAX(0,ABS($AG10)/$AO10-1)+MAX(0,ABS($AH10)/$AP10-1))/8) -> 0 | BQ10: =MAX(0,$BQ9*(1-ASSUMPTIONS!$B$18)+$BP10-$BM10*ASSUMPTIONS!$B$17) -> 2.0275477
A11: 4 | B11: =CLIMATE!B11 -> 1946 | C11: =IFERROR(INDEX(CAPABILITIES!$B$7:$B$15,MATCH(PLAY!$D11,CAPABILITIES!$A$7:$A$15,0)),"NONE") -> NONE | D11: =IFERROR(IF(INDEX(CAPABILITIES!$B$7:$B$15,MATCH(PLAY!$D11,CAPABILITIES!$A$7:$A$15,0))="DRIVER",INDEX(CAPABILITIES!$C$7:$C$15,MATCH(PLAY!$D11,CAPABILITIES!$A$7:$A$15,0)),PLAY!$E11),"") -> 0 | E11: =IFERROR(INDEX(CAPABILITIES!$D$7:$D$15,MATCH(PLAY!$D11,CAPABILITIES!$A$7:$A$15,0))*IF(INDEX(CAPABILITIES!$K$7:$K$15,MATCH(PLAY!$D11,CAPABILITIES!$A$7:$A$15,0))="Y",IF(IFERROR(INDEX($AA10:$AH10,MATCH(PLAY!$E11,REGIONS!$B$7:$B$14,0)),0)<ASSUMPTIONS!$B$20,1,ASSUMPTIONS!$B$21),1),0) -> 0 | F11: =IFERROR(INDEX(CAPABILITIES!$E$7:$E$15,MATCH(PLAY!$D11,CAPABILITIES!$A$7:$A$15,0)),0) -> 0 | G11: =IFERROR(INDEX(CAPABILITIES!$F$7:$F$15,MATCH(PLAY!$D11,CAPABILITIES!$A$7:$A$15,0)),0) -> 0 | H11: =IFERROR(INDEX(CAPABILITIES!$G$7:$G$15,MATCH(PLAY!$D11,CAPABILITIES!$A$7:$A$15,0)),0) -> 0 | I11: =IFERROR(INDEX(CAPABILITIES!$H$7:$H$15,MATCH(PLAY!$D11,CAPABILITIES!$A$7:$A$15,0)),"") -> 0 | J11: =IFERROR(INDEX(CAPABILITIES!$D$7:$D$15,MATCH(PLAY!$D11,CAPABILITIES!$A$7:$A$15,0))*INDEX(CAPABILITIES!$I$7:$I$15,MATCH(PLAY!$D11,CAPABILITIES!$A$7:$A$15,0)),0) -> 0 | K11: =IFERROR(INDEX(CAPABILITIES!$E$7:$E$15,MATCH(PLAY!$D11,CAPABILITIES!$A$7:$A$15,0))+INDEX(CAPABILITIES!$J$7:$J$15,MATCH(PLAY!$D11,CAPABILITIES!$A$7:$A$15,0)),0) -> 0 | L11: =IFERROR(INDEX(CAPABILITIES!$L$7:$L$15,MATCH(PLAY!$D11,CAPABILITIES!$A$7:$A$15,0)),0) -> 0 | M11: =IFERROR(INDEX(CAPABILITIES!$B$7:$B$15,MATCH(PLAY!$F11,CAPABILITIES!$A$7:$A$15,0)),"NONE") -> NONE | N11: =IFERROR(IF(INDEX(CAPABILITIES!$B$7:$B$15,MATCH(PLAY!$F11,CAPABILITIES!$A$7:$A$15,0))="DRIVER",INDEX(CAPABILITIES!$C$7:$C$15,MATCH(PLAY!$F11,CAPABILITIES!$A$7:$A$15,0)),PLAY!$G11),"") -> 0 | O11: =IFERROR(INDEX(CAPABILITIES!$D$7:$D$15,MATCH(PLAY!$F11,CAPABILITIES!$A$7:$A$15,0))*IF(INDEX(CAPABILITIES!$K$7:$K$15,MATCH(PLAY!$F11,CAPABILITIES!$A$7:$A$15,0))="Y",IF(IFERROR(INDEX($AA10:$AH10,MATCH(PLAY!$G11,REGIONS!$B$7:$B$14,0)),0)<ASSUMPTIONS!$B$20,1,ASSUMPTIONS!$B$21),1),0) -> 0 | P11: =IFERROR(INDEX(CAPABILITIES!$E$7:$E$15,MATCH(PLAY!$F11,CAPABILITIES!$A$7:$A$15,0)),0) -> 0 | Q11: =IFERROR(INDEX(CAPABILITIES!$F$7:$F$15,MATCH(PLAY!$F11,CAPABILITIES!$A$7:$A$15,0)),0) -> 0 | R11: =IFERROR(INDEX(CAPABILITIES!$G$7:$G$15,MATCH(PLAY!$F11,CAPABILITIES!$A$7:$A$15,0)),0) -> 0 | S11: =IFERROR(INDEX(CAPABILITIES!$H$7:$H$15,MATCH(PLAY!$F11,CAPABILITIES!$A$7:$A$15,0)),"") -> 0 | T11: =IFERROR(INDEX(CAPABILITIES!$D$7:$D$15,MATCH(PLAY!$F11,CAPABILITIES!$A$7:$A$15,0))*INDEX(CAPABILITIES!$I$7:$I$15,MATCH(PLAY!$F11,CAPABILITIES!$A$7:$A$15,0)),0) -> 0 | U11: =IFERROR(INDEX(CAPABILITIES!$E$7:$E$15,MATCH(PLAY!$F11,CAPABILITIES!$A$7:$A$15,0))+INDEX(CAPABILITIES!$J$7:$J$15,MATCH(PLAY!$F11,CAPABILITIES!$A$7:$A$15,0)),0) -> 0 | V11: =IFERROR(INDEX(CAPABILITIES!$L$7:$L$15,MATCH(PLAY!$F11,CAPABILITIES!$A$7:$A$15,0)),0) -> 0 | W11: =CLIMATE!D11+SUMPRODUCT(($D$8:$D$10="ENSO")*($F$8:$F$10+$A$8:$A$10=$A11)*$E$8:$E$10)+SUMPRODUCT(($I$8:$I$10="ENSO")*($K$8:$K$10+$A$8:$A$10=$A11)*$J$8:$J$10)+SUMPRODUCT(($N$8:$N$10="ENSO")*($P$8:$P$10+$A$8:$A$10=$A11)*$O$8:$O$10)+SUMPRODUCT(($S$8:$S$10="ENSO")*($U$8:$U$10+$A$8:$A$10=$A11)*$T$8:$T$10) -> 0.489 | X11: =CLIMATE!E11+SUMPRODUCT(($D$8:$D$10="IOD")*($F$8:$F$10+$A$8:$A$10=$A11)*$E$8:$E$10)+SUMPRODUCT(($I$8:$I$10="IOD")*($K$8:$K$10+$A$8:$A$10=$A11)*$J$8:$J$10)+SUMPRODUCT(($N$8:$N$10="IOD")*($P$8:$P$10+$A$8:$A$10=$A11)*$O$8:$O$10)+SUMPRODUCT(($S$8:$S$10="IOD")*($U$8:$U$10+$A$8:$A$10=$A11)*$T$8:$T$10) -> -1.236 | Y11: =CLIMATE!F11+SUMPRODUCT(($D$8:$D$10="NATL")*($F$8:$F$10+$A$8:$A$10=$A11)*$E$8:$E$10)+SUMPRODUCT(($I$8:$I$10="NATL")*($K$8:$K$10+$A$8:$A$10=$A11)*$J$8:$J$10)+SUMPRODUCT(($N$8:$N$10="NATL")*($P$8:$P$10+$A$8:$A$10=$A11)*$O$8:$O$10)+SUMPRODUCT(($S$8:$S$10="NATL")*($U$8:$U$10+$A$8:$A$10=$A11)*$T$8:$T$10) -> 0.309 | Z11: =CLIMATE!G11+SUMPRODUCT(($D$8:$D$10="GLOBAL")*($F$8:$F$10+$A$8:$A$10=$A11)*$E$8:$E$10)+SUMPRODUCT(($I$8:$I$10="GLOBAL")*($K$8:$K$10+$A$8:$A$10=$A11)*$J$8:$J$10)+SUMPRODUCT(($N$8:$N$10="GLOBAL")*($P$8:$P$10+$A$8:$A$10=$A11)*$O$8:$O$10)+SUMPRODUCT(($S$8:$S$10="GLOBAL")*($U$8:$U$10+$A$8:$A$10=$A11)*$T$8:$T$10) -> 0 | AA11: =CLIMATE!H11+IFERROR(INDEX($W$8:$W$47,$A11-GRAPH!B17),0)*GRAPH!B9+IFERROR(INDEX($X$8:$X$47,$A11-GRAPH!B18),0)*GRAPH!B10+IFERROR(INDEX($Y$8:$Y$47,$A11-GRAPH!B19),0)*GRAPH!B11+IFERROR(INDEX($Z$8:$Z$47,$A11-GRAPH!B20),0)*GRAPH!B12+SUMPRODUCT(($D$8:$D$10=REGIONS!$B$7)*($F$8:$F$10+$A$8:$A$10=$A11)*$E$8:$E$10)+SUMPRODUCT(($N$8:$N$10=REGIONS!$B$7)*($P$8:$P$10+$A$8:$A$10=$A11)*$O$8:$O$10) -> 0.3064 | AB11: =CLIMATE!I11+IFERROR(INDEX($W$8:$W$47,$A11-GRAPH!C17),0)*GRAPH!C9+IFERROR(INDEX($X$8:$X$47,$A11-GRAPH!C18),0)*GRAPH!C10+IFERROR(INDEX($Y$8:$Y$47,$A11-GRAPH!C19),0)*GRAPH!C11+IFERROR(INDEX($Z$8:$Z$47,$A11-GRAPH!C20),0)*GRAPH!C12+SUMPRODUCT(($D$8:$D$10=REGIONS!$B$8)*($F$8:$F$10+$A$8:$A$10=$A11)*$E$8:$E$10)+SUMPRODUCT(($N$8:$N$10=REGIONS!$B$8)*($P$8:$P$10+$A$8:$A$10=$A11)*$O$8:$O$10) -> -0.3707 | AC11: =CLIMATE!J11+IFERROR(INDEX($W$8:$W$47,$A11-GRAPH!D17),0)*GRAPH!D9+IFERROR(INDEX($X$8:$X$47,$A11-GRAPH!D18),0)*GRAPH!D10+IFERROR(INDEX($Y$8:$Y$47,$A11-GRAPH!D19),0)*GRAPH!D11+IFERROR(INDEX($Z$8:$Z$47,$A11-GRAPH!D20),0)*GRAPH!D12+SUMPRODUCT(($D$8:$D$10=REGIONS!$B$9)*($F$8:$F$10+$A$8:$A$10=$A11)*$E$8:$E$10)+SUMPRODUCT(($N$8:$N$10=REGIONS!$B$9)*($P$8:$P$10+$A$8:$A$10=$A11)*$O$8:$O$10) -> 0.627 | AD11: =CLIMATE!K11+IFERROR(INDEX($W$8:$W$47,$A11-GRAPH!E17),0)*GRAPH!E9+IFERROR(INDEX($X$8:$X$47,$A11-GRAPH!E18),0)*GRAPH!E10+IFERROR(INDEX($Y$8:$Y$47,$A11-GRAPH!E19),0)*GRAPH!E11+IFERROR(INDEX($Z$8:$Z$47,$A11-GRAPH!E20),0)*GRAPH!E12+SUMPRODUCT(($D$8:$D$10=REGIONS!$B$10)*($F$8:$F$10+$A$8:$A$10=$A11)*$E$8:$E$10)+SUMPRODUCT(($N$8:$N$10=REGIONS!$B$10)*($P$8:$P$10+$A$8:$A$10=$A11)*$O$8:$O$10) -> -0.7368 | AE11: =CLIMATE!L11+IFERROR(INDEX($W$8:$W$47,$A11-GRAPH!F17),0)*GRAPH!F9+IFERROR(INDEX($X$8:$X$47,$A11-GRAPH!F18),0)*GRAPH!F10+IFERROR(INDEX($Y$8:$Y$47,$A11-GRAPH!F19),0)*GRAPH!F11+IFERROR(INDEX($Z$8:$Z$47,$A11-GRAPH!F20),0)*GRAPH!F12+SUMPRODUCT(($D$8:$D$10=REGIONS!$B$11)*($F$8:$F$10+$A$8:$A$10=$A11)*$E$8:$E$10)+SUMPRODUCT(($N$8:$N$10=REGIONS!$B$11)*($P$8:$P$10+$A$8:$A$10=$A11)*$O$8:$O$10) -> -0.2841 | AF11: =CLIMATE!M11+IFERROR(INDEX($W$8:$W$47,$A11-GRAPH!G17),0)*GRAPH!G9+IFERROR(INDEX($X$8:$X$47,$A11-GRAPH!G18),0)*GRAPH!G10+IFERROR(INDEX($Y$8:$Y$47,$A11-GRAPH!G19),0)*GRAPH!G11+IFERROR(INDEX($Z$8:$Z$47,$A11-GRAPH!G20),0)*GRAPH!G12+SUMPRODUCT(($D$8:$D$10=REGIONS!$B$12)*($F$8:$F$10+$A$8:$A$10=$A11)*$E$8:$E$10)+SUMPRODUCT(($N$8:$N$10=REGIONS!$B$12)*($P$8:$P$10+$A$8:$A$10=$A11)*$O$8:$O$10) -> -0.3703 | AG11: =CLIMATE!N11+IFERROR(INDEX($W$8:$W$47,$A11-GRAPH!H17),0)*GRAPH!H9+IFERROR(INDEX($X$8:$X$47,$A11-GRAPH!H18),0)*GRAPH!H10+IFERROR(INDEX($Y$8:$Y$47,$A11-GRAPH!H19),0)*GRAPH!H11+IFERROR(INDEX($Z$8:$Z$47,$A11-GRAPH!H20),0)*GRAPH!H12+SUMPRODUCT(($D$8:$D$10=REGIONS!$B$13)*($F$8:$F$10+$A$8:$A$10=$A11)*$E$8:$E$10)+SUMPRODUCT(($N$8:$N$10=REGIONS!$B$13)*($P$8:$P$10+$A$8:$A$10=$A11)*$O$8:$O$10) -> -0.6682 | AH11: =CLIMATE!O11+IFERROR(INDEX($W$8:$W$47,$A11-GRAPH!I17),0)*GRAPH!I9+IFERROR(INDEX($X$8:$X$47,$A11-GRAPH!I18),0)*GRAPH!I10+IFERROR(INDEX($Y$8:$Y$47,$A11-GRAPH!I19),0)*GRAPH!I11+IFERROR(INDEX($Z$8:$Z$47,$A11-GRAPH!I20),0)*GRAPH!I12+SUMPRODUCT(($D$8:$D$10=REGIONS!$B$14)*($F$8:$F$10+$A$8:$A$10=$A11)*$E$8:$E$10)+SUMPRODUCT(($N$8:$N$10=REGIONS!$B$14)*($P$8:$P$10+$A$8:$A$10=$A11)*$O$8:$O$10) -> 0.1482 | AI11: =REGIONS!$F$7*(1+ASSUMPTIONS!$B$19*$A11) -> 0.8192 | AJ11: =REGIONS!$F$8*(1+ASSUMPTIONS!$B$19*$A11) -> 0.9216 | AK11: =REGIONS!$F$9*(1+ASSUMPTIONS!$B$19*$A11) -> 0.9216 | AL11: =REGIONS!$F$10*(1+ASSUMPTIONS!$B$19*$A11) -> 0.7168 | AM11: =REGIONS!$F$11*(1+ASSUMPTIONS!$B$19*$A11) -> 0.7168 | AN11: =REGIONS!$F$12*(1+ASSUMPTIONS!$B$19*$A11) -> 1.1264 | AO11: =REGIONS!$F$13*(1+ASSUMPTIONS!$B$19*$A11) -> 1.2288 | AP11: =REGIONS!$F$14*(1+ASSUMPTIONS!$B$19*$A11) -> 1.2288 | AQ11: =SUMPRODUCT(($D$8:$D$47=REGIONS!$B$7)*($A$8:$A$47<=$A11)*$L$8:$L$47)+SUMPRODUCT(($N$8:$N$47=REGIONS!$B$7)*($A$8:$A$47<=$A11)*$V$8:$V$47) -> 0 | AR11: =SUMPRODUCT(($D$8:$D$47=REGIONS!$B$8)*($A$8:$A$47<=$A11)*$L$8:$L$47)+SUMPRODUCT(($N$8:$N$47=REGIONS!$B$8)*($A$8:$A$47<=$A11)*$V$8:$V$47) -> 0 | AS11: =SUMPRODUCT(($D$8:$D$47=REGIONS!$B$9)*($A$8:$A$47<=$A11)*$L$8:$L$47)+SUMPRODUCT(($N$8:$N$47=REGIONS!$B$9)*($A$8:$A$47<=$A11)*$V$8:$V$47) -> 0 | AT11: =SUMPRODUCT(($D$8:$D$47=REGIONS!$B$10)*($A$8:$A$47<=$A11)*$L$8:$L$47)+SUMPRODUCT(($N$8:$N$47=REGIONS!$B$10)*($A$8:$A$47<=$A11)*$V$8:$V$47) -> 0 | AU11: =SUMPRODUCT(($D$8:$D$47=REGIONS!$B$11)*($A$8:$A$47<=$A11)*$L$8:$L$47)+SUMPRODUCT(($N$8:$N$47=REGIONS!$B$11)*($A$8:$A$47<=$A11)*$V$8:$V$47) -> 0 | AV11: =SUMPRODUCT(($D$8:$D$47=REGIONS!$B$12)*($A$8:$A$47<=$A11)*$L$8:$L$47)+SUMPRODUCT(($N$8:$N$47=REGIONS!$B$12)*($A$8:$A$47<=$A11)*$V$8:$V$47) -> 0 | AW11: =SUMPRODUCT(($D$8:$D$47=REGIONS!$B$13)*($A$8:$A$47<=$A11)*$L$8:$L$47)+SUMPRODUCT(($N$8:$N$47=REGIONS!$B$13)*($A$8:$A$47<=$A11)*$V$8:$V$47) -> 0 | AX11: =SUMPRODUCT(($D$8:$D$47=REGIONS!$B$14)*($A$8:$A$47<=$A11)*$L$8:$L$47)+SUMPRODUCT(($N$8:$N$47=REGIONS!$B$14)*($A$8:$A$47<=$A11)*$V$8:$V$47) -> 0 | AY11: =MAX(0,MIN(135,100-(MAX(0,-$AA11)*REGIONS!$E$7*ASSUMPTIONS!$B$7+MAX(0,$AA11-ASSUMPTIONS!$B$9)*REGIONS!$E$7*ASSUMPTIONS!$B$8)*(1-$AQ11/100))) -> 100 | AZ11: =MAX(0,MIN(135,100-(MAX(0,-$AB11)*REGIONS!$E$8*ASSUMPTIONS!$B$7+MAX(0,$AB11-ASSUMPTIONS!$B$9)*REGIONS!$E$8*ASSUMPTIONS!$B$8)*(1-$AR11/100))) -> 94.29122 | BA11: =MAX(0,MIN(135,100-(MAX(0,-$AC11)*REGIONS!$E$9*ASSUMPTIONS!$B$7+MAX(0,$AC11-ASSUMPTIONS!$B$9)*REGIONS!$E$9*ASSUMPTIONS!$B$8)*(1-$AS11/100))) -> 100 | BB11: =MAX(0,MIN(135,100-(MAX(0,-$AD11)*REGIONS!$E$10*ASSUMPTIONS!$B$7+MAX(0,$AD11-ASSUMPTIONS!$B$9)*REGIONS!$E$10*ASSUMPTIONS!$B$8)*(1-$AT11/100))) -> 87.62176 | BC11: =MAX(0,MIN(135,100-(MAX(0,-$AE11)*REGIONS!$E$11*ASSUMPTIONS!$B$7+MAX(0,$AE11-ASSUMPTIONS!$B$9)*REGIONS!$E$11*ASSUMPTIONS!$B$8)*(1-$AU11/100))) -> 95.62486 | BD11: =MAX(0,MIN(135,100-(MAX(0,-$AF11)*REGIONS!$E$12*ASSUMPTIONS!$B$7+MAX(0,$AF11-ASSUMPTIONS!$B$9)*REGIONS!$E$12*ASSUMPTIONS!$B$8)*(1-$AV11/100))) -> 93.26054 | BE11: =MAX(0,MIN(135,100-(MAX(0,-$AG11)*REGIONS!$E$13*ASSUMPTIONS!$B$7+MAX(0,$AG11-ASSUMPTIONS!$B$9)*REGIONS!$E$13*ASSUMPTIONS!$B$8)*(1-$AW11/100))) -> 86.90328 | BF11: =MAX(0,MIN(135,100-(MAX(0,-$AH11)*REGIONS!$E$14*ASSUMPTIONS!$B$7+MAX(0,$AH11-ASSUMPTIONS!$B$9)*REGIONS!$E$14*ASSUMPTIONS!$B$8)*(1-$AX11/100))) -> 100 | BG11: =$AY11*REGIONS!$D$7/100+$AZ11*REGIONS!$D$8/100+$BA11*REGIONS!$D$9/100+$BB11*REGIONS!$D$10/100+$BC11*REGIONS!$D$11/100+$BD11*REGIONS!$D$12/100+$BE11*REGIONS!$D$13/100+$BF11*REGIONS!$D$14/100 -> 95.07593 | BH11: =100*(100/MAX(1,$BG11))^ASSUMPTIONS!$B$10 -> 109.51484 | BI11: =$AY11*$BH11/100*ASSUMPTIONS!$B$11 -> 93.08761 | BJ11: =MAX(0,ABS($AA11)-$AI11*ASSUMPTIONS!$B$24)*REGIONS!$D$7/100+MAX(0,ABS($AB11)-$AJ11*ASSUMPTIONS!$B$24)*REGIONS!$D$8/100+MAX(0,ABS($AC11)-$AK11*ASSUMPTIONS!$B$24)*REGIONS!$D$9/100+MAX(0,ABS($AD11)-$AL11*ASSUMPTIONS!$B$24)*REGIONS!$D$10/100+MAX(0,ABS($AE11)-$AM11*ASSUMPTIONS!$B$24)*REGIONS!$D$11/100+MAX(0,ABS($AF11)-$AN11*ASSUMPTIONS!$B$24)*REGIONS!$D$12/100+MAX(0,ABS($AG11)-$AO11*ASSUMPTIONS!$B$24)*REGIONS!$D$13/100+MAX(0,ABS($AH11)-$AP11*ASSUMPTIONS!$B$24)*REGIONS!$D$14/100 -> 0.035856 | BK11: =MIN(ASSUMPTIONS!$B$14,ASSUMPTIONS!$B$12+$BJ11*ASSUMPTIONS!$B$13) -> 29.505952 | BL11: =$H11+$R11 -> 0 | BM11: =PLAY!$H11 -> 0 | BN11: =$BI11*ASSUMPTIONS!$B$15+$BK11*ASSUMPTIONS!$B$16 -> 37.72587 | BO11: =$BO10+$BN11-$BL11-$BM11-ASSUMPTIONS!$B$23 -> 112.37145 | BP11: =(SUMPRODUCT(($F$8:$F$10+$A$8:$A$10=$A11)*($C$8:$C$10<>"NONE")*$G$8:$G$10)+SUMPRODUCT(($P$8:$P$10+$A$8:$A$10=$A11)*($M$8:$M$10<>"NONE")*$Q$8:$Q$10))*(1+ASSUMPTIONS!$B$22*(MAX(0,ABS($AA11)/$AI11-1)+MAX(0,ABS($AB11)/$AJ11-1)+MAX(0,ABS($AC11)/$AK11-1)+MAX(0,ABS($AD11)/$AL11-1)+MAX(0,ABS($AE11)/$AM11-1)+MAX(0,ABS($AF11)/$AN11-1)+MAX(0,ABS($AG11)/$AO11-1)+MAX(0,ABS($AH11)/$AP11-1))/8) -> 0 | BQ11: =MAX(0,$BQ10*(1-ASSUMPTIONS!$B$18)+$BP11-$BM11*ASSUMPTIONS!$B$17) -> 1.9464458
A12: 5 | B12: =CLIMATE!B12 -> 1947 | C12: =IFERROR(INDEX(CAPABILITIES!$B$7:$B$15,MATCH(PLAY!$D12,CAPABILITIES!$A$7:$A$15,0)),"NONE") -> NONE | D12: =IFERROR(IF(INDEX(CAPABILITIES!$B$7:$B$15,MATCH(PLAY!$D12,CAPABILITIES!$A$7:$A$15,0))="DRIVER",INDEX(CAPABILITIES!$C$7:$C$15,MATCH(PLAY!$D12,CAPABILITIES!$A$7:$A$15,0)),PLAY!$E12),"") -> 0 | E12: =IFERROR(INDEX(CAPABILITIES!$D$7:$D$15,MATCH(PLAY!$D12,CAPABILITIES!$A$7:$A$15,0))*IF(INDEX(CAPABILITIES!$K$7:$K$15,MATCH(PLAY!$D12,CAPABILITIES!$A$7:$A$15,0))="Y",IF(IFERROR(INDEX($AA11:$AH11,MATCH(PLAY!$E12,REGIONS!$B$7:$B$14,0)),0)<ASSUMPTIONS!$B$20,1,ASSUMPTIONS!$B$21),1),0) -> 0 | F12: =IFERROR(INDEX(CAPABILITIES!$E$7:$E$15,MATCH(PLAY!$D12,CAPABILITIES!$A$7:$A$15,0)),0) -> 0 | G12: =IFERROR(INDEX(CAPABILITIES!$F$7:$F$15,MATCH(PLAY!$D12,CAPABILITIES!$A$7:$A$15,0)),0) -> 0 | H12: =IFERROR(INDEX(CAPABILITIES!$G$7:$G$15,MATCH(PLAY!$D12,CAPABILITIES!$A$7:$A$15,0)),0) -> 0 | I12: =IFERROR(INDEX(CAPABILITIES!$H$7:$H$15,MATCH(PLAY!$D12,CAPABILITIES!$A$7:$A$15,0)),"") -> 0 | J12: =IFERROR(INDEX(CAPABILITIES!$D$7:$D$15,MATCH(PLAY!$D12,CAPABILITIES!$A$7:$A$15,0))*INDEX(CAPABILITIES!$I$7:$I$15,MATCH(PLAY!$D12,CAPABILITIES!$A$7:$A$15,0)),0) -> 0 | K12: =IFERROR(INDEX(CAPABILITIES!$E$7:$E$15,MATCH(PLAY!$D12,CAPABILITIES!$A$7:$A$15,0))+INDEX(CAPABILITIES!$J$7:$J$15,MATCH(PLAY!$D12,CAPABILITIES!$A$7:$A$15,0)),0) -> 0 | L12: =IFERROR(INDEX(CAPABILITIES!$L$7:$L$15,MATCH(PLAY!$D12,CAPABILITIES!$A$7:$A$15,0)),0) -> 0 | M12: =IFERROR(INDEX(CAPABILITIES!$B$7:$B$15,MATCH(PLAY!$F12,CAPABILITIES!$A$7:$A$15,0)),"NONE") -> NONE | N12: =IFERROR(IF(INDEX(CAPABILITIES!$B$7:$B$15,MATCH(PLAY!$F12,CAPABILITIES!$A$7:$A$15,0))="DRIVER",INDEX(CAPABILITIES!$C$7:$C$15,MATCH(PLAY!$F12,CAPABILITIES!$A$7:$A$15,0)),PLAY!$G12),"") -> 0 | O12: =IFERROR(INDEX(CAPABILITIES!$D$7:$D$15,MATCH(PLAY!$F12,CAPABILITIES!$A$7:$A$15,0))*IF(INDEX(CAPABILITIES!$K$7:$K$15,MATCH(PLAY!$F12,CAPABILITIES!$A$7:$A$15,0))="Y",IF(IFERROR(INDEX($AA11:$AH11,MATCH(PLAY!$G12,REGIONS!$B$7:$B$14,0)),0)<ASSUMPTIONS!$B$20,1,ASSUMPTIONS!$B$21),1),0) -> 0 | P12: =IFERROR(INDEX(CAPABILITIES!$E$7:$E$15,MATCH(PLAY!$F12,CAPABILITIES!$A$7:$A$15,0)),0) -> 0 | Q12: =IFERROR(INDEX(CAPABILITIES!$F$7:$F$15,MATCH(PLAY!$F12,CAPABILITIES!$A$7:$A$15,0)),0) -> 0 | R12: =IFERROR(INDEX(CAPABILITIES!$G$7:$G$15,MATCH(PLAY!$F12,CAPABILITIES!$A$7:$A$15,0)),0) -> 0 | S12: =IFERROR(INDEX(CAPABILITIES!$H$7:$H$15,MATCH(PLAY!$F12,CAPABILITIES!$A$7:$A$15,0)),"") -> 0 | T12: =IFERROR(INDEX(CAPABILITIES!$D$7:$D$15,MATCH(PLAY!$F12,CAPABILITIES!$A$7:$A$15,0))*INDEX(CAPABILITIES!$I$7:$I$15,MATCH(PLAY!$F12,CAPABILITIES!$A$7:$A$15,0)),0) -> 0 | U12: =IFERROR(INDEX(CAPABILITIES!$E$7:$E$15,MATCH(PLAY!$F12,CAPABILITIES!$A$7:$A$15,0))+INDEX(CAPABILITIES!$J$7:$J$15,MATCH(PLAY!$F12,CAPABILITIES!$A$7:$A$15,0)),0) -> 0 | V12: =IFERROR(INDEX(CAPABILITIES!$L$7:$L$15,MATCH(PLAY!$F12,CAPABILITIES!$A$7:$A$15,0)),0) -> 0 | W12: =CLIMATE!D12+SUMPRODUCT(($D$8:$D$11="ENSO")*($F$8:$F$11+$A$8:$A$11=$A12)*$E$8:$E$11)+SUMPRODUCT(($I$8:$I$11="ENSO")*($K$8:$K$11+$A$8:$A$11=$A12)*$J$8:$J$11)+SUMPRODUCT(($N$8:$N$11="ENSO")*($P$8:$P$11+$A$8:$A$11=$A12)*$O$8:$O$11)+SUMPRODUCT(($S$8:$S$11="ENSO")*($U$8:$U$11+$A$8:$A$11=$A12)*$T$8:$T$11) -> 0.702 | X12: =CLIMATE!E12+SUMPRODUCT(($D$8:$D$11="IOD")*($F$8:$F$11+$A$8:$A$11=$A12)*$E$8:$E$11)+SUMPRODUCT(($I$8:$I$11="IOD")*($K$8:$K$11+$A$8:$A$11=$A12)*$J$8:$J$11)+SUMPRODUCT(($N$8:$N$11="IOD")*($P$8:$P$11+$A$8:$A$11=$A12)*$O$8:$O$11)+SUMPRODUCT(($S$8:$S$11="IOD")*($U$8:$U$11+$A$8:$A$11=$A12)*$T$8:$T$11) -> -0.658 | Y12: =CLIMATE!F12+SUMPRODUCT(($D$8:$D$11="NATL")*($F$8:$F$11+$A$8:$A$11=$A12)*$E$8:$E$11)+SUMPRODUCT(($I$8:$I$11="NATL")*($K$8:$K$11+$A$8:$A$11=$A12)*$J$8:$J$11)+SUMPRODUCT(($N$8:$N$11="NATL")*($P$8:$P$11+$A$8:$A$11=$A12)*$O$8:$O$11)+SUMPRODUCT(($S$8:$S$11="NATL")*($U$8:$U$11+$A$8:$A$11=$A12)*$T$8:$T$11) -> 0.547 | Z12: =CLIMATE!G12+SUMPRODUCT(($D$8:$D$11="GLOBAL")*($F$8:$F$11+$A$8:$A$11=$A12)*$E$8:$E$11)+SUMPRODUCT(($I$8:$I$11="GLOBAL")*($K$8:$K$11+$A$8:$A$11=$A12)*$J$8:$J$11)+SUMPRODUCT(($N$8:$N$11="GLOBAL")*($P$8:$P$11+$A$8:$A$11=$A12)*$O$8:$O$11)+SUMPRODUCT(($S$8:$S$11="GLOBAL")*($U$8:$U$11+$A$8:$A$11=$A12)*$T$8:$T$11) -> 0 | AA12: =CLIMATE!H12+IFERROR(INDEX($W$8:$W$47,$A12-GRAPH!B17),0)*GRAPH!B9+IFERROR(INDEX($X$8:$X$47,$A12-GRAPH!B18),0)*GRAPH!B10+IFERROR(INDEX($Y$8:$Y$47,$A12-GRAPH!B19),0)*GRAPH!B11+IFERROR(INDEX($Z$8:$Z$47,$A12-GRAPH!B20),0)*GRAPH!B12+SUMPRODUCT(($D$8:$D$11=REGIONS!$B$7)*($F$8:$F$11+$A$8:$A$11=$A12)*$E$8:$E$11)+SUMPRODUCT(($N$8:$N$11=REGIONS!$B$7)*($P$8:$P$11+$A$8:$A$11=$A12)*$O$8:$O$11) -> -0.2012 | AB12: =CLIMATE!I12+IFERROR(INDEX($W$8:$W$47,$A12-GRAPH!C17),0)*GRAPH!C9+IFERROR(INDEX($X$8:$X$47,$A12-GRAPH!C18),0)*GRAPH!C10+IFERROR(INDEX($Y$8:$Y$47,$A12-GRAPH!C19),0)*GRAPH!C11+IFERROR(INDEX($Z$8:$Z$47,$A12-GRAPH!C20),0)*GRAPH!C12+SUMPRODUCT(($D$8:$D$11=REGIONS!$B$8)*($F$8:$F$11+$A$8:$A$11=$A12)*$E$8:$E$11)+SUMPRODUCT(($N$8:$N$11=REGIONS!$B$8)*($P$8:$P$11+$A$8:$A$11=$A12)*$O$8:$O$11) -> -0.3746 | AC12: =CLIMATE!J12+IFERROR(INDEX($W$8:$W$47,$A12-GRAPH!D17),0)*GRAPH!D9+IFERROR(INDEX($X$8:$X$47,$A12-GRAPH!D18),0)*GRAPH!D10+IFERROR(INDEX($Y$8:$Y$47,$A12-GRAPH!D19),0)*GRAPH!D11+IFERROR(INDEX($Z$8:$Z$47,$A12-GRAPH!D20),0)*GRAPH!D12+SUMPRODUCT(($D$8:$D$11=REGIONS!$B$9)*($F$8:$F$11+$A$8:$A$11=$A12)*$E$8:$E$11)+SUMPRODUCT(($N$8:$N$11=REGIONS!$B$9)*($P$8:$P$11+$A$8:$A$11=$A12)*$O$8:$O$11) -> 0.2085 | AD12: =CLIMATE!K12+IFERROR(INDEX($W$8:$W$47,$A12-GRAPH!E17),0)*GRAPH!E9+IFERROR(INDEX($X$8:$X$47,$A12-GRAPH!E18),0)*GRAPH!E10+IFERROR(INDEX($Y$8:$Y$47,$A12-GRAPH!E19),0)*GRAPH!E11+IFERROR(INDEX($Z$8:$Z$47,$A12-GRAPH!E20),0)*GRAPH!E12+SUMPRODUCT(($D$8:$D$11=REGIONS!$B$10)*($F$8:$F$11+$A$8:$A$11=$A12)*$E$8:$E$11)+SUMPRODUCT(($N$8:$N$11=REGIONS!$B$10)*($P$8:$P$11+$A$8:$A$11=$A12)*$O$8:$O$11) -> -0.6115 | AE12: =CLIMATE!L12+IFERROR(INDEX($W$8:$W$47,$A12-GRAPH!F17),0)*GRAPH!F9+IFERROR(INDEX($X$8:$X$47,$A12-GRAPH!F18),0)*GRAPH!F10+IFERROR(INDEX($Y$8:$Y$47,$A12-GRAPH!F19),0)*GRAPH!F11+IFERROR(INDEX($Z$8:$Z$47,$A12-GRAPH!F20),0)*GRAPH!F12+SUMPRODUCT(($D$8:$D$11=REGIONS!$B$11)*($F$8:$F$11+$A$8:$A$11=$A12)*$E$8:$E$11)+SUMPRODUCT(($N$8:$N$11=REGIONS!$B$11)*($P$8:$P$11+$A$8:$A$11=$A12)*$O$8:$O$11) -> -0.4571 | AF12: =CLIMATE!M12+IFERROR(INDEX($W$8:$W$47,$A12-GRAPH!G17),0)*GRAPH!G9+IFERROR(INDEX($X$8:$X$47,$A12-GRAPH!G18),0)*GRAPH!G10+IFERROR(INDEX($Y$8:$Y$47,$A12-GRAPH!G19),0)*GRAPH!G11+IFERROR(INDEX($Z$8:$Z$47,$A12-GRAPH!G20),0)*GRAPH!G12+SUMPRODUCT(($D$8:$D$11=REGIONS!$B$12)*($F$8:$F$11+$A$8:$A$11=$A12)*$E$8:$E$11)+SUMPRODUCT(($N$8:$N$11=REGIONS!$B$12)*($P$8:$P$11+$A$8:$A$11=$A12)*$O$8:$O$11) -> 0.0845 | AG12: =CLIMATE!N12+IFERROR(INDEX($W$8:$W$47,$A12-GRAPH!H17),0)*GRAPH!H9+IFERROR(INDEX($X$8:$X$47,$A12-GRAPH!H18),0)*GRAPH!H10+IFERROR(INDEX($Y$8:$Y$47,$A12-GRAPH!H19),0)*GRAPH!H11+IFERROR(INDEX($Z$8:$Z$47,$A12-GRAPH!H20),0)*GRAPH!H12+SUMPRODUCT(($D$8:$D$11=REGIONS!$B$13)*($F$8:$F$11+$A$8:$A$11=$A12)*$E$8:$E$11)+SUMPRODUCT(($N$8:$N$11=REGIONS!$B$13)*($P$8:$P$11+$A$8:$A$11=$A12)*$O$8:$O$11) -> -0.3204 | AH12: =CLIMATE!O12+IFERROR(INDEX($W$8:$W$47,$A12-GRAPH!I17),0)*GRAPH!I9+IFERROR(INDEX($X$8:$X$47,$A12-GRAPH!I18),0)*GRAPH!I10+IFERROR(INDEX($Y$8:$Y$47,$A12-GRAPH!I19),0)*GRAPH!I11+IFERROR(INDEX($Z$8:$Z$47,$A12-GRAPH!I20),0)*GRAPH!I12+SUMPRODUCT(($D$8:$D$11=REGIONS!$B$14)*($F$8:$F$11+$A$8:$A$11=$A12)*$E$8:$E$11)+SUMPRODUCT(($N$8:$N$11=REGIONS!$B$14)*($P$8:$P$11+$A$8:$A$11=$A12)*$O$8:$O$11) -> -0.986 | AI12: =REGIONS!$F$7*(1+ASSUMPTIONS!$B$19*$A12) -> 0.824 | AJ12: =REGIONS!$F$8*(1+ASSUMPTIONS!$B$19*$A12) -> 0.927 | AK12: =REGIONS!$F$9*(1+ASSUMPTIONS!$B$19*$A12) -> 0.927 | AL12: =REGIONS!$F$10*(1+ASSUMPTIONS!$B$19*$A12) -> 0.721 | AM12: =REGIONS!$F$11*(1+ASSUMPTIONS!$B$19*$A12) -> 0.721 | AN12: =REGIONS!$F$12*(1+ASSUMPTIONS!$B$19*$A12) -> 1.133 | AO12: =REGIONS!$F$13*(1+ASSUMPTIONS!$B$19*$A12) -> 1.236 | AP12: =REGIONS!$F$14*(1+ASSUMPTIONS!$B$19*$A12) -> 1.236 | AQ12: =SUMPRODUCT(($D$8:$D$47=REGIONS!$B$7)*($A$8:$A$47<=$A12)*$L$8:$L$47)+SUMPRODUCT(($N$8:$N$47=REGIONS!$B$7)*($A$8:$A$47<=$A12)*$V$8:$V$47) -> 0 | AR12: =SUMPRODUCT(($D$8:$D$47=REGIONS!$B$8)*($A$8:$A$47<=$A12)*$L$8:$L$47)+SUMPRODUCT(($N$8:$N$47=REGIONS!$B$8)*($A$8:$A$47<=$A12)*$V$8:$V$47) -> 0 | AS12: =SUMPRODUCT(($D$8:$D$47=REGIONS!$B$9)*($A$8:$A$47<=$A12)*$L$8:$L$47)+SUMPRODUCT(($N$8:$N$47=REGIONS!$B$9)*($A$8:$A$47<=$A12)*$V$8:$V$47) -> 0 | AT12: =SUMPRODUCT(($D$8:$D$47=REGIONS!$B$10)*($A$8:$A$47<=$A12)*$L$8:$L$47)+SUMPRODUCT(($N$8:$N$47=REGIONS!$B$10)*($A$8:$A$47<=$A12)*$V$8:$V$47) -> 0 | AU12: =SUMPRODUCT(($D$8:$D$47=REGIONS!$B$11)*($A$8:$A$47<=$A12)*$L$8:$L$47)+SUMPRODUCT(($N$8:$N$47=REGIONS!$B$11)*($A$8:$A$47<=$A12)*$V$8:$V$47) -> 0 | AV12: =SUMPRODUCT(($D$8:$D$47=REGIONS!$B$12)*($A$8:$A$47<=$A12)*$L$8:$L$47)+SUMPRODUCT(($N$8:$N$47=REGIONS!$B$12)*($A$8:$A$47<=$A12)*$V$8:$V$47) -> 0 | AW12: =SUMPRODUCT(($D$8:$D$47=REGIONS!$B$13)*($A$8:$A$47<=$A12)*$L$8:$L$47)+SUMPRODUCT(($N$8:$N$47=REGIONS!$B$13)*($A$8:$A$47<=$A12)*$V$8:$V$47) -> 0 | AX12: =SUMPRODUCT(($D$8:$D$47=REGIONS!$B$14)*($A$8:$A$47<=$A12)*$L$8:$L$47)+SUMPRODUCT(($N$8:$N$47=REGIONS!$B$14)*($A$8:$A$47<=$A12)*$V$8:$V$47) -> 0 | AY12: =MAX(0,MIN(135,100-(MAX(0,-$AA12)*REGIONS!$E$7*ASSUMPTIONS!$B$7+MAX(0,$AA12-ASSUMPTIONS!$B$9)*REGIONS!$E$7*ASSUMPTIONS!$B$8)*(1-$AQ12/100))) -> 97.1832 | AZ12: =MAX(0,MIN(135,100-(MAX(0,-$AB12)*REGIONS!$E$8*ASSUMPTIONS!$B$7+MAX(0,$AB12-ASSUMPTIONS!$B$9)*REGIONS!$E$8*ASSUMPTIONS!$B$8)*(1-$AR12/100))) -> 94.23116 | BA12: =MAX(0,MIN(135,100-(MAX(0,-$AC12)*REGIONS!$E$9*ASSUMPTIONS!$B$7+MAX(0,$AC12-ASSUMPTIONS!$B$9)*REGIONS!$E$9*ASSUMPTIONS!$B$8)*(1-$AS12/100))) -> 100 | BB12: =MAX(0,MIN(135,100-(MAX(0,-$AD12)*REGIONS!$E$10*ASSUMPTIONS!$B$7+MAX(0,$AD12-ASSUMPTIONS!$B$9)*REGIONS!$E$10*ASSUMPTIONS!$B$8)*(1-$AT12/100))) -> 89.7268 | BC12: =MAX(0,MIN(135,100-(MAX(0,-$AE12)*REGIONS!$E$11*ASSUMPTIONS!$B$7+MAX(0,$AE12-ASSUMPTIONS!$B$9)*REGIONS!$E$11*ASSUMPTIONS!$B$8)*(1-$AU12/100))) -> 92.96066 | BD12: =MAX(0,MIN(135,100-(MAX(0,-$AF12)*REGIONS!$E$12*ASSUMPTIONS!$B$7+MAX(0,$AF12-ASSUMPTIONS!$B$9)*REGIONS!$E$12*ASSUMPTIONS!$B$8)*(1-$AV12/100))) -> 100 | BE12: =MAX(0,MIN(135,100-(MAX(0,-$AG12)*REGIONS!$E$13*ASSUMPTIONS!$B$7+MAX(0,$AG12-ASSUMPTIONS!$B$9)*REGIONS!$E$13*ASSUMPTIONS!$B$8)*(1-$AW12/100))) -> 93.72016 | BF12: =MAX(0,MIN(135,100-(MAX(0,-$AH12)*REGIONS!$E$14*ASSUMPTIONS!$B$7+MAX(0,$AH12-ASSUMPTIONS!$B$9)*REGIONS!$E$14*ASSUMPTIONS!$B$8)*(1-$AX12/100))) -> 80.6744 | BG12: =$AY12*REGIONS!$D$7/100+$AZ12*REGIONS!$D$8/100+$BA12*REGIONS!$D$9/100+$BB12*REGIONS!$D$10/100+$BC12*REGIONS!$D$11/100+$BD12*REGIONS!$D$12/100+$BE12*REGIONS!$D$13/100+$BF12*REGIONS!$D$14/100 -> 94.283402 | BH12: =100*(100/MAX(1,$BG12))^ASSUMPTIONS!$B$10 -> 111.17741 | BI12: =$AY12*$BH12/100*ASSUMPTIONS!$B$11 -> 91.838901 | BJ12: =MAX(0,ABS($AA12)-$AI12*ASSUMPTIONS!$B$24)*REGIONS!$D$7/100+MAX(0,ABS($AB12)-$AJ12*ASSUMPTIONS!$B$24)*REGIONS!$D$8/100+MAX(0,ABS($AC12)-$AK12*ASSUMPTIONS!$B$24)*REGIONS!$D$9/100+MAX(0,ABS($AD12)-$AL12*ASSUMPTIONS!$B$24)*REGIONS!$D$10/100+MAX(0,ABS($AE12)-$AM12*ASSUMPTIONS!$B$24)*REGIONS!$D$11/100+MAX(0,ABS($AF12)-$AN12*ASSUMPTIONS!$B$24)*REGIONS!$D$12/100+MAX(0,ABS($AG12)-$AO12*ASSUMPTIONS!$B$24)*REGIONS!$D$13/100+MAX(0,ABS($AH12)-$AP12*ASSUMPTIONS!$B$24)*REGIONS!$D$14/100 -> 0.016275 | BK12: =MIN(ASSUMPTIONS!$B$14,ASSUMPTIONS!$B$12+$BJ12*ASSUMPTIONS!$B$13) -> 28.68355 | BL12: =$H12+$R12 -> 0 | BM12: =PLAY!$H12 -> 0 | BN12: =$BI12*ASSUMPTIONS!$B$15+$BK12*ASSUMPTIONS!$B$16 -> 36.835863 | BO12: =$BO11+$BN12-$BL12-$BM12-ASSUMPTIONS!$B$23 -> 117.20732 | BP12: =(SUMPRODUCT(($F$8:$F$11+$A$8:$A$11=$A12)*($C$8:$C$11<>"NONE")*$G$8:$G$11)+SUMPRODUCT(($P$8:$P$11+$A$8:$A$11=$A12)*($M$8:$M$11<>"NONE")*$Q$8:$Q$11))*(1+ASSUMPTIONS!$B$22*(MAX(0,ABS($AA12)/$AI12-1)+MAX(0,ABS($AB12)/$AJ12-1)+MAX(0,ABS($AC12)/$AK12-1)+MAX(0,ABS($AD12)/$AL12-1)+MAX(0,ABS($AE12)/$AM12-1)+MAX(0,ABS($AF12)/$AN12-1)+MAX(0,ABS($AG12)/$AO12-1)+MAX(0,ABS($AH12)/$AP12-1))/8) -> 0 | BQ12: =MAX(0,$BQ11*(1-ASSUMPTIONS!$B$18)+$BP12-$BM12*ASSUMPTIONS!$B$17) -> 1.8685879
A13: 6 | B13: =CLIMATE!B13 -> 1947 | C13: =IFERROR(INDEX(CAPABILITIES!$B$7:$B$15,MATCH(PLAY!$D13,CAPABILITIES!$A$7:$A$15,0)),"NONE") -> NONE | D13: =IFERROR(IF(INDEX(CAPABILITIES!$B$7:$B$15,MATCH(PLAY!$D13,CAPABILITIES!$A$7:$A$15,0))="DRIVER",INDEX(CAPABILITIES!$C$7:$C$15,MATCH(PLAY!$D13,CAPABILITIES!$A$7:$A$15,0)),PLAY!$E13),"") -> 0 | E13: =IFERROR(INDEX(CAPABILITIES!$D$7:$D$15,MATCH(PLAY!$D13,CAPABILITIES!$A$7:$A$15,0))*IF(INDEX(CAPABILITIES!$K$7:$K$15,MATCH(PLAY!$D13,CAPABILITIES!$A$7:$A$15,0))="Y",IF(IFERROR(INDEX($AA12:$AH12,MATCH(PLAY!$E13,REGIONS!$B$7:$B$14,0)),0)<ASSUMPTIONS!$B$20,1,ASSUMPTIONS!$B$21),1),0) -> 0 | F13: =IFERROR(INDEX(CAPABILITIES!$E$7:$E$15,MATCH(PLAY!$D13,CAPABILITIES!$A$7:$A$15,0)),0) -> 0 | G13: =IFERROR(INDEX(CAPABILITIES!$F$7:$F$15,MATCH(PLAY!$D13,CAPABILITIES!$A$7:$A$15,0)),0) -> 0 | H13: =IFERROR(INDEX(CAPABILITIES!$G$7:$G$15,MATCH(PLAY!$D13,CAPABILITIES!$A$7:$A$15,0)),0) -> 0 | I13: =IFERROR(INDEX(CAPABILITIES!$H$7:$H$15,MATCH(PLAY!$D13,CAPABILITIES!$A$7:$A$15,0)),"") -> 0 | J13: =IFERROR(INDEX(CAPABILITIES!$D$7:$D$15,MATCH(PLAY!$D13,CAPABILITIES!$A$7:$A$15,0))*INDEX(CAPABILITIES!$I$7:$I$15,MATCH(PLAY!$D13,CAPABILITIES!$A$7:$A$15,0)),0) -> 0 | K13: =IFERROR(INDEX(CAPABILITIES!$E$7:$E$15,MATCH(PLAY!$D13,CAPABILITIES!$A$7:$A$15,0))+INDEX(CAPABILITIES!$J$7:$J$15,MATCH(PLAY!$D13,CAPABILITIES!$A$7:$A$15,0)),0) -> 0 | L13: =IFERROR(INDEX(CAPABILITIES!$L$7:$L$15,MATCH(PLAY!$D13,CAPABILITIES!$A$7:$A$15,0)),0) -> 0 | M13: =IFERROR(INDEX(CAPABILITIES!$B$7:$B$15,MATCH(PLAY!$F13,CAPABILITIES!$A$7:$A$15,0)),"NONE") -> NONE | N13: =IFERROR(IF(INDEX(CAPABILITIES!$B$7:$B$15,MATCH(PLAY!$F13,CAPABILITIES!$A$7:$A$15,0))="DRIVER",INDEX(CAPABILITIES!$C$7:$C$15,MATCH(PLAY!$F13,CAPABILITIES!$A$7:$A$15,0)),PLAY!$G13),"") -> 0 | O13: =IFERROR(INDEX(CAPABILITIES!$D$7:$D$15,MATCH(PLAY!$F13,CAPABILITIES!$A$7:$A$15,0))*IF(INDEX(CAPABILITIES!$K$7:$K$15,MATCH(PLAY!$F13,CAPABILITIES!$A$7:$A$15,0))="Y",IF(IFERROR(INDEX($AA12:$AH12,MATCH(PLAY!$G13,REGIONS!$B$7:$B$14,0)),0)<ASSUMPTIONS!$B$20,1,ASSUMPTIONS!$B$21),1),0) -> 0 | P13: =IFERROR(INDEX(CAPABILITIES!$E$7:$E$15,MATCH(PLAY!$F13,CAPABILITIES!$A$7:$A$15,0)),0) -> 0 | Q13: =IFERROR(INDEX(CAPABILITIES!$F$7:$F$15,MATCH(PLAY!$F13,CAPABILITIES!$A$7:$A$15,0)),0) -> 0 | R13: =IFERROR(INDEX(CAPABILITIES!$G$7:$G$15,MATCH(PLAY!$F13,CAPABILITIES!$A$7:$A$15,0)),0) -> 0 | S13: =IFERROR(INDEX(CAPABILITIES!$H$7:$H$15,MATCH(PLAY!$F13,CAPABILITIES!$A$7:$A$15,0)),"") -> 0 | T13: =IFERROR(INDEX(CAPABILITIES!$D$7:$D$15,MATCH(PLAY!$F13,CAPABILITIES!$A$7:$A$15,0))*INDEX(CAPABILITIES!$I$7:$I$15,MATCH(PLAY!$F13,CAPABILITIES!$A$7:$A$15,0)),0) -> 0 | U13: =IFERROR(INDEX(CAPABILITIES!$E$7:$E$15,MATCH(PLAY!$F13,CAPABILITIES!$A$7:$A$15,0))+INDEX(CAPABILITIES!$J$7:$J$15,MATCH(PLAY!$F13,CAPABILITIES!$A$7:$A$15,0)),0) -> 0 | V13: =IFERROR(INDEX(CAPABILITIES!$L$7:$L$15,MATCH(PLAY!$F13,CAPABILITIES!$A$7:$A$15,0)),0) -> 0 | W13: =CLIMATE!D13+SUMPRODUCT(($D$8:$D$12="ENSO")*($F$8:$F$12+$A$8:$A$12=$A13)*$E$8:$E$12)+SUMPRODUCT(($I$8:$I$12="ENSO")*($K$8:$K$12+$A$8:$A$12=$A13)*$J$8:$J$12)+SUMPRODUCT(($N$8:$N$12="ENSO")*($P$8:$P$12+$A$8:$A$12=$A13)*$O$8:$O$12)+SUMPRODUCT(($S$8:$S$12="ENSO")*($U$8:$U$12+$A$8:$A$12=$A13)*$T$8:$T$12) -> 0.229 | X13: =CLIMATE!E13+SUMPRODUCT(($D$8:$D$12="IOD")*($F$8:$F$12+$A$8:$A$12=$A13)*$E$8:$E$12)+SUMPRODUCT(($I$8:$I$12="IOD")*($K$8:$K$12+$A$8:$A$12=$A13)*$J$8:$J$12)+SUMPRODUCT(($N$8:$N$12="IOD")*($P$8:$P$12+$A$8:$A$12=$A13)*$O$8:$O$12)+SUMPRODUCT(($S$8:$S$12="IOD")*($U$8:$U$12+$A$8:$A$12=$A13)*$T$8:$T$12) -> 0.532 | Y13: =CLIMATE!F13+SUMPRODUCT(($D$8:$D$12="NATL")*($F$8:$F$12+$A$8:$A$12=$A13)*$E$8:$E$12)+SUMPRODUCT(($I$8:$I$12="NATL")*($K$8:$K$12+$A$8:$A$12=$A13)*$J$8:$J$12)+SUMPRODUCT(($N$8:$N$12="NATL")*($P$8:$P$12+$A$8:$A$12=$A13)*$O$8:$O$12)+SUMPRODUCT(($S$8:$S$12="NATL")*($U$8:$U$12+$A$8:$A$12=$A13)*$T$8:$T$12) -> 0.941 | Z13: =CLIMATE!G13+SUMPRODUCT(($D$8:$D$12="GLOBAL")*($F$8:$F$12+$A$8:$A$12=$A13)*$E$8:$E$12)+SUMPRODUCT(($I$8:$I$12="GLOBAL")*($K$8:$K$12+$A$8:$A$12=$A13)*$J$8:$J$12)+SUMPRODUCT(($N$8:$N$12="GLOBAL")*($P$8:$P$12+$A$8:$A$12=$A13)*$O$8:$O$12)+SUMPRODUCT(($S$8:$S$12="GLOBAL")*($U$8:$U$12+$A$8:$A$12=$A13)*$T$8:$T$12) -> 0 | AA13: =CLIMATE!H13+IFERROR(INDEX($W$8:$W$47,$A13-GRAPH!B17),0)*GRAPH!B9+IFERROR(INDEX($X$8:$X$47,$A13-GRAPH!B18),0)*GRAPH!B10+IFERROR(INDEX($Y$8:$Y$47,$A13-GRAPH!B19),0)*GRAPH!B11+IFERROR(INDEX($Z$8:$Z$47,$A13-GRAPH!B20),0)*GRAPH!B12+SUMPRODUCT(($D$8:$D$12=REGIONS!$B$7)*($F$8:$F$12+$A$8:$A$12=$A13)*$E$8:$E$12)+SUMPRODUCT(($N$8:$N$12=REGIONS!$B$7)*($P$8:$P$12+$A$8:$A$12=$A13)*$O$8:$O$12) -> -0.1159 | AB13: =CLIMATE!I13+IFERROR(INDEX($W$8:$W$47,$A13-GRAPH!C17),0)*GRAPH!C9+IFERROR(INDEX($X$8:$X$47,$A13-GRAPH!C18),0)*GRAPH!C10+IFERROR(INDEX($Y$8:$Y$47,$A13-GRAPH!C19),0)*GRAPH!C11+IFERROR(INDEX($Z$8:$Z$47,$A13-GRAPH!C20),0)*GRAPH!C12+SUMPRODUCT(($D$8:$D$12=REGIONS!$B$8)*($F$8:$F$12+$A$8:$A$12=$A13)*$E$8:$E$12)+SUMPRODUCT(($N$8:$N$12=REGIONS!$B$8)*($P$8:$P$12+$A$8:$A$12=$A13)*$O$8:$O$12) -> -0.1293 | AC13: =CLIMATE!J13+IFERROR(INDEX($W$8:$W$47,$A13-GRAPH!D17),0)*GRAPH!D9+IFERROR(INDEX($X$8:$X$47,$A13-GRAPH!D18),0)*GRAPH!D10+IFERROR(INDEX($Y$8:$Y$47,$A13-GRAPH!D19),0)*GRAPH!D11+IFERROR(INDEX($Z$8:$Z$47,$A13-GRAPH!D20),0)*GRAPH!D12+SUMPRODUCT(($D$8:$D$12=REGIONS!$B$9)*($F$8:$F$12+$A$8:$A$12=$A13)*$E$8:$E$12)+SUMPRODUCT(($N$8:$N$12=REGIONS!$B$9)*($P$8:$P$12+$A$8:$A$12=$A13)*$O$8:$O$12) -> 0.2595 | AD13: =CLIMATE!K13+IFERROR(INDEX($W$8:$W$47,$A13-GRAPH!E17),0)*GRAPH!E9+IFERROR(INDEX($X$8:$X$47,$A13-GRAPH!E18),0)*GRAPH!E10+IFERROR(INDEX($Y$8:$Y$47,$A13-GRAPH!E19),0)*GRAPH!E11+IFERROR(INDEX($Z$8:$Z$47,$A13-GRAPH!E20),0)*GRAPH!E12+SUMPRODUCT(($D$8:$D$12=REGIONS!$B$10)*($F$8:$F$12+$A$8:$A$12=$A13)*$E$8:$E$12)+SUMPRODUCT(($N$8:$N$12=REGIONS!$B$10)*($P$8:$P$12+$A$8:$A$12=$A13)*$O$8:$O$12) -> -0.8956 | AE13: =CLIMATE!L13+IFERROR(INDEX($W$8:$W$47,$A13-GRAPH!F17),0)*GRAPH!F9+IFERROR(INDEX($X$8:$X$47,$A13-GRAPH!F18),0)*GRAPH!F10+IFERROR(INDEX($Y$8:$Y$47,$A13-GRAPH!F19),0)*GRAPH!F11+IFERROR(INDEX($Z$8:$Z$47,$A13-GRAPH!F20),0)*GRAPH!F12+SUMPRODUCT(($D$8:$D$12=REGIONS!$B$11)*($F$8:$F$12+$A$8:$A$12=$A13)*$E$8:$E$12)+SUMPRODUCT(($N$8:$N$12=REGIONS!$B$11)*($P$8:$P$12+$A$8:$A$12=$A13)*$O$8:$O$12) -> -0.6908 | AF13: =CLIMATE!M13+IFERROR(INDEX($W$8:$W$47,$A13-GRAPH!G17),0)*GRAPH!G9+IFERROR(INDEX($X$8:$X$47,$A13-GRAPH!G18),0)*GRAPH!G10+IFERROR(INDEX($Y$8:$Y$47,$A13-GRAPH!G19),0)*GRAPH!G11+IFERROR(INDEX($Z$8:$Z$47,$A13-GRAPH!G20),0)*GRAPH!G12+SUMPRODUCT(($D$8:$D$12=REGIONS!$B$12)*($F$8:$F$12+$A$8:$A$12=$A13)*$E$8:$E$12)+SUMPRODUCT(($N$8:$N$12=REGIONS!$B$12)*($P$8:$P$12+$A$8:$A$12=$A13)*$O$8:$O$12) -> -0.489 | AG13: =CLIMATE!N13+IFERROR(INDEX($W$8:$W$47,$A13-GRAPH!H17),0)*GRAPH!H9+IFERROR(INDEX($X$8:$X$47,$A13-GRAPH!H18),0)*GRAPH!H10+IFERROR(INDEX($Y$8:$Y$47,$A13-GRAPH!H19),0)*GRAPH!H11+IFERROR(INDEX($Z$8:$Z$47,$A13-GRAPH!H20),0)*GRAPH!H12+SUMPRODUCT(($D$8:$D$12=REGIONS!$B$13)*($F$8:$F$12+$A$8:$A$12=$A13)*$E$8:$E$12)+SUMPRODUCT(($N$8:$N$12=REGIONS!$B$13)*($P$8:$P$12+$A$8:$A$12=$A13)*$O$8:$O$12) -> -0.228 | AH13: =CLIMATE!O13+IFERROR(INDEX($W$8:$W$47,$A13-GRAPH!I17),0)*GRAPH!I9+IFERROR(INDEX($X$8:$X$47,$A13-GRAPH!I18),0)*GRAPH!I10+IFERROR(INDEX($Y$8:$Y$47,$A13-GRAPH!I19),0)*GRAPH!I11+IFERROR(INDEX($Z$8:$Z$47,$A13-GRAPH!I20),0)*GRAPH!I12+SUMPRODUCT(($D$8:$D$12=REGIONS!$B$14)*($F$8:$F$12+$A$8:$A$12=$A13)*$E$8:$E$12)+SUMPRODUCT(($N$8:$N$12=REGIONS!$B$14)*($P$8:$P$12+$A$8:$A$12=$A13)*$O$8:$O$12) -> -0.3242 | AI13: =REGIONS!$F$7*(1+ASSUMPTIONS!$B$19*$A13) -> 0.8288 | AJ13: =REGIONS!$F$8*(1+ASSUMPTIONS!$B$19*$A13) -> 0.9324 | AK13: =REGIONS!$F$9*(1+ASSUMPTIONS!$B$19*$A13) -> 0.9324 | AL13: =REGIONS!$F$10*(1+ASSUMPTIONS!$B$19*$A13) -> 0.7252 | AM13: =REGIONS!$F$11*(1+ASSUMPTIONS!$B$19*$A13) -> 0.7252 | AN13: =REGIONS!$F$12*(1+ASSUMPTIONS!$B$19*$A13) -> 1.1396 | AO13: =REGIONS!$F$13*(1+ASSUMPTIONS!$B$19*$A13) -> 1.2432 | AP13: =REGIONS!$F$14*(1+ASSUMPTIONS!$B$19*$A13) -> 1.2432 | AQ13: =SUMPRODUCT(($D$8:$D$47=REGIONS!$B$7)*($A$8:$A$47<=$A13)*$L$8:$L$47)+SUMPRODUCT(($N$8:$N$47=REGIONS!$B$7)*($A$8:$A$47<=$A13)*$V$8:$V$47) -> 0 | AR13: =SUMPRODUCT(($D$8:$D$47=REGIONS!$B$8)*($A$8:$A$47<=$A13)*$L$8:$L$47)+SUMPRODUCT(($N$8:$N$47=REGIONS!$B$8)*($A$8:$A$47<=$A13)*$V$8:$V$47) -> 0 | AS13: =SUMPRODUCT(($D$8:$D$47=REGIONS!$B$9)*($A$8:$A$47<=$A13)*$L$8:$L$47)+SUMPRODUCT(($N$8:$N$47=REGIONS!$B$9)*($A$8:$A$47<=$A13)*$V$8:$V$47) -> 0 | AT13: =SUMPRODUCT(($D$8:$D$47=REGIONS!$B$10)*($A$8:$A$47<=$A13)*$L$8:$L$47)+SUMPRODUCT(($N$8:$N$47=REGIONS!$B$10)*($A$8:$A$47<=$A13)*$V$8:$V$47) -> 0 | AU13: =SUMPRODUCT(($D$8:$D$47=REGIONS!$B$11)*($A$8:$A$47<=$A13)*$L$8:$L$47)+SUMPRODUCT(($N$8:$N$47=REGIONS!$B$11)*($A$8:$A$47<=$A13)*$V$8:$V$47) -> 0 | AV13: =SUMPRODUCT(($D$8:$D$47=REGIONS!$B$12)*($A$8:$A$47<=$A13)*$L$8:$L$47)+SUMPRODUCT(($N$8:$N$47=REGIONS!$B$12)*($A$8:$A$47<=$A13)*$V$8:$V$47) -> 0 | AW13: =SUMPRODUCT(($D$8:$D$47=REGIONS!$B$13)*($A$8:$A$47<=$A13)*$L$8:$L$47)+SUMPRODUCT(($N$8:$N$47=REGIONS!$B$13)*($A$8:$A$47<=$A13)*$V$8:$V$47) -> 0 | AX13: =SUMPRODUCT(($D$8:$D$47=REGIONS!$B$14)*($A$8:$A$47<=$A13)*$L$8:$L$47)+SUMPRODUCT(($N$8:$N$47=REGIONS!$B$14)*($A$8:$A$47<=$A13)*$V$8:$V$47) -> 0 | AY13: =MAX(0,MIN(135,100-(MAX(0,-$AA13)*REGIONS!$E$7*ASSUMPTIONS!$B$7+MAX(0,$AA13-ASSUMPTIONS!$B$9)*REGIONS!$E$7*ASSUMPTIONS!$B$8)*(1-$AQ13/100))) -> 98.3774 | AZ13: =MAX(0,MIN(135,100-(MAX(0,-$AB13)*REGIONS!$E$8*ASSUMPTIONS!$B$7+MAX(0,$AB13-ASSUMPTIONS!$B$9)*REGIONS!$E$8*ASSUMPTIONS!$B$8)*(1-$AR13/100))) -> 98.00878 | BA13: =MAX(0,MIN(135,100-(MAX(0,-$AC13)*REGIONS!$E$9*ASSUMPTIONS!$B$7+MAX(0,$AC13-ASSUMPTIONS!$B$9)*REGIONS!$E$9*ASSUMPTIONS!$B$8)*(1-$AS13/100))) -> 100 | BB13: =MAX(0,MIN(135,100-(MAX(0,-$AD13)*REGIONS!$E$10*ASSUMPTIONS!$B$7+MAX(0,$AD13-ASSUMPTIONS!$B$9)*REGIONS!$E$10*ASSUMPTIONS!$B$8)*(1-$AT13/100))) -> 84.95392 | BC13: =MAX(0,MIN(135,100-(MAX(0,-$AE13)*REGIONS!$E$11*ASSUMPTIONS!$B$7+MAX(0,$AE13-ASSUMPTIONS!$B$9)*REGIONS!$E$11*ASSUMPTIONS!$B$8)*(1-$AU13/100))) -> 89.36168 | BD13: =MAX(0,MIN(135,100-(MAX(0,-$AF13)*REGIONS!$E$12*ASSUMPTIONS!$B$7+MAX(0,$AF13-ASSUMPTIONS!$B$9)*REGIONS!$E$12*ASSUMPTIONS!$B$8)*(1-$AV13/100))) -> 91.1002 | BE13: =MAX(0,MIN(135,100-(MAX(0,-$AG13)*REGIONS!$E$13*ASSUMPTIONS!$B$7+MAX(0,$AG13-ASSUMPTIONS!$B$9)*REGIONS!$E$13*ASSUMPTIONS!$B$8)*(1-$AW13/100))) -> 95.5312 | BF13: =MAX(0,MIN(135,100-(MAX(0,-$AH13)*REGIONS!$E$14*ASSUMPTIONS!$B$7+MAX(0,$AH13-ASSUMPTIONS!$B$9)*REGIONS!$E$14*ASSUMPTIONS!$B$8)*(1-$AX13/100))) -> 93.64568 | BG13: =$AY13*REGIONS!$D$7/100+$AZ13*REGIONS!$D$8/100+$BA13*REGIONS!$D$9/100+$BB13*REGIONS!$D$10/100+$BC13*REGIONS!$D$11/100+$BD13*REGIONS!$D$12/100+$BE13*REGIONS!$D$13/100+$BF13*REGIONS!$D$14/100 -> 94.099619 | BH13: =100*(100/MAX(1,$BG13))^ASSUMPTIONS!$B$10 -> 111.56856 | BI13: =$AY13*$BH13/100*ASSUMPTIONS!$B$11 -> 93.294515 | BJ13: =MAX(0,ABS($AA13)-$AI13*ASSUMPTIONS!$B$24)*REGIONS!$D$7/100+MAX(0,ABS($AB13)-$AJ13*ASSUMPTIONS!$B$24)*REGIONS!$D$8/100+MAX(0,ABS($AC13)-$AK13*ASSUMPTIONS!$B$24)*REGIONS!$D$9/100+MAX(0,ABS($AD13)-$AL13*ASSUMPTIONS!$B$24)*REGIONS!$D$10/100+MAX(0,ABS($AE13)-$AM13*ASSUMPTIONS!$B$24)*REGIONS!$D$11/100+MAX(0,ABS($AF13)-$AN13*ASSUMPTIONS!$B$24)*REGIONS!$D$12/100+MAX(0,ABS($AG13)-$AO13*ASSUMPTIONS!$B$24)*REGIONS!$D$13/100+MAX(0,ABS($AH13)-$AP13*ASSUMPTIONS!$B$24)*REGIONS!$D$14/100 -> 0.080934 | BK13: =MIN(ASSUMPTIONS!$B$14,ASSUMPTIONS!$B$12+$BJ13*ASSUMPTIONS!$B$13) -> 31.399228 | BL13: =$H13+$R13 -> 0 | BM13: =PLAY!$H13 -> 0 | BN13: =$BI13*ASSUMPTIONS!$B$15+$BK13*ASSUMPTIONS!$B$16 -> 39.454647 | BO13: =$BO12+$BN13-$BL13-$BM13-ASSUMPTIONS!$B$23 -> 124.66196 | BP13: =(SUMPRODUCT(($F$8:$F$12+$A$8:$A$12=$A13)*($C$8:$C$12<>"NONE")*$G$8:$G$12)+SUMPRODUCT(($P$8:$P$12+$A$8:$A$12=$A13)*($M$8:$M$12<>"NONE")*$Q$8:$Q$12))*(1+ASSUMPTIONS!$B$22*(MAX(0,ABS($AA13)/$AI13-1)+MAX(0,ABS($AB13)/$AJ13-1)+MAX(0,ABS($AC13)/$AK13-1)+MAX(0,ABS($AD13)/$AL13-1)+MAX(0,ABS($AE13)/$AM13-1)+MAX(0,ABS($AF13)/$AN13-1)+MAX(0,ABS($AG13)/$AO13-1)+MAX(0,ABS($AH13)/$AP13-1))/8) -> 0 | BQ13: =MAX(0,$BQ12*(1-ASSUMPTIONS!$B$18)+$BP13-$BM13*ASSUMPTIONS!$B$17) -> 1.7938444
A14: 7 | B14: =CLIMATE!B14 -> 1947 | C14: =IFERROR(INDEX(CAPABILITIES!$B$7:$B$15,MATCH(PLAY!$D14,CAPABILITIES!$A$7:$A$15,0)),"NONE") -> NONE | D14: =IFERROR(IF(INDEX(CAPABILITIES!$B$7:$B$15,MATCH(PLAY!$D14,CAPABILITIES!$A$7:$A$15,0))="DRIVER",INDEX(CAPABILITIES!$C$7:$C$15,MATCH(PLAY!$D14,CAPABILITIES!$A$7:$A$15,0)),PLAY!$E14),"") -> 0 | E14: =IFERROR(INDEX(CAPABILITIES!$D$7:$D$15,MATCH(PLAY!$D14,CAPABILITIES!$A$7:$A$15,0))*IF(INDEX(CAPABILITIES!$K$7:$K$15,MATCH(PLAY!$D14,CAPABILITIES!$A$7:$A$15,0))="Y",IF(IFERROR(INDEX($AA13:$AH13,MATCH(PLAY!$E14,REGIONS!$B$7:$B$14,0)),0)<ASSUMPTIONS!$B$20,1,ASSUMPTIONS!$B$21),1),0) -> 0 | F14: =IFERROR(INDEX(CAPABILITIES!$E$7:$E$15,MATCH(PLAY!$D14,CAPABILITIES!$A$7:$A$15,0)),0) -> 0 | G14: =IFERROR(INDEX(CAPABILITIES!$F$7:$F$15,MATCH(PLAY!$D14,CAPABILITIES!$A$7:$A$15,0)),0) -> 0 | H14: =IFERROR(INDEX(CAPABILITIES!$G$7:$G$15,MATCH(PLAY!$D14,CAPABILITIES!$A$7:$A$15,0)),0) -> 0 | I14: =IFERROR(INDEX(CAPABILITIES!$H$7:$H$15,MATCH(PLAY!$D14,CAPABILITIES!$A$7:$A$15,0)),"") -> 0 | J14: =IFERROR(INDEX(CAPABILITIES!$D$7:$D$15,MATCH(PLAY!$D14,CAPABILITIES!$A$7:$A$15,0))*INDEX(CAPABILITIES!$I$7:$I$15,MATCH(PLAY!$D14,CAPABILITIES!$A$7:$A$15,0)),0) -> 0 | K14: =IFERROR(INDEX(CAPABILITIES!$E$7:$E$15,MATCH(PLAY!$D14,CAPABILITIES!$A$7:$A$15,0))+INDEX(CAPABILITIES!$J$7:$J$15,MATCH(PLAY!$D14,CAPABILITIES!$A$7:$A$15,0)),0) -> 0 | L14: =IFERROR(INDEX(CAPABILITIES!$L$7:$L$15,MATCH(PLAY!$D14,CAPABILITIES!$A$7:$A$15,0)),0) -> 0 | M14: =IFERROR(INDEX(CAPABILITIES!$B$7:$B$15,MATCH(PLAY!$F14,CAPABILITIES!$A$7:$A$15,0)),"NONE") -> NONE | N14: =IFERROR(IF(INDEX(CAPABILITIES!$B$7:$B$15,MATCH(PLAY!$F14,CAPABILITIES!$A$7:$A$15,0))="DRIVER",INDEX(CAPABILITIES!$C$7:$C$15,MATCH(PLAY!$F14,CAPABILITIES!$A$7:$A$15,0)),PLAY!$G14),"") -> 0 | O14: =IFERROR(INDEX(CAPABILITIES!$D$7:$D$15,MATCH(PLAY!$F14,CAPABILITIES!$A$7:$A$15,0))*IF(INDEX(CAPABILITIES!$K$7:$K$15,MATCH(PLAY!$F14,CAPABILITIES!$A$7:$A$15,0))="Y",IF(IFERROR(INDEX($AA13:$AH13,MATCH(PLAY!$G14,REGIONS!$B$7:$B$14,0)),0)<ASSUMPTIONS!$B$20,1,ASSUMPTIONS!$B$21),1),0) -> 0 | P14: =IFERROR(INDEX(CAPABILITIES!$E$7:$E$15,MATCH(PLAY!$F14,CAPABILITIES!$A$7:$A$15,0)),0) -> 0 | Q14: =IFERROR(INDEX(CAPABILITIES!$F$7:$F$15,MATCH(PLAY!$F14,CAPABILITIES!$A$7:$A$15,0)),0) -> 0 | R14: =IFERROR(INDEX(CAPABILITIES!$G$7:$G$15,MATCH(PLAY!$F14,CAPABILITIES!$A$7:$A$15,0)),0) -> 0 | S14: =IFERROR(INDEX(CAPABILITIES!$H$7:$H$15,MATCH(PLAY!$F14,CAPABILITIES!$A$7:$A$15,0)),"") -> 0 | T14: =IFERROR(INDEX(CAPABILITIES!$D$7:$D$15,MATCH(PLAY!$F14,CAPABILITIES!$A$7:$A$15,0))*INDEX(CAPABILITIES!$I$7:$I$15,MATCH(PLAY!$F14,CAPABILITIES!$A$7:$A$15,0)),0) -> 0 | U14: =IFERROR(INDEX(CAPABILITIES!$E$7:$E$15,MATCH(PLAY!$F14,CAPABILITIES!$A$7:$A$15,0))+INDEX(CAPABILITIES!$J$7:$J$15,MATCH(PLAY!$F14,CAPABILITIES!$A$7:$A$15,0)),0) -> 0 | V14: =IFERROR(INDEX(CAPABILITIES!$L$7:$L$15,MATCH(PLAY!$F14,CAPABILITIES!$A$7:$A$15,0)),0) -> 0 | W14: =CLIMATE!D14+SUMPRODUCT(($D$8:$D$13="ENSO")*($F$8:$F$13+$A$8:$A$13=$A14)*$E$8:$E$13)+SUMPRODUCT(($I$8:$I$13="ENSO")*($K$8:$K$13+$A$8:$A$13=$A14)*$J$8:$J$13)+SUMPRODUCT(($N$8:$N$13="ENSO")*($P$8:$P$13+$A$8:$A$13=$A14)*$O$8:$O$13)+SUMPRODUCT(($S$8:$S$13="ENSO")*($U$8:$U$13+$A$8:$A$13=$A14)*$T$8:$T$13) -> 0.048 | X14: =CLIMATE!E14+SUMPRODUCT(($D$8:$D$13="IOD")*($F$8:$F$13+$A$8:$A$13=$A14)*$E$8:$E$13)+SUMPRODUCT(($I$8:$I$13="IOD")*($K$8:$K$13+$A$8:$A$13=$A14)*$J$8:$J$13)+SUMPRODUCT(($N$8:$N$13="IOD")*($P$8:$P$13+$A$8:$A$13=$A14)*$O$8:$O$13)+SUMPRODUCT(($S$8:$S$13="IOD")*($U$8:$U$13+$A$8:$A$13=$A14)*$T$8:$T$13) -> 0.464 | Y14: =CLIMATE!F14+SUMPRODUCT(($D$8:$D$13="NATL")*($F$8:$F$13+$A$8:$A$13=$A14)*$E$8:$E$13)+SUMPRODUCT(($I$8:$I$13="NATL")*($K$8:$K$13+$A$8:$A$13=$A14)*$J$8:$J$13)+SUMPRODUCT(($N$8:$N$13="NATL")*($P$8:$P$13+$A$8:$A$13=$A14)*$O$8:$O$13)+SUMPRODUCT(($S$8:$S$13="NATL")*($U$8:$U$13+$A$8:$A$13=$A14)*$T$8:$T$13) -> 0.385 | Z14: =CLIMATE!G14+SUMPRODUCT(($D$8:$D$13="GLOBAL")*($F$8:$F$13+$A$8:$A$13=$A14)*$E$8:$E$13)+SUMPRODUCT(($I$8:$I$13="GLOBAL")*($K$8:$K$13+$A$8:$A$13=$A14)*$J$8:$J$13)+SUMPRODUCT(($N$8:$N$13="GLOBAL")*($P$8:$P$13+$A$8:$A$13=$A14)*$O$8:$O$13)+SUMPRODUCT(($S$8:$S$13="GLOBAL")*($U$8:$U$13+$A$8:$A$13=$A14)*$T$8:$T$13) -> 0 | AA14: =CLIMATE!H14+IFERROR(INDEX($W$8:$W$47,$A14-GRAPH!B17),0)*GRAPH!B9+IFERROR(INDEX($X$8:$X$47,$A14-GRAPH!B18),0)*GRAPH!B10+IFERROR(INDEX($Y$8:$Y$47,$A14-GRAPH!B19),0)*GRAPH!B11+IFERROR(INDEX($Z$8:$Z$47,$A14-GRAPH!B20),0)*GRAPH!B12+SUMPRODUCT(($D$8:$D$13=REGIONS!$B$7)*($F$8:$F$13+$A$8:$A$13=$A14)*$E$8:$E$13)+SUMPRODUCT(($N$8:$N$13=REGIONS!$B$7)*($P$8:$P$13+$A$8:$A$13=$A14)*$O$8:$O$13) -> 0.0333 | AB14: =CLIMATE!I14+IFERROR(INDEX($W$8:$W$47,$A14-GRAPH!C17),0)*GRAPH!C9+IFERROR(INDEX($X$8:$X$47,$A14-GRAPH!C18),0)*GRAPH!C10+IFERROR(INDEX($Y$8:$Y$47,$A14-GRAPH!C19),0)*GRAPH!C11+IFERROR(INDEX($Z$8:$Z$47,$A14-GRAPH!C20),0)*GRAPH!C12+SUMPRODUCT(($D$8:$D$13=REGIONS!$B$8)*($F$8:$F$13+$A$8:$A$13=$A14)*$E$8:$E$13)+SUMPRODUCT(($N$8:$N$13=REGIONS!$B$8)*($P$8:$P$13+$A$8:$A$13=$A14)*$O$8:$O$13) -> -0.2297 | AC14: =CLIMATE!J14+IFERROR(INDEX($W$8:$W$47,$A14-GRAPH!D17),0)*GRAPH!D9+IFERROR(INDEX($X$8:$X$47,$A14-GRAPH!D18),0)*GRAPH!D10+IFERROR(INDEX($Y$8:$Y$47,$A14-GRAPH!D19),0)*GRAPH!D11+IFERROR(INDEX($Z$8:$Z$47,$A14-GRAPH!D20),0)*GRAPH!D12+SUMPRODUCT(($D$8:$D$13=REGIONS!$B$9)*($F$8:$F$13+$A$8:$A$13=$A14)*$E$8:$E$13)+SUMPRODUCT(($N$8:$N$13=REGIONS!$B$9)*($P$8:$P$13+$A$8:$A$13=$A14)*$O$8:$O$13) -> 0.053 | AD14: =CLIMATE!K14+IFERROR(INDEX($W$8:$W$47,$A14-GRAPH!E17),0)*GRAPH!E9+IFERROR(INDEX($X$8:$X$47,$A14-GRAPH!E18),0)*GRAPH!E10+IFERROR(INDEX($Y$8:$Y$47,$A14-GRAPH!E19),0)*GRAPH!E11+IFERROR(INDEX($Z$8:$Z$47,$A14-GRAPH!E20),0)*GRAPH!E12+SUMPRODUCT(($D$8:$D$13=REGIONS!$B$10)*($F$8:$F$13+$A$8:$A$13=$A14)*$E$8:$E$13)+SUMPRODUCT(($N$8:$N$13=REGIONS!$B$10)*($P$8:$P$13+$A$8:$A$13=$A14)*$O$8:$O$13) -> 0.1745 | AE14: =CLIMATE!L14+IFERROR(INDEX($W$8:$W$47,$A14-GRAPH!F17),0)*GRAPH!F9+IFERROR(INDEX($X$8:$X$47,$A14-GRAPH!F18),0)*GRAPH!F10+IFERROR(INDEX($Y$8:$Y$47,$A14-GRAPH!F19),0)*GRAPH!F11+IFERROR(INDEX($Z$8:$Z$47,$A14-GRAPH!F20),0)*GRAPH!F12+SUMPRODUCT(($D$8:$D$13=REGIONS!$B$11)*($F$8:$F$13+$A$8:$A$13=$A14)*$E$8:$E$13)+SUMPRODUCT(($N$8:$N$13=REGIONS!$B$11)*($P$8:$P$13+$A$8:$A$13=$A14)*$O$8:$O$13) -> -0.4287 | AF14: =CLIMATE!M14+IFERROR(INDEX($W$8:$W$47,$A14-GRAPH!G17),0)*GRAPH!G9+IFERROR(INDEX($X$8:$X$47,$A14-GRAPH!G18),0)*GRAPH!G10+IFERROR(INDEX($Y$8:$Y$47,$A14-GRAPH!G19),0)*GRAPH!G11+IFERROR(INDEX($Z$8:$Z$47,$A14-GRAPH!G20),0)*GRAPH!G12+SUMPRODUCT(($D$8:$D$13=REGIONS!$B$12)*($F$8:$F$13+$A$8:$A$13=$A14)*$E$8:$E$13)+SUMPRODUCT(($N$8:$N$13=REGIONS!$B$12)*($P$8:$P$13+$A$8:$A$13=$A14)*$O$8:$O$13) -> -0.8723 | AG14: =CLIMATE!N14+IFERROR(INDEX($W$8:$W$47,$A14-GRAPH!H17),0)*GRAPH!H9+IFERROR(INDEX($X$8:$X$47,$A14-GRAPH!H18),0)*GRAPH!H10+IFERROR(INDEX($Y$8:$Y$47,$A14-GRAPH!H19),0)*GRAPH!H11+IFERROR(INDEX($Z$8:$Z$47,$A14-GRAPH!H20),0)*GRAPH!H12+SUMPRODUCT(($D$8:$D$13=REGIONS!$B$13)*($F$8:$F$13+$A$8:$A$13=$A14)*$E$8:$E$13)+SUMPRODUCT(($N$8:$N$13=REGIONS!$B$13)*($P$8:$P$13+$A$8:$A$13=$A14)*$O$8:$O$13) -> 0.0745 | AH14: =CLIMATE!O14+IFERROR(INDEX($W$8:$W$47,$A14-GRAPH!I17),0)*GRAPH!I9+IFERROR(INDEX($X$8:$X$47,$A14-GRAPH!I18),0)*GRAPH!I10+IFERROR(INDEX($Y$8:$Y$47,$A14-GRAPH!I19),0)*GRAPH!I11+IFERROR(INDEX($Z$8:$Z$47,$A14-GRAPH!I20),0)*GRAPH!I12+SUMPRODUCT(($D$8:$D$13=REGIONS!$B$14)*($F$8:$F$13+$A$8:$A$13=$A14)*$E$8:$E$13)+SUMPRODUCT(($N$8:$N$13=REGIONS!$B$14)*($P$8:$P$13+$A$8:$A$13=$A14)*$O$8:$O$13) -> 0.6906 | AI14: =REGIONS!$F$7*(1+ASSUMPTIONS!$B$19*$A14) -> 0.8336 | AJ14: =REGIONS!$F$8*(1+ASSUMPTIONS!$B$19*$A14) -> 0.9378 | AK14: =REGIONS!$F$9*(1+ASSUMPTIONS!$B$19*$A14) -> 0.9378 | AL14: =REGIONS!$F$10*(1+ASSUMPTIONS!$B$19*$A14) -> 0.7294 | AM14: =REGIONS!$F$11*(1+ASSUMPTIONS!$B$19*$A14) -> 0.7294 | AN14: =REGIONS!$F$12*(1+ASSUMPTIONS!$B$19*$A14) -> 1.1462 | AO14: =REGIONS!$F$13*(1+ASSUMPTIONS!$B$19*$A14) -> 1.2504 | AP14: =REGIONS!$F$14*(1+ASSUMPTIONS!$B$19*$A14) -> 1.2504 | AQ14: =SUMPRODUCT(($D$8:$D$47=REGIONS!$B$7)*($A$8:$A$47<=$A14)*$L$8:$L$47)+SUMPRODUCT(($N$8:$N$47=REGIONS!$B$7)*($A$8:$A$47<=$A14)*$V$8:$V$47) -> 0 | AR14: =SUMPRODUCT(($D$8:$D$47=REGIONS!$B$8)*($A$8:$A$47<=$A14)*$L$8:$L$47)+SUMPRODUCT(($N$8:$N$47=REGIONS!$B$8)*($A$8:$A$47<=$A14)*$V$8:$V$47) -> 0 | AS14: =SUMPRODUCT(($D$8:$D$47=REGIONS!$B$9)*($A$8:$A$47<=$A14)*$L$8:$L$47)+SUMPRODUCT(($N$8:$N$47=REGIONS!$B$9)*($A$8:$A$47<=$A14)*$V$8:$V$47) -> 0 | AT14: =SUMPRODUCT(($D$8:$D$47=REGIONS!$B$10)*($A$8:$A$47<=$A14)*$L$8:$L$47)+SUMPRODUCT(($N$8:$N$47=REGIONS!$B$10)*($A$8:$A$47<=$A14)*$V$8:$V$47) -> 0 | AU14: =SUMPRODUCT(($D$8:$D$47=REGIONS!$B$11)*($A$8:$A$47<=$A14)*$L$8:$L$47)+SUMPRODUCT(($N$8:$N$47=REGIONS!$B$11)*($A$8:$A$47<=$A14)*$V$8:$V$47) -> 0 | AV14: =SUMPRODUCT(($D$8:$D$47=REGIONS!$B$12)*($A$8:$A$47<=$A14)*$L$8:$L$47)+SUMPRODUCT(($N$8:$N$47=REGIONS!$B$12)*($A$8:$A$47<=$A14)*$V$8:$V$47) -> 0 | AW14: =SUMPRODUCT(($D$8:$D$47=REGIONS!$B$13)*($A$8:$A$47<=$A14)*$L$8:$L$47)+SUMPRODUCT(($N$8:$N$47=REGIONS!$B$13)*($A$8:$A$47<=$A14)*$V$8:$V$47) -> 0 | AX14: =SUMPRODUCT(($D$8:$D$47=REGIONS!$B$14)*($A$8:$A$47<=$A14)*$L$8:$L$47)+SUMPRODUCT(($N$8:$N$47=REGIONS!$B$14)*($A$8:$A$47<=$A14)*$V$8:$V$47) -> 0 | AY14: =MAX(0,MIN(135,100-(MAX(0,-$AA14)*REGIONS!$E$7*ASSUMPTIONS!$B$7+MAX(0,$AA14-ASSUMPTIONS!$B$9)*REGIONS!$E$7*ASSUMPTIONS!$B$8)*(1-$AQ14/100))) -> 100 | AZ14: =MAX(0,MIN(135,100-(MAX(0,-$AB14)*REGIONS!$E$8*ASSUMPTIONS!$B$7+MAX(0,$AB14-ASSUMPTIONS!$B$9)*REGIONS!$E$8*ASSUMPTIONS!$B$8)*(1-$AR14/100))) -> 96.46262 | BA14: =MAX(0,MIN(135,100-(MAX(0,-$AC14)*REGIONS!$E$9*ASSUMPTIONS!$B$7+MAX(0,$AC14-ASSUMPTIONS!$B$9)*REGIONS!$E$9*ASSUMPTIONS!$B$8)*(1-$AS14/100))) -> 100 | BB14: =MAX(0,MIN(135,100-(MAX(0,-$AD14)*REGIONS!$E$10*ASSUMPTIONS!$B$7+MAX(0,$AD14-ASSUMPTIONS!$B$9)*REGIONS!$E$10*ASSUMPTIONS!$B$8)*(1-$AT14/100))) -> 100 | BC14: =MAX(0,MIN(135,100-(MAX(0,-$AE14)*REGIONS!$E$11*ASSUMPTIONS!$B$7+MAX(0,$AE14-ASSUMPTIONS!$B$9)*REGIONS!$E$11*ASSUMPTIONS!$B$8)*(1-$AU14/100))) -> 93.39802 | BD14: =MAX(0,MIN(135,100-(MAX(0,-$AF14)*REGIONS!$E$12*ASSUMPTIONS!$B$7+MAX(0,$AF14-ASSUMPTIONS!$B$9)*REGIONS!$E$12*ASSUMPTIONS!$B$8)*(1-$AV14/100))) -> 84.12414 | BE14: =MAX(0,MIN(135,100-(MAX(0,-$AG14)*REGIONS!$E$13*ASSUMPTIONS!$B$7+MAX(0,$AG14-ASSUMPTIONS!$B$9)*REGIONS!$E$13*ASSUMPTIONS!$B$8)*(1-$AW14/100))) -> 100 | BF14: =MAX(0,MIN(135,100-(MAX(0,-$AH14)*REGIONS!$E$14*ASSUMPTIONS!$B$7+MAX(0,$AH14-ASSUMPTIONS!$B$9)*REGIONS!$E$14*ASSUMPTIONS!$B$8)*(1-$AX14/100))) -> 100 | BG14: =$AY14*REGIONS!$D$7/100+$AZ14*REGIONS!$D$8/100+$BA14*REGIONS!$D$9/100+$BB14*REGIONS!$D$10/100+$BC14*REGIONS!$D$11/100+$BD14*REGIONS!$D$12/100+$BE14*REGIONS!$D$13/100+$BF14*REGIONS!$D$14/100 -> 97.530471 | BH14: =100*(100/MAX(1,$BG14))^ASSUMPTIONS!$B$10 -> 104.60379 | BI14: =$AY14*$BH14/100*ASSUMPTIONS!$B$11 -> 88.913221 | BJ14: =MAX(0,ABS($AA14)-$AI14*ASSUMPTIONS!$B$24)*REGIONS!$D$7/100+MAX(0,ABS($AB14)-$AJ14*ASSUMPTIONS!$B$24)*REGIONS!$D$8/100+MAX(0,ABS($AC14)-$AK14*ASSUMPTIONS!$B$24)*REGIONS!$D$9/100+MAX(0,ABS($AD14)-$AL14*ASSUMPTIONS!$B$24)*REGIONS!$D$10/100+MAX(0,ABS($AE14)-$AM14*ASSUMPTIONS!$B$24)*REGIONS!$D$11/100+MAX(0,ABS($AF14)-$AN14*ASSUMPTIONS!$B$24)*REGIONS!$D$12/100+MAX(0,ABS($AG14)-$AO14*ASSUMPTIONS!$B$24)*REGIONS!$D$13/100+MAX(0,ABS($AH14)-$AP14*ASSUMPTIONS!$B$24)*REGIONS!$D$14/100 -> 0.0008855 | BK14: =MIN(ASSUMPTIONS!$B$14,ASSUMPTIONS!$B$12+$BJ14*ASSUMPTIONS!$B$13) -> 28.037191 | BL14: =$H14+$R14 -> 0 | BM14: =PLAY!$H14 -> 0 | BN14: =$BI14*ASSUMPTIONS!$B$15+$BK14*ASSUMPTIONS!$B$16 -> 35.903058 | BO14: =$BO13+$BN14-$BL14-$BM14-ASSUMPTIONS!$B$23 -> 128.56502 | BP14: =(SUMPRODUCT(($F$8:$F$13+$A$8:$A$13=$A14)*($C$8:$C$13<>"NONE")*$G$8:$G$13)+SUMPRODUCT(($P$8:$P$13+$A$8:$A$13=$A14)*($M$8:$M$13<>"NONE")*$Q$8:$Q$13))*(1+ASSUMPTIONS!$B$22*(MAX(0,ABS($AA14)/$AI14-1)+MAX(0,ABS($AB14)/$AJ14-1)+MAX(0,ABS($AC14)/$AK14-1)+MAX(0,ABS($AD14)/$AL14-1)+MAX(0,ABS($AE14)/$AM14-1)+MAX(0,ABS($AF14)/$AN14-1)+MAX(0,ABS($AG14)/$AO14-1)+MAX(0,ABS($AH14)/$AP14-1))/8) -> 0 | BQ14: =MAX(0,$BQ13*(1-ASSUMPTIONS!$B$18)+$BP14-$BM14*ASSUMPTIONS!$B$17) -> 1.7220906
A15: 8 | B15: =CLIMATE!B15 -> 1947 | C15: =IFERROR(INDEX(CAPABILITIES!$B$7:$B$15,MATCH(PLAY!$D15,CAPABILITIES!$A$7:$A$15,0)),"NONE") -> NONE | D15: =IFERROR(IF(INDEX(CAPABILITIES!$B$7:$B$15,MATCH(PLAY!$D15,CAPABILITIES!$A$7:$A$15,0))="DRIVER",INDEX(CAPABILITIES!$C$7:$C$15,MATCH(PLAY!$D15,CAPABILITIES!$A$7:$A$15,0)),PLAY!$E15),"") -> 0 | E15: =IFERROR(INDEX(CAPABILITIES!$D$7:$D$15,MATCH(PLAY!$D15,CAPABILITIES!$A$7:$A$15,0))*IF(INDEX(CAPABILITIES!$K$7:$K$15,MATCH(PLAY!$D15,CAPABILITIES!$A$7:$A$15,0))="Y",IF(IFERROR(INDEX($AA14:$AH14,MATCH(PLAY!$E15,REGIONS!$B$7:$B$14,0)),0)<ASSUMPTIONS!$B$20,1,ASSUMPTIONS!$B$21),1),0) -> 0 | F15: =IFERROR(INDEX(CAPABILITIES!$E$7:$E$15,MATCH(PLAY!$D15,CAPABILITIES!$A$7:$A$15,0)),0) -> 0 | G15: =IFERROR(INDEX(CAPABILITIES!$F$7:$F$15,MATCH(PLAY!$D15,CAPABILITIES!$A$7:$A$15,0)),0) -> 0 | H15: =IFERROR(INDEX(CAPABILITIES!$G$7:$G$15,MATCH(PLAY!$D15,CAPABILITIES!$A$7:$A$15,0)),0) -> 0 | I15: =IFERROR(INDEX(CAPABILITIES!$H$7:$H$15,MATCH(PLAY!$D15,CAPABILITIES!$A$7:$A$15,0)),"") -> 0 | J15: =IFERROR(INDEX(CAPABILITIES!$D$7:$D$15,MATCH(PLAY!$D15,CAPABILITIES!$A$7:$A$15,0))*INDEX(CAPABILITIES!$I$7:$I$15,MATCH(PLAY!$D15,CAPABILITIES!$A$7:$A$15,0)),0) -> 0 | K15: =IFERROR(INDEX(CAPABILITIES!$E$7:$E$15,MATCH(PLAY!$D15,CAPABILITIES!$A$7:$A$15,0))+INDEX(CAPABILITIES!$J$7:$J$15,MATCH(PLAY!$D15,CAPABILITIES!$A$7:$A$15,0)),0) -> 0 | L15: =IFERROR(INDEX(CAPABILITIES!$L$7:$L$15,MATCH(PLAY!$D15,CAPABILITIES!$A$7:$A$15,0)),0) -> 0 | M15: =IFERROR(INDEX(CAPABILITIES!$B$7:$B$15,MATCH(PLAY!$F15,CAPABILITIES!$A$7:$A$15,0)),"NONE") -> NONE | N15: =IFERROR(IF(INDEX(CAPABILITIES!$B$7:$B$15,MATCH(PLAY!$F15,CAPABILITIES!$A$7:$A$15,0))="DRIVER",INDEX(CAPABILITIES!$C$7:$C$15,MATCH(PLAY!$F15,CAPABILITIES!$A$7:$A$15,0)),PLAY!$G15),"") -> 0 | O15: =IFERROR(INDEX(CAPABILITIES!$D$7:$D$15,MATCH(PLAY!$F15,CAPABILITIES!$A$7:$A$15,0))*IF(INDEX(CAPABILITIES!$K$7:$K$15,MATCH(PLAY!$F15,CAPABILITIES!$A$7:$A$15,0))="Y",IF(IFERROR(INDEX($AA14:$AH14,MATCH(PLAY!$G15,REGIONS!$B$7:$B$14,0)),0)<ASSUMPTIONS!$B$20,1,ASSUMPTIONS!$B$21),1),0) -> 0 | P15: =IFERROR(INDEX(CAPABILITIES!$E$7:$E$15,MATCH(PLAY!$F15,CAPABILITIES!$A$7:$A$15,0)),0) -> 0 | Q15: =IFERROR(INDEX(CAPABILITIES!$F$7:$F$15,MATCH(PLAY!$F15,CAPABILITIES!$A$7:$A$15,0)),0) -> 0 | R15: =IFERROR(INDEX(CAPABILITIES!$G$7:$G$15,MATCH(PLAY!$F15,CAPABILITIES!$A$7:$A$15,0)),0) -> 0 | S15: =IFERROR(INDEX(CAPABILITIES!$H$7:$H$15,MATCH(PLAY!$F15,CAPABILITIES!$A$7:$A$15,0)),"") -> 0 | T15: =IFERROR(INDEX(CAPABILITIES!$D$7:$D$15,MATCH(PLAY!$F15,CAPABILITIES!$A$7:$A$15,0))*INDEX(CAPABILITIES!$I$7:$I$15,MATCH(PLAY!$F15,CAPABILITIES!$A$7:$A$15,0)),0) -> 0 | U15: =IFERROR(INDEX(CAPABILITIES!$E$7:$E$15,MATCH(PLAY!$F15,CAPABILITIES!$A$7:$A$15,0))+INDEX(CAPABILITIES!$J$7:$J$15,MATCH(PLAY!$F15,CAPABILITIES!$A$7:$A$15,0)),0) -> 0 | V15: =IFERROR(INDEX(CAPABILITIES!$L$7:$L$15,MATCH(PLAY!$F15,CAPABILITIES!$A$7:$A$15,0)),0) -> 0 | W15: =CLIMATE!D15+SUMPRODUCT(($D$8:$D$14="ENSO")*($F$8:$F$14+$A$8:$A$14=$A15)*$E$8:$E$14)+SUMPRODUCT(($I$8:$I$14="ENSO")*($K$8:$K$14+$A$8:$A$14=$A15)*$J$8:$J$14)+SUMPRODUCT(($N$8:$N$14="ENSO")*($P$8:$P$14+$A$8:$A$14=$A15)*$O$8:$O$14)+SUMPRODUCT(($S$8:$S$14="ENSO")*($U$8:$U$14+$A$8:$A$14=$A15)*$T$8:$T$14) -> -0.85 | X15: =CLIMATE!E15+SUMPRODUCT(($D$8:$D$14="IOD")*($F$8:$F$14+$A$8:$A$14=$A15)*$E$8:$E$14)+SUMPRODUCT(($I$8:$I$14="IOD")*($K$8:$K$14+$A$8:$A$14=$A15)*$J$8:$J$14)+SUMPRODUCT(($N$8:$N$14="IOD")*($P$8:$P$14+$A$8:$A$14=$A15)*$O$8:$O$14)+SUMPRODUCT(($S$8:$S$14="IOD")*($U$8:$U$14+$A$8:$A$14=$A15)*$T$8:$T$14) -> 0.368 | Y15: =CLIMATE!F15+SUMPRODUCT(($D$8:$D$14="NATL")*($F$8:$F$14+$A$8:$A$14=$A15)*$E$8:$E$14)+SUMPRODUCT(($I$8:$I$14="NATL")*($K$8:$K$14+$A$8:$A$14=$A15)*$J$8:$J$14)+SUMPRODUCT(($N$8:$N$14="NATL")*($P$8:$P$14+$A$8:$A$14=$A15)*$O$8:$O$14)+SUMPRODUCT(($S$8:$S$14="NATL")*($U$8:$U$14+$A$8:$A$14=$A15)*$T$8:$T$14) -> 0.602 | Z15: =CLIMATE!G15+SUMPRODUCT(($D$8:$D$14="GLOBAL")*($F$8:$F$14+$A$8:$A$14=$A15)*$E$8:$E$14)+SUMPRODUCT(($I$8:$I$14="GLOBAL")*($K$8:$K$14+$A$8:$A$14=$A15)*$J$8:$J$14)+SUMPRODUCT(($N$8:$N$14="GLOBAL")*($P$8:$P$14+$A$8:$A$14=$A15)*$O$8:$O$14)+SUMPRODUCT(($S$8:$S$14="GLOBAL")*($U$8:$U$14+$A$8:$A$14=$A15)*$T$8:$T$14) -> 0 | AA15: =CLIMATE!H15+IFERROR(INDEX($W$8:$W$47,$A15-GRAPH!B17),0)*GRAPH!B9+IFERROR(INDEX($X$8:$X$47,$A15-GRAPH!B18),0)*GRAPH!B10+IFERROR(INDEX($Y$8:$Y$47,$A15-GRAPH!B19),0)*GRAPH!B11+IFERROR(INDEX($Z$8:$Z$47,$A15-GRAPH!B20),0)*GRAPH!B12+SUMPRODUCT(($D$8:$D$14=REGIONS!$B$7)*($F$8:$F$14+$A$8:$A$14=$A15)*$E$8:$E$14)+SUMPRODUCT(($N$8:$N$14=REGIONS!$B$7)*($P$8:$P$14+$A$8:$A$14=$A15)*$O$8:$O$14) -> -0.1755 | AB15: =CLIMATE!I15+IFERROR(INDEX($W$8:$W$47,$A15-GRAPH!C17),0)*GRAPH!C9+IFERROR(INDEX($X$8:$X$47,$A15-GRAPH!C18),0)*GRAPH!C10+IFERROR(INDEX($Y$8:$Y$47,$A15-GRAPH!C19),0)*GRAPH!C11+IFERROR(INDEX($Z$8:$Z$47,$A15-GRAPH!C20),0)*GRAPH!C12+SUMPRODUCT(($D$8:$D$14=REGIONS!$B$8)*($F$8:$F$14+$A$8:$A$14=$A15)*$E$8:$E$14)+SUMPRODUCT(($N$8:$N$14=REGIONS!$B$8)*($P$8:$P$14+$A$8:$A$14=$A15)*$O$8:$O$14) -> -0.3146 | AC15: =CLIMATE!J15+IFERROR(INDEX($W$8:$W$47,$A15-GRAPH!D17),0)*GRAPH!D9+IFERROR(INDEX($X$8:$X$47,$A15-GRAPH!D18),0)*GRAPH!D10+IFERROR(INDEX($Y$8:$Y$47,$A15-GRAPH!D19),0)*GRAPH!D11+IFERROR(INDEX($Z$8:$Z$47,$A15-GRAPH!D20),0)*GRAPH!D12+SUMPRODUCT(($D$8:$D$14=REGIONS!$B$9)*($F$8:$F$14+$A$8:$A$14=$A15)*$E$8:$E$14)+SUMPRODUCT(($N$8:$N$14=REGIONS!$B$9)*($P$8:$P$14+$A$8:$A$14=$A15)*$O$8:$O$14) -> 0.2825 | AD15: =CLIMATE!K15+IFERROR(INDEX($W$8:$W$47,$A15-GRAPH!E17),0)*GRAPH!E9+IFERROR(INDEX($X$8:$X$47,$A15-GRAPH!E18),0)*GRAPH!E10+IFERROR(INDEX($Y$8:$Y$47,$A15-GRAPH!E19),0)*GRAPH!E11+IFERROR(INDEX($Z$8:$Z$47,$A15-GRAPH!E20),0)*GRAPH!E12+SUMPRODUCT(($D$8:$D$14=REGIONS!$B$10)*($F$8:$F$14+$A$8:$A$14=$A15)*$E$8:$E$14)+SUMPRODUCT(($N$8:$N$14=REGIONS!$B$10)*($P$8:$P$14+$A$8:$A$14=$A15)*$O$8:$O$14) -> 0.2754 | AE15: =CLIMATE!L15+IFERROR(INDEX($W$8:$W$47,$A15-GRAPH!F17),0)*GRAPH!F9+IFERROR(INDEX($X$8:$X$47,$A15-GRAPH!F18),0)*GRAPH!F10+IFERROR(INDEX($Y$8:$Y$47,$A15-GRAPH!F19),0)*GRAPH!F11+IFERROR(INDEX($Z$8:$Z$47,$A15-GRAPH!F20),0)*GRAPH!F12+SUMPRODUCT(($D$8:$D$14=REGIONS!$B$11)*($F$8:$F$14+$A$8:$A$14=$A15)*$E$8:$E$14)+SUMPRODUCT(($N$8:$N$14=REGIONS!$B$11)*($P$8:$P$14+$A$8:$A$14=$A15)*$O$8:$O$14) -> -0.3504 | AF15: =CLIMATE!M15+IFERROR(INDEX($W$8:$W$47,$A15-GRAPH!G17),0)*GRAPH!G9+IFERROR(INDEX($X$8:$X$47,$A15-GRAPH!G18),0)*GRAPH!G10+IFERROR(INDEX($Y$8:$Y$47,$A15-GRAPH!G19),0)*GRAPH!G11+IFERROR(INDEX($Z$8:$Z$47,$A15-GRAPH!G20),0)*GRAPH!G12+SUMPRODUCT(($D$8:$D$14=REGIONS!$B$12)*($F$8:$F$14+$A$8:$A$14=$A15)*$E$8:$E$14)+SUMPRODUCT(($N$8:$N$14=REGIONS!$B$12)*($P$8:$P$14+$A$8:$A$14=$A15)*$O$8:$O$14) -> -0.2426 | AG15: =CLIMATE!N15+IFERROR(INDEX($W$8:$W$47,$A15-GRAPH!H17),0)*GRAPH!H9+IFERROR(INDEX($X$8:$X$47,$A15-GRAPH!H18),0)*GRAPH!H10+IFERROR(INDEX($Y$8:$Y$47,$A15-GRAPH!H19),0)*GRAPH!H11+IFERROR(INDEX($Z$8:$Z$47,$A15-GRAPH!H20),0)*GRAPH!H12+SUMPRODUCT(($D$8:$D$14=REGIONS!$B$13)*($F$8:$F$14+$A$8:$A$14=$A15)*$E$8:$E$14)+SUMPRODUCT(($N$8:$N$14=REGIONS!$B$13)*($P$8:$P$14+$A$8:$A$14=$A15)*$O$8:$O$14) -> 0.5262 | AH15: =CLIMATE!O15+IFERROR(INDEX($W$8:$W$47,$A15-GRAPH!I17),0)*GRAPH!I9+IFERROR(INDEX($X$8:$X$47,$A15-GRAPH!I18),0)*GRAPH!I10+IFERROR(INDEX($Y$8:$Y$47,$A15-GRAPH!I19),0)*GRAPH!I11+IFERROR(INDEX($Z$8:$Z$47,$A15-GRAPH!I20),0)*GRAPH!I12+SUMPRODUCT(($D$8:$D$14=REGIONS!$B$14)*($F$8:$F$14+$A$8:$A$14=$A15)*$E$8:$E$14)+SUMPRODUCT(($N$8:$N$14=REGIONS!$B$14)*($P$8:$P$14+$A$8:$A$14=$A15)*$O$8:$O$14) -> 0.805 | AI15: =REGIONS!$F$7*(1+ASSUMPTIONS!$B$19*$A15) -> 0.8384 | AJ15: =REGIONS!$F$8*(1+ASSUMPTIONS!$B$19*$A15) -> 0.9432 | AK15: =REGIONS!$F$9*(1+ASSUMPTIONS!$B$19*$A15) -> 0.9432 | AL15: =REGIONS!$F$10*(1+ASSUMPTIONS!$B$19*$A15) -> 0.7336 | AM15: =REGIONS!$F$11*(1+ASSUMPTIONS!$B$19*$A15) -> 0.7336 | AN15: =REGIONS!$F$12*(1+ASSUMPTIONS!$B$19*$A15) -> 1.1528 | AO15: =REGIONS!$F$13*(1+ASSUMPTIONS!$B$19*$A15) -> 1.2576 | AP15: =REGIONS!$F$14*(1+ASSUMPTIONS!$B$19*$A15) -> 1.2576 | AQ15: =SUMPRODUCT(($D$8:$D$47=REGIONS!$B$7)*($A$8:$A$47<=$A15)*$L$8:$L$47)+SUMPRODUCT(($N$8:$N$47=REGIONS!$B$7)*($A$8:$A$47<=$A15)*$V$8:$V$47) -> 0 | AR15: =SUMPRODUCT(($D$8:$D$47=REGIONS!$B$8)*($A$8:$A$47<=$A15)*$L$8:$L$47)+SUMPRODUCT(($N$8:$N$47=REGIONS!$B$8)*($A$8:$A$47<=$A15)*$V$8:$V$47) -> 0 | AS15: =SUMPRODUCT(($D$8:$D$47=REGIONS!$B$9)*($A$8:$A$47<=$A15)*$L$8:$L$47)+SUMPRODUCT(($N$8:$N$47=REGIONS!$B$9)*($A$8:$A$47<=$A15)*$V$8:$V$47) -> 0 | AT15: =SUMPRODUCT(($D$8:$D$47=REGIONS!$B$10)*($A$8:$A$47<=$A15)*$L$8:$L$47)+SUMPRODUCT(($N$8:$N$47=REGIONS!$B$10)*($A$8:$A$47<=$A15)*$V$8:$V$47) -> 0 | AU15: =SUMPRODUCT(($D$8:$D$47=REGIONS!$B$11)*($A$8:$A$47<=$A15)*$L$8:$L$47)+SUMPRODUCT(($N$8:$N$47=REGIONS!$B$11)*($A$8:$A$47<=$A15)*$V$8:$V$47) -> 0 | AV15: =SUMPRODUCT(($D$8:$D$47=REGIONS!$B$12)*($A$8:$A$47<=$A15)*$L$8:$L$47)+SUMPRODUCT(($N$8:$N$47=REGIONS!$B$12)*($A$8:$A$47<=$A15)*$V$8:$V$47) -> 0 | AW15: =SUMPRODUCT(($D$8:$D$47=REGIONS!$B$13)*($A$8:$A$47<=$A15)*$L$8:$L$47)+SUMPRODUCT(($N$8:$N$47=REGIONS!$B$13)*($A$8:$A$47<=$A15)*$V$8:$V$47) -> 0 | AX15: =SUMPRODUCT(($D$8:$D$47=REGIONS!$B$14)*($A$8:$A$47<=$A15)*$L$8:$L$47)+SUMPRODUCT(($N$8:$N$47=REGIONS!$B$14)*($A$8:$A$47<=$A15)*$V$8:$V$47) -> 0 | AY15: =MAX(0,MIN(135,100-(MAX(0,-$AA15)*REGIONS!$E$7*ASSUMPTIONS!$B$7+MAX(0,$AA15-ASSUMPTIONS!$B$9)*REGIONS!$E$7*ASSUMPTIONS!$B$8)*(1-$AQ15/100))) -> 97.543 | AZ15: =MAX(0,MIN(135,100-(MAX(0,-$AB15)*REGIONS!$E$8*ASSUMPTIONS!$B$7+MAX(0,$AB15-ASSUMPTIONS!$B$9)*REGIONS!$E$8*ASSUMPTIONS!$B$8)*(1-$AR15/100))) -> 95.15516 | BA15: =MAX(0,MIN(135,100-(MAX(0,-$AC15)*REGIONS!$E$9*ASSUMPTIONS!$B$7+MAX(0,$AC15-ASSUMPTIONS!$B$9)*REGIONS!$E$9*ASSUMPTIONS!$B$8)*(1-$AS15/100))) -> 100 | BB15: =MAX(0,MIN(135,100-(MAX(0,-$AD15)*REGIONS!$E$10*ASSUMPTIONS!$B$7+MAX(0,$AD15-ASSUMPTIONS!$B$9)*REGIONS!$E$10*ASSUMPTIONS!$B$8)*(1-$AT15/100))) -> 100 | BC15: =MAX(0,MIN(135,100-(MAX(0,-$AE15)*REGIONS!$E$11*ASSUMPTIONS!$B$7+MAX(0,$AE15-ASSUMPTIONS!$B$9)*REGIONS!$E$11*ASSUMPTIONS!$B$8)*(1-$AU15/100))) -> 94.60384 | BD15: =MAX(0,MIN(135,100-(MAX(0,-$AF15)*REGIONS!$E$12*ASSUMPTIONS!$B$7+MAX(0,$AF15-ASSUMPTIONS!$B$9)*REGIONS!$E$12*ASSUMPTIONS!$B$8)*(1-$AV15/100))) -> 95.58468 | BE15: =MAX(0,MIN(135,100-(MAX(0,-$AG15)*REGIONS!$E$13*ASSUMPTIONS!$B$7+MAX(0,$AG15-ASSUMPTIONS!$B$9)*REGIONS!$E$13*ASSUMPTIONS!$B$8)*(1-$AW15/100))) -> 100 | BF15: =MAX(0,MIN(135,100-(MAX(0,-$AH15)*REGIONS!$E$14*ASSUMPTIONS!$B$7+MAX(0,$AH15-ASSUMPTIONS!$B$9)*REGIONS!$E$14*ASSUMPTIONS!$B$8)*(1-$AX15/100))) -> 100 | BG15: =$AY15*REGIONS!$D$7/100+$AZ15*REGIONS!$D$8/100+$BA15*REGIONS!$D$9/100+$BB15*REGIONS!$D$10/100+$BC15*REGIONS!$D$11/100+$BD15*REGIONS!$D$12/100+$BE15*REGIONS!$D$13/100+$BF15*REGIONS!$D$14/100 -> 97.776814 | BH15: =100*(100/MAX(1,$BG15))^ASSUMPTIONS!$B$10 -> 104.12989 | BI15: =$AY15*$BH15/100*ASSUMPTIONS!$B$11 -> 86.335706 | BJ15: =MAX(0,ABS($AA15)-$AI15*ASSUMPTIONS!$B$24)*REGIONS!$D$7/100+MAX(0,ABS($AB15)-$AJ15*ASSUMPTIONS!$B$24)*REGIONS!$D$8/100+MAX(0,ABS($AC15)-$AK15*ASSUMPTIONS!$B$24)*REGIONS!$D$9/100+MAX(0,ABS($AD15)-$AL15*ASSUMPTIONS!$B$24)*REGIONS!$D$10/100+MAX(0,ABS($AE15)-$AM15*ASSUMPTIONS!$B$24)*REGIONS!$D$11/100+MAX(0,ABS($AF15)-$AN15*ASSUMPTIONS!$B$24)*REGIONS!$D$12/100+MAX(0,ABS($AG15)-$AO15*ASSUMPTIONS!$B$24)*REGIONS!$D$13/100+MAX(0,ABS($AH15)-$AP15*ASSUMPTIONS!$B$24)*REGIONS!$D$14/100 -> 0 | BK15: =MIN(ASSUMPTIONS!$B$14,ASSUMPTIONS!$B$12+$BJ15*ASSUMPTIONS!$B$13) -> 28 | BL15: =$H15+$R15 -> 0 | BM15: =PLAY!$H15 -> 0 | BN15: =$BI15*ASSUMPTIONS!$B$15+$BK15*ASSUMPTIONS!$B$16 -> 35.560285 | BO15: =$BO14+$BN15-$BL15-$BM15-ASSUMPTIONS!$B$23 -> 132.12531 | BP15: =(SUMPRODUCT(($F$8:$F$14+$A$8:$A$14=$A15)*($C$8:$C$14<>"NONE")*$G$8:$G$14)+SUMPRODUCT(($P$8:$P$14+$A$8:$A$14=$A15)*($M$8:$M$14<>"NONE")*$Q$8:$Q$14))*(1+ASSUMPTIONS!$B$22*(MAX(0,ABS($AA15)/$AI15-1)+MAX(0,ABS($AB15)/$AJ15-1)+MAX(0,ABS($AC15)/$AK15-1)+MAX(0,ABS($AD15)/$AL15-1)+MAX(0,ABS($AE15)/$AM15-1)+MAX(0,ABS($AF15)/$AN15-1)+MAX(0,ABS($AG15)/$AO15-1)+MAX(0,ABS($AH15)/$AP15-1))/8) -> 0 | BQ15: =MAX(0,$BQ14*(1-ASSUMPTIONS!$B$18)+$BP15-$BM15*ASSUMPTIONS!$B$17) -> 1.653207
A16: 9 | B16: =CLIMATE!B16 -> 1948 | C16: =IFERROR(INDEX(CAPABILITIES!$B$7:$B$15,MATCH(PLAY!$D16,CAPABILITIES!$A$7:$A$15,0)),"NONE") -> NONE | D16: =IFERROR(IF(INDEX(CAPABILITIES!$B$7:$B$15,MATCH(PLAY!$D16,CAPABILITIES!$A$7:$A$15,0))="DRIVER",INDEX(CAPABILITIES!$C$7:$C$15,MATCH(PLAY!$D16,CAPABILITIES!$A$7:$A$15,0)),PLAY!$E16),"") -> 0 | E16: =IFERROR(INDEX(CAPABILITIES!$D$7:$D$15,MATCH(PLAY!$D16,CAPABILITIES!$A$7:$A$15,0))*IF(INDEX(CAPABILITIES!$K$7:$K$15,MATCH(PLAY!$D16,CAPABILITIES!$A$7:$A$15,0))="Y",IF(IFERROR(INDEX($AA15:$AH15,MATCH(PLAY!$E16,REGIONS!$B$7:$B$14,0)),0)<ASSUMPTIONS!$B$20,1,ASSUMPTIONS!$B$21),1),0) -> 0 | F16: =IFERROR(INDEX(CAPABILITIES!$E$7:$E$15,MATCH(PLAY!$D16,CAPABILITIES!$A$7:$A$15,0)),0) -> 0 | G16: =IFERROR(INDEX(CAPABILITIES!$F$7:$F$15,MATCH(PLAY!$D16,CAPABILITIES!$A$7:$A$15,0)),0) -> 0 | H16: =IFERROR(INDEX(CAPABILITIES!$G$7:$G$15,MATCH(PLAY!$D16,CAPABILITIES!$A$7:$A$15,0)),0) -> 0 | I16: =IFERROR(INDEX(CAPABILITIES!$H$7:$H$15,MATCH(PLAY!$D16,CAPABILITIES!$A$7:$A$15,0)),"") -> 0 | J16: =IFERROR(INDEX(CAPABILITIES!$D$7:$D$15,MATCH(PLAY!$D16,CAPABILITIES!$A$7:$A$15,0))*INDEX(CAPABILITIES!$I$7:$I$15,MATCH(PLAY!$D16,CAPABILITIES!$A$7:$A$15,0)),0) -> 0 | K16: =IFERROR(INDEX(CAPABILITIES!$E$7:$E$15,MATCH(PLAY!$D16,CAPABILITIES!$A$7:$A$15,0))+INDEX(CAPABILITIES!$J$7:$J$15,MATCH(PLAY!$D16,CAPABILITIES!$A$7:$A$15,0)),0) -> 0 | L16: =IFERROR(INDEX(CAPABILITIES!$L$7:$L$15,MATCH(PLAY!$D16,CAPABILITIES!$A$7:$A$15,0)),0) -> 0 | M16: =IFERROR(INDEX(CAPABILITIES!$B$7:$B$15,MATCH(PLAY!$F16,CAPABILITIES!$A$7:$A$15,0)),"NONE") -> NONE | N16: =IFERROR(IF(INDEX(CAPABILITIES!$B$7:$B$15,MATCH(PLAY!$F16,CAPABILITIES!$A$7:$A$15,0))="DRIVER",INDEX(CAPABILITIES!$C$7:$C$15,MATCH(PLAY!$F16,CAPABILITIES!$A$7:$A$15,0)),PLAY!$G16),"") -> 0 | O16: =IFERROR(INDEX(CAPABILITIES!$D$7:$D$15,MATCH(PLAY!$F16,CAPABILITIES!$A$7:$A$15,0))*IF(INDEX(CAPABILITIES!$K$7:$K$15,MATCH(PLAY!$F16,CAPABILITIES!$A$7:$A$15,0))="Y",IF(IFERROR(INDEX($AA15:$AH15,MATCH(PLAY!$G16,REGIONS!$B$7:$B$14,0)),0)<ASSUMPTIONS!$B$20,1,ASSUMPTIONS!$B$21),1),0) -> 0 | P16: =IFERROR(INDEX(CAPABILITIES!$E$7:$E$15,MATCH(PLAY!$F16,CAPABILITIES!$A$7:$A$15,0)),0) -> 0 | Q16: =IFERROR(INDEX(CAPABILITIES!$F$7:$F$15,MATCH(PLAY!$F16,CAPABILITIES!$A$7:$A$15,0)),0) -> 0 | R16: =IFERROR(INDEX(CAPABILITIES!$G$7:$G$15,MATCH(PLAY!$F16,CAPABILITIES!$A$7:$A$15,0)),0) -> 0 | S16: =IFERROR(INDEX(CAPABILITIES!$H$7:$H$15,MATCH(PLAY!$F16,CAPABILITIES!$A$7:$A$15,0)),"") -> 0 | T16: =IFERROR(INDEX(CAPABILITIES!$D$7:$D$15,MATCH(PLAY!$F16,CAPABILITIES!$A$7:$A$15,0))*INDEX(CAPABILITIES!$I$7:$I$15,MATCH(PLAY!$F16,CAPABILITIES!$A$7:$A$15,0)),0) -> 0 | U16: =IFERROR(INDEX(CAPABILITIES!$E$7:$E$15,MATCH(PLAY!$F16,CAPABILITIES!$A$7:$A$15,0))+INDEX(CAPABILITIES!$J$7:$J$15,MATCH(PLAY!$F16,CAPABILITIES!$A$7:$A$15,0)),0) -> 0 | V16: =IFERROR(INDEX(CAPABILITIES!$L$7:$L$15,MATCH(PLAY!$F16,CAPABILITIES!$A$7:$A$15,0)),0) -> 0 | W16: =CLIMATE!D16+SUMPRODUCT(($D$8:$D$15="ENSO")*($F$8:$F$15+$A$8:$A$15=$A16)*$E$8:$E$15)+SUMPRODUCT(($I$8:$I$15="ENSO")*($K$8:$K$15+$A$8:$A$15=$A16)*$J$8:$J$15)+SUMPRODUCT(($N$8:$N$15="ENSO")*($P$8:$P$15+$A$8:$A$15=$A16)*$O$8:$O$15)+SUMPRODUCT(($S$8:$S$15="ENSO")*($U$8:$U$15+$A$8:$A$15=$A16)*$T$8:$T$15) -> -1.58 | X16: =CLIMATE!E16+SUMPRODUCT(($D$8:$D$15="IOD")*($F$8:$F$15+$A$8:$A$15=$A16)*$E$8:$E$15)+SUMPRODUCT(($I$8:$I$15="IOD")*($K$8:$K$15+$A$8:$A$15=$A16)*$J$8:$J$15)+SUMPRODUCT(($N$8:$N$15="IOD")*($P$8:$P$15+$A$8:$A$15=$A16)*$O$8:$O$15)+SUMPRODUCT(($S$8:$S$15="IOD")*($U$8:$U$15+$A$8:$A$15=$A16)*$T$8:$T$15) -> 0.727 | Y16: =CLIMATE!F16+SUMPRODUCT(($D$8:$D$15="NATL")*($F$8:$F$15+$A$8:$A$15=$A16)*$E$8:$E$15)+SUMPRODUCT(($I$8:$I$15="NATL")*($K$8:$K$15+$A$8:$A$15=$A16)*$J$8:$J$15)+SUMPRODUCT(($N$8:$N$15="NATL")*($P$8:$P$15+$A$8:$A$15=$A16)*$O$8:$O$15)+SUMPRODUCT(($S$8:$S$15="NATL")*($U$8:$U$15+$A$8:$A$15=$A16)*$T$8:$T$15) -> 0.214 | Z16: =CLIMATE!G16+SUMPRODUCT(($D$8:$D$15="GLOBAL")*($F$8:$F$15+$A$8:$A$15=$A16)*$E$8:$E$15)+SUMPRODUCT(($I$8:$I$15="GLOBAL")*($K$8:$K$15+$A$8:$A$15=$A16)*$J$8:$J$15)+SUMPRODUCT(($N$8:$N$15="GLOBAL")*($P$8:$P$15+$A$8:$A$15=$A16)*$O$8:$O$15)+SUMPRODUCT(($S$8:$S$15="GLOBAL")*($U$8:$U$15+$A$8:$A$15=$A16)*$T$8:$T$15) -> 0 | AA16: =CLIMATE!H16+IFERROR(INDEX($W$8:$W$47,$A16-GRAPH!B17),0)*GRAPH!B9+IFERROR(INDEX($X$8:$X$47,$A16-GRAPH!B18),0)*GRAPH!B10+IFERROR(INDEX($Y$8:$Y$47,$A16-GRAPH!B19),0)*GRAPH!B11+IFERROR(INDEX($Z$8:$Z$47,$A16-GRAPH!B20),0)*GRAPH!B12+SUMPRODUCT(($D$8:$D$15=REGIONS!$B$7)*($F$8:$F$15+$A$8:$A$15=$A16)*$E$8:$E$15)+SUMPRODUCT(($N$8:$N$15=REGIONS!$B$7)*($P$8:$P$15+$A$8:$A$15=$A16)*$O$8:$O$15) -> 0.3041 | AB16: =CLIMATE!I16+IFERROR(INDEX($W$8:$W$47,$A16-GRAPH!C17),0)*GRAPH!C9+IFERROR(INDEX($X$8:$X$47,$A16-GRAPH!C18),0)*GRAPH!C10+IFERROR(INDEX($Y$8:$Y$47,$A16-GRAPH!C19),0)*GRAPH!C11+IFERROR(INDEX($Z$8:$Z$47,$A16-GRAPH!C20),0)*GRAPH!C12+SUMPRODUCT(($D$8:$D$15=REGIONS!$B$8)*($F$8:$F$15+$A$8:$A$15=$A16)*$E$8:$E$15)+SUMPRODUCT(($N$8:$N$15=REGIONS!$B$8)*($P$8:$P$15+$A$8:$A$15=$A16)*$O$8:$O$15) -> -0.2561 | AC16: =CLIMATE!J16+IFERROR(INDEX($W$8:$W$47,$A16-GRAPH!D17),0)*GRAPH!D9+IFERROR(INDEX($X$8:$X$47,$A16-GRAPH!D18),0)*GRAPH!D10+IFERROR(INDEX($Y$8:$Y$47,$A16-GRAPH!D19),0)*GRAPH!D11+IFERROR(INDEX($Z$8:$Z$47,$A16-GRAPH!D20),0)*GRAPH!D12+SUMPRODUCT(($D$8:$D$15=REGIONS!$B$9)*($F$8:$F$15+$A$8:$A$15=$A16)*$E$8:$E$15)+SUMPRODUCT(($N$8:$N$15=REGIONS!$B$9)*($P$8:$P$15+$A$8:$A$15=$A16)*$O$8:$O$15) -> 0.026 | AD16: =CLIMATE!K16+IFERROR(INDEX($W$8:$W$47,$A16-GRAPH!E17),0)*GRAPH!E9+IFERROR(INDEX($X$8:$X$47,$A16-GRAPH!E18),0)*GRAPH!E10+IFERROR(INDEX($Y$8:$Y$47,$A16-GRAPH!E19),0)*GRAPH!E11+IFERROR(INDEX($Z$8:$Z$47,$A16-GRAPH!E20),0)*GRAPH!E12+SUMPRODUCT(($D$8:$D$15=REGIONS!$B$10)*($F$8:$F$15+$A$8:$A$15=$A16)*$E$8:$E$15)+SUMPRODUCT(($N$8:$N$15=REGIONS!$B$10)*($P$8:$P$15+$A$8:$A$15=$A16)*$O$8:$O$15) -> 0.6634 | AE16: =CLIMATE!L16+IFERROR(INDEX($W$8:$W$47,$A16-GRAPH!F17),0)*GRAPH!F9+IFERROR(INDEX($X$8:$X$47,$A16-GRAPH!F18),0)*GRAPH!F10+IFERROR(INDEX($Y$8:$Y$47,$A16-GRAPH!F19),0)*GRAPH!F11+IFERROR(INDEX($Z$8:$Z$47,$A16-GRAPH!F20),0)*GRAPH!F12+SUMPRODUCT(($D$8:$D$15=REGIONS!$B$11)*($F$8:$F$15+$A$8:$A$15=$A16)*$E$8:$E$15)+SUMPRODUCT(($N$8:$N$15=REGIONS!$B$11)*($P$8:$P$15+$A$8:$A$15=$A16)*$O$8:$O$15) -> 0.6224 | AF16: =CLIMATE!M16+IFERROR(INDEX($W$8:$W$47,$A16-GRAPH!G17),0)*GRAPH!G9+IFERROR(INDEX($X$8:$X$47,$A16-GRAPH!G18),0)*GRAPH!G10+IFERROR(INDEX($Y$8:$Y$47,$A16-GRAPH!G19),0)*GRAPH!G11+IFERROR(INDEX($Z$8:$Z$47,$A16-GRAPH!G20),0)*GRAPH!G12+SUMPRODUCT(($D$8:$D$15=REGIONS!$B$12)*($F$8:$F$15+$A$8:$A$15=$A16)*$E$8:$E$15)+SUMPRODUCT(($N$8:$N$15=REGIONS!$B$12)*($P$8:$P$15+$A$8:$A$15=$A16)*$O$8:$O$15) -> 0.6972 | AG16: =CLIMATE!N16+IFERROR(INDEX($W$8:$W$47,$A16-GRAPH!H17),0)*GRAPH!H9+IFERROR(INDEX($X$8:$X$47,$A16-GRAPH!H18),0)*GRAPH!H10+IFERROR(INDEX($Y$8:$Y$47,$A16-GRAPH!H19),0)*GRAPH!H11+IFERROR(INDEX($Z$8:$Z$47,$A16-GRAPH!H20),0)*GRAPH!H12+SUMPRODUCT(($D$8:$D$15=REGIONS!$B$13)*($F$8:$F$15+$A$8:$A$15=$A16)*$E$8:$E$15)+SUMPRODUCT(($N$8:$N$15=REGIONS!$B$13)*($P$8:$P$15+$A$8:$A$15=$A16)*$O$8:$O$15) -> 0.5075 | AH16: =CLIMATE!O16+IFERROR(INDEX($W$8:$W$47,$A16-GRAPH!I17),0)*GRAPH!I9+IFERROR(INDEX($X$8:$X$47,$A16-GRAPH!I18),0)*GRAPH!I10+IFERROR(INDEX($Y$8:$Y$47,$A16-GRAPH!I19),0)*GRAPH!I11+IFERROR(INDEX($Z$8:$Z$47,$A16-GRAPH!I20),0)*GRAPH!I12+SUMPRODUCT(($D$8:$D$15=REGIONS!$B$14)*($F$8:$F$15+$A$8:$A$15=$A16)*$E$8:$E$15)+SUMPRODUCT(($N$8:$N$15=REGIONS!$B$14)*($P$8:$P$15+$A$8:$A$15=$A16)*$O$8:$O$15) -> 0.7714 | AI16: =REGIONS!$F$7*(1+ASSUMPTIONS!$B$19*$A16) -> 0.8432 | AJ16: =REGIONS!$F$8*(1+ASSUMPTIONS!$B$19*$A16) -> 0.9486 | AK16: =REGIONS!$F$9*(1+ASSUMPTIONS!$B$19*$A16) -> 0.9486 | AL16: =REGIONS!$F$10*(1+ASSUMPTIONS!$B$19*$A16) -> 0.7378 | AM16: =REGIONS!$F$11*(1+ASSUMPTIONS!$B$19*$A16) -> 0.7378 | AN16: =REGIONS!$F$12*(1+ASSUMPTIONS!$B$19*$A16) -> 1.1594 | AO16: =REGIONS!$F$13*(1+ASSUMPTIONS!$B$19*$A16) -> 1.2648 | AP16: =REGIONS!$F$14*(1+ASSUMPTIONS!$B$19*$A16) -> 1.2648 | AQ16: =SUMPRODUCT(($D$8:$D$47=REGIONS!$B$7)*($A$8:$A$47<=$A16)*$L$8:$L$47)+SUMPRODUCT(($N$8:$N$47=REGIONS!$B$7)*($A$8:$A$47<=$A16)*$V$8:$V$47) -> 0 | AR16: =SUMPRODUCT(($D$8:$D$47=REGIONS!$B$8)*($A$8:$A$47<=$A16)*$L$8:$L$47)+SUMPRODUCT(($N$8:$N$47=REGIONS!$B$8)*($A$8:$A$47<=$A16)*$V$8:$V$47) -> 0 | AS16: =SUMPRODUCT(($D$8:$D$47=REGIONS!$B$9)*($A$8:$A$47<=$A16)*$L$8:$L$47)+SUMPRODUCT(($N$8:$N$47=REGIONS!$B$9)*($A$8:$A$47<=$A16)*$V$8:$V$47) -> 0 | AT16: =SUMPRODUCT(($D$8:$D$47=REGIONS!$B$10)*($A$8:$A$47<=$A16)*$L$8:$L$47)+SUMPRODUCT(($N$8:$N$47=REGIONS!$B$10)*($A$8:$A$47<=$A16)*$V$8:$V$47) -> 0 | AU16: =SUMPRODUCT(($D$8:$D$47=REGIONS!$B$11)*($A$8:$A$47<=$A16)*$L$8:$L$47)+SUMPRODUCT(($N$8:$N$47=REGIONS!$B$11)*($A$8:$A$47<=$A16)*$V$8:$V$47) -> 0 | AV16: =SUMPRODUCT(($D$8:$D$47=REGIONS!$B$12)*($A$8:$A$47<=$A16)*$L$8:$L$47)+SUMPRODUCT(($N$8:$N$47=REGIONS!$B$12)*($A$8:$A$47<=$A16)*$V$8:$V$47) -> 0 | AW16: =SUMPRODUCT(($D$8:$D$47=REGIONS!$B$13)*($A$8:$A$47<=$A16)*$L$8:$L$47)+SUMPRODUCT(($N$8:$N$47=REGIONS!$B$13)*($A$8:$A$47<=$A16)*$V$8:$V$47) -> 0 | AX16: =SUMPRODUCT(($D$8:$D$47=REGIONS!$B$14)*($A$8:$A$47<=$A16)*$L$8:$L$47)+SUMPRODUCT(($N$8:$N$47=REGIONS!$B$14)*($A$8:$A$47<=$A16)*$V$8:$V$47) -> 0 | AY16: =MAX(0,MIN(135,100-(MAX(0,-$AA16)*REGIONS!$E$7*ASSUMPTIONS!$B$7+MAX(0,$AA16-ASSUMPTIONS!$B$9)*REGIONS!$E$7*ASSUMPTIONS!$B$8)*(1-$AQ16/100))) -> 100 | AZ16: =MAX(0,MIN(135,100-(MAX(0,-$AB16)*REGIONS!$E$8*ASSUMPTIONS!$B$7+MAX(0,$AB16-ASSUMPTIONS!$B$9)*REGIONS!$E$8*ASSUMPTIONS!$B$8)*(1-$AR16/100))) -> 96.05606 | BA16: =MAX(0,MIN(135,100-(MAX(0,-$AC16)*REGIONS!$E$9*ASSUMPTIONS!$B$7+MAX(0,$AC16-ASSUMPTIONS!$B$9)*REGIONS!$E$9*ASSUMPTIONS!$B$8)*(1-$AS16/100))) -> 100 | BB16: =MAX(0,MIN(135,100-(MAX(0,-$AD16)*REGIONS!$E$10*ASSUMPTIONS!$B$7+MAX(0,$AD16-ASSUMPTIONS!$B$9)*REGIONS!$E$10*ASSUMPTIONS!$B$8)*(1-$AT16/100))) -> 100 | BC16: =MAX(0,MIN(135,100-(MAX(0,-$AE16)*REGIONS!$E$11*ASSUMPTIONS!$B$7+MAX(0,$AE16-ASSUMPTIONS!$B$9)*REGIONS!$E$11*ASSUMPTIONS!$B$8)*(1-$AU16/100))) -> 100 | BD16: =MAX(0,MIN(135,100-(MAX(0,-$AF16)*REGIONS!$E$12*ASSUMPTIONS!$B$7+MAX(0,$AF16-ASSUMPTIONS!$B$9)*REGIONS!$E$12*ASSUMPTIONS!$B$8)*(1-$AV16/100))) -> 100 | BE16: =MAX(0,MIN(135,100-(MAX(0,-$AG16)*REGIONS!$E$13*ASSUMPTIONS!$B$7+MAX(0,$AG16-ASSUMPTIONS!$B$9)*REGIONS!$E$13*ASSUMPTIONS!$B$8)*(1-$AW16/100))) -> 100 | BF16: =MAX(0,MIN(135,100-(MAX(0,-$AH16)*REGIONS!$E$14*ASSUMPTIONS!$B$7+MAX(0,$AH16-ASSUMPTIONS!$B$9)*REGIONS!$E$14*ASSUMPTIONS!$B$8)*(1-$AX16/100))) -> 100 | BG16: =$AY16*REGIONS!$D$7/100+$AZ16*REGIONS!$D$8/100+$BA16*REGIONS!$D$9/100+$BB16*REGIONS!$D$10/100+$BC16*REGIONS!$D$11/100+$BD16*REGIONS!$D$12/100+$BE16*REGIONS!$D$13/100+$BF16*REGIONS!$D$14/100 -> 99.36897 | BH16: =100*(100/MAX(1,$BG16))^ASSUMPTIONS!$B$10 -> 101.14597 | BI16: =$AY16*$BH16/100*ASSUMPTIONS!$B$11 -> 85.974075 | BJ16: =MAX(0,ABS($AA16)-$AI16*ASSUMPTIONS!$B$24)*REGIONS!$D$7/100+MAX(0,ABS($AB16)-$AJ16*ASSUMPTIONS!$B$24)*REGIONS!$D$8/100+MAX(0,ABS($AC16)-$AK16*ASSUMPTIONS!$B$24)*REGIONS!$D$9/100+MAX(0,ABS($AD16)-$AL16*ASSUMPTIONS!$B$24)*REGIONS!$D$10/100+MAX(0,ABS($AE16)-$AM16*ASSUMPTIONS!$B$24)*REGIONS!$D$11/100+MAX(0,ABS($AF16)-$AN16*ASSUMPTIONS!$B$24)*REGIONS!$D$12/100+MAX(0,ABS($AG16)-$AO16*ASSUMPTIONS!$B$24)*REGIONS!$D$13/100+MAX(0,ABS($AH16)-$AP16*ASSUMPTIONS!$B$24)*REGIONS!$D$14/100 -> 0.028095 | BK16: =MIN(ASSUMPTIONS!$B$14,ASSUMPTIONS!$B$12+$BJ16*ASSUMPTIONS!$B$13) -> 29.17999 | BL16: =$H16+$R16 -> 0 | BM16: =PLAY!$H16 -> 0 | BN16: =$BI16*ASSUMPTIONS!$B$15+$BK16*ASSUMPTIONS!$B$16 -> 36.57888 | BO16: =$BO15+$BN16-$BL16-$BM16-ASSUMPTIONS!$B$23 -> 136.70419 | BP16: =(SUMPRODUCT(($F$8:$F$15+$A$8:$A$15=$A16)*($C$8:$C$15<>"NONE")*$G$8:$G$15)+SUMPRODUCT(($P$8:$P$15+$A$8:$A$15=$A16)*($M$8:$M$15<>"NONE")*$Q$8:$Q$15))*(1+ASSUMPTIONS!$B$22*(MAX(0,ABS($AA16)/$AI16-1)+MAX(0,ABS($AB16)/$AJ16-1)+MAX(0,ABS($AC16)/$AK16-1)+MAX(0,ABS($AD16)/$AL16-1)+MAX(0,ABS($AE16)/$AM16-1)+MAX(0,ABS($AF16)/$AN16-1)+MAX(0,ABS($AG16)/$AO16-1)+MAX(0,ABS($AH16)/$AP16-1))/8) -> 0 | BQ16: =MAX(0,$BQ15*(1-ASSUMPTIONS!$B$18)+$BP16-$BM16*ASSUMPTIONS!$B$17) -> 1.5870787
A17: 10 | B17: =CLIMATE!B17 -> 1948 | C17: =IFERROR(INDEX(CAPABILITIES!$B$7:$B$15,MATCH(PLAY!$D17,CAPABILITIES!$A$7:$A$15,0)),"NONE") -> NONE | D17: =IFERROR(IF(INDEX(CAPABILITIES!$B$7:$B$15,MATCH(PLAY!$D17,CAPABILITIES!$A$7:$A$15,0))="DRIVER",INDEX(CAPABILITIES!$C$7:$C$15,MATCH(PLAY!$D17,CAPABILITIES!$A$7:$A$15,0)),PLAY!$E17),"") -> 0 | E17: =IFERROR(INDEX(CAPABILITIES!$D$7:$D$15,MATCH(PLAY!$D17,CAPABILITIES!$A$7:$A$15,0))*IF(INDEX(CAPABILITIES!$K$7:$K$15,MATCH(PLAY!$D17,CAPABILITIES!$A$7:$A$15,0))="Y",IF(IFERROR(INDEX($AA16:$AH16,MATCH(PLAY!$E17,REGIONS!$B$7:$B$14,0)),0)<ASSUMPTIONS!$B$20,1,ASSUMPTIONS!$B$21),1),0) -> 0 | F17: =IFERROR(INDEX(CAPABILITIES!$E$7:$E$15,MATCH(PLAY!$D17,CAPABILITIES!$A$7:$A$15,0)),0) -> 0 | G17: =IFERROR(INDEX(CAPABILITIES!$F$7:$F$15,MATCH(PLAY!$D17,CAPABILITIES!$A$7:$A$15,0)),0) -> 0 | H17: =IFERROR(INDEX(CAPABILITIES!$G$7:$G$15,MATCH(PLAY!$D17,CAPABILITIES!$A$7:$A$15,0)),0) -> 0 | I17: =IFERROR(INDEX(CAPABILITIES!$H$7:$H$15,MATCH(PLAY!$D17,CAPABILITIES!$A$7:$A$15,0)),"") -> 0 | J17: =IFERROR(INDEX(CAPABILITIES!$D$7:$D$15,MATCH(PLAY!$D17,CAPABILITIES!$A$7:$A$15,0))*INDEX(CAPABILITIES!$I$7:$I$15,MATCH(PLAY!$D17,CAPABILITIES!$A$7:$A$15,0)),0) -> 0 | K17: =IFERROR(INDEX(CAPABILITIES!$E$7:$E$15,MATCH(PLAY!$D17,CAPABILITIES!$A$7:$A$15,0))+INDEX(CAPABILITIES!$J$7:$J$15,MATCH(PLAY!$D17,CAPABILITIES!$A$7:$A$15,0)),0) -> 0 | L17: =IFERROR(INDEX(CAPABILITIES!$L$7:$L$15,MATCH(PLAY!$D17,CAPABILITIES!$A$7:$A$15,0)),0) -> 0 | M17: =IFERROR(INDEX(CAPABILITIES!$B$7:$B$15,MATCH(PLAY!$F17,CAPABILITIES!$A$7:$A$15,0)),"NONE") -> NONE | N17: =IFERROR(IF(INDEX(CAPABILITIES!$B$7:$B$15,MATCH(PLAY!$F17,CAPABILITIES!$A$7:$A$15,0))="DRIVER",INDEX(CAPABILITIES!$C$7:$C$15,MATCH(PLAY!$F17,CAPABILITIES!$A$7:$A$15,0)),PLAY!$G17),"") -> 0 | O17: =IFERROR(INDEX(CAPABILITIES!$D$7:$D$15,MATCH(PLAY!$F17,CAPABILITIES!$A$7:$A$15,0))*IF(INDEX(CAPABILITIES!$K$7:$K$15,MATCH(PLAY!$F17,CAPABILITIES!$A$7:$A$15,0))="Y",IF(IFERROR(INDEX($AA16:$AH16,MATCH(PLAY!$G17,REGIONS!$B$7:$B$14,0)),0)<ASSUMPTIONS!$B$20,1,ASSUMPTIONS!$B$21),1),0) -> 0 | P17: =IFERROR(INDEX(CAPABILITIES!$E$7:$E$15,MATCH(PLAY!$F17,CAPABILITIES!$A$7:$A$15,0)),0) -> 0 | Q17: =IFERROR(INDEX(CAPABILITIES!$F$7:$F$15,MATCH(PLAY!$F17,CAPABILITIES!$A$7:$A$15,0)),0) -> 0 | R17: =IFERROR(INDEX(CAPABILITIES!$G$7:$G$15,MATCH(PLAY!$F17,CAPABILITIES!$A$7:$A$15,0)),0) -> 0 | S17: =IFERROR(INDEX(CAPABILITIES!$H$7:$H$15,MATCH(PLAY!$F17,CAPABILITIES!$A$7:$A$15,0)),"") -> 0 | T17: =IFERROR(INDEX(CAPABILITIES!$D$7:$D$15,MATCH(PLAY!$F17,CAPABILITIES!$A$7:$A$15,0))*INDEX(CAPABILITIES!$I$7:$I$15,MATCH(PLAY!$F17,CAPABILITIES!$A$7:$A$15,0)),0) -> 0 | U17: =IFERROR(INDEX(CAPABILITIES!$E$7:$E$15,MATCH(PLAY!$F17,CAPABILITIES!$A$7:$A$15,0))+INDEX(CAPABILITIES!$J$7:$J$15,MATCH(PLAY!$F17,CAPABILITIES!$A$7:$A$15,0)),0) -> 0 | V17: =IFERROR(INDEX(CAPABILITIES!$L$7:$L$15,MATCH(PLAY!$F17,CAPABILITIES!$A$7:$A$15,0)),0) -> 0 | W17: =CLIMATE!D17+SUMPRODUCT(($D$8:$D$16="ENSO")*($F$8:$F$16+$A$8:$A$16=$A17)*$E$8:$E$16)+SUMPRODUCT(($I$8:$I$16="ENSO")*($K$8:$K$16+$A$8:$A$16=$A17)*$J$8:$J$16)+SUMPRODUCT(($N$8:$N$16="ENSO")*($P$8:$P$16+$A$8:$A$16=$A17)*$O$8:$O$16)+SUMPRODUCT(($S$8:$S$16="ENSO")*($U$8:$U$16+$A$8:$A$16=$A17)*$T$8:$T$16) -> -1.107 | X17: =CLIMATE!E17+SUMPRODUCT(($D$8:$D$16="IOD")*($F$8:$F$16+$A$8:$A$16=$A17)*$E$8:$E$16)+SUMPRODUCT(($I$8:$I$16="IOD")*($K$8:$K$16+$A$8:$A$16=$A17)*$J$8:$J$16)+SUMPRODUCT(($N$8:$N$16="IOD")*($P$8:$P$16+$A$8:$A$16=$A17)*$O$8:$O$16)+SUMPRODUCT(($S$8:$S$16="IOD")*($U$8:$U$16+$A$8:$A$16=$A17)*$T$8:$T$16) -> 0.664 | Y17: =CLIMATE!F17+SUMPRODUCT(($D$8:$D$16="NATL")*($F$8:$F$16+$A$8:$A$16=$A17)*$E$8:$E$16)+SUMPRODUCT(($I$8:$I$16="NATL")*($K$8:$K$16+$A$8:$A$16=$A17)*$J$8:$J$16)+SUMPRODUCT(($N$8:$N$16="NATL")*($P$8:$P$16+$A$8:$A$16=$A17)*$O$8:$O$16)+SUMPRODUCT(($S$8:$S$16="NATL")*($U$8:$U$16+$A$8:$A$16=$A17)*$T$8:$T$16) -> 0.327 | Z17: =CLIMATE!G17+SUMPRODUCT(($D$8:$D$16="GLOBAL")*($F$8:$F$16+$A$8:$A$16=$A17)*$E$8:$E$16)+SUMPRODUCT(($I$8:$I$16="GLOBAL")*($K$8:$K$16+$A$8:$A$16=$A17)*$J$8:$J$16)+SUMPRODUCT(($N$8:$N$16="GLOBAL")*($P$8:$P$16+$A$8:$A$16=$A17)*$O$8:$O$16)+SUMPRODUCT(($S$8:$S$16="GLOBAL")*($U$8:$U$16+$A$8:$A$16=$A17)*$T$8:$T$16) -> 0 | AA17: =CLIMATE!H17+IFERROR(INDEX($W$8:$W$47,$A17-GRAPH!B17),0)*GRAPH!B9+IFERROR(INDEX($X$8:$X$47,$A17-GRAPH!B18),0)*GRAPH!B10+IFERROR(INDEX($Y$8:$Y$47,$A17-GRAPH!B19),0)*GRAPH!B11+IFERROR(INDEX($Z$8:$Z$47,$A17-GRAPH!B20),0)*GRAPH!B12+SUMPRODUCT(($D$8:$D$16=REGIONS!$B$7)*($F$8:$F$16+$A$8:$A$16=$A17)*$E$8:$E$16)+SUMPRODUCT(($N$8:$N$16=REGIONS!$B$7)*($P$8:$P$16+$A$8:$A$16=$A17)*$O$8:$O$16) -> 0.0794 | AB17: =CLIMATE!I17+IFERROR(INDEX($W$8:$W$47,$A17-GRAPH!C17),0)*GRAPH!C9+IFERROR(INDEX($X$8:$X$47,$A17-GRAPH!C18),0)*GRAPH!C10+IFERROR(INDEX($Y$8:$Y$47,$A17-GRAPH!C19),0)*GRAPH!C11+IFERROR(INDEX($Z$8:$Z$47,$A17-GRAPH!C20),0)*GRAPH!C12+SUMPRODUCT(($D$8:$D$16=REGIONS!$B$8)*($F$8:$F$16+$A$8:$A$16=$A17)*$E$8:$E$16)+SUMPRODUCT(($N$8:$N$16=REGIONS!$B$8)*($P$8:$P$16+$A$8:$A$16=$A17)*$O$8:$O$16) -> 0.2312 | AC17: =CLIMATE!J17+IFERROR(INDEX($W$8:$W$47,$A17-GRAPH!D17),0)*GRAPH!D9+IFERROR(INDEX($X$8:$X$47,$A17-GRAPH!D18),0)*GRAPH!D10+IFERROR(INDEX($Y$8:$Y$47,$A17-GRAPH!D19),0)*GRAPH!D11+IFERROR(INDEX($Z$8:$Z$47,$A17-GRAPH!D20),0)*GRAPH!D12+SUMPRODUCT(($D$8:$D$16=REGIONS!$B$9)*($F$8:$F$16+$A$8:$A$16=$A17)*$E$8:$E$16)+SUMPRODUCT(($N$8:$N$16=REGIONS!$B$9)*($P$8:$P$16+$A$8:$A$16=$A17)*$O$8:$O$16) -> -0.236 | AD17: =CLIMATE!K17+IFERROR(INDEX($W$8:$W$47,$A17-GRAPH!E17),0)*GRAPH!E9+IFERROR(INDEX($X$8:$X$47,$A17-GRAPH!E18),0)*GRAPH!E10+IFERROR(INDEX($Y$8:$Y$47,$A17-GRAPH!E19),0)*GRAPH!E11+IFERROR(INDEX($Z$8:$Z$47,$A17-GRAPH!E20),0)*GRAPH!E12+SUMPRODUCT(($D$8:$D$16=REGIONS!$B$10)*($F$8:$F$16+$A$8:$A$16=$A17)*$E$8:$E$16)+SUMPRODUCT(($N$8:$N$16=REGIONS!$B$10)*($P$8:$P$16+$A$8:$A$16=$A17)*$O$8:$O$16) -> 1.1885 | AE17: =CLIMATE!L17+IFERROR(INDEX($W$8:$W$47,$A17-GRAPH!F17),0)*GRAPH!F9+IFERROR(INDEX($X$8:$X$47,$A17-GRAPH!F18),0)*GRAPH!F10+IFERROR(INDEX($Y$8:$Y$47,$A17-GRAPH!F19),0)*GRAPH!F11+IFERROR(INDEX($Z$8:$Z$47,$A17-GRAPH!F20),0)*GRAPH!F12+SUMPRODUCT(($D$8:$D$16=REGIONS!$B$11)*($F$8:$F$16+$A$8:$A$16=$A17)*$E$8:$E$16)+SUMPRODUCT(($N$8:$N$16=REGIONS!$B$11)*($P$8:$P$16+$A$8:$A$16=$A17)*$O$8:$O$16) -> 1.3896 | AF17: =CLIMATE!M17+IFERROR(INDEX($W$8:$W$47,$A17-GRAPH!G17),0)*GRAPH!G9+IFERROR(INDEX($X$8:$X$47,$A17-GRAPH!G18),0)*GRAPH!G10+IFERROR(INDEX($Y$8:$Y$47,$A17-GRAPH!G19),0)*GRAPH!G11+IFERROR(INDEX($Z$8:$Z$47,$A17-GRAPH!G20),0)*GRAPH!G12+SUMPRODUCT(($D$8:$D$16=REGIONS!$B$12)*($F$8:$F$16+$A$8:$A$16=$A17)*$E$8:$E$16)+SUMPRODUCT(($N$8:$N$16=REGIONS!$B$12)*($P$8:$P$16+$A$8:$A$16=$A17)*$O$8:$O$16) -> 1.2838 | AG17: =CLIMATE!N17+IFERROR(INDEX($W$8:$W$47,$A17-GRAPH!H17),0)*GRAPH!H9+IFERROR(INDEX($X$8:$X$47,$A17-GRAPH!H18),0)*GRAPH!H10+IFERROR(INDEX($Y$8:$Y$47,$A17-GRAPH!H19),0)*GRAPH!H11+IFERROR(INDEX($Z$8:$Z$47,$A17-GRAPH!H20),0)*GRAPH!H12+SUMPRODUCT(($D$8:$D$16=REGIONS!$B$13)*($F$8:$F$16+$A$8:$A$16=$A17)*$E$8:$E$16)+SUMPRODUCT(($N$8:$N$16=REGIONS!$B$13)*($P$8:$P$16+$A$8:$A$16=$A17)*$O$8:$O$16) -> 0.8802 | AH17: =CLIMATE!O17+IFERROR(INDEX($W$8:$W$47,$A17-GRAPH!I17),0)*GRAPH!I9+IFERROR(INDEX($X$8:$X$47,$A17-GRAPH!I18),0)*GRAPH!I10+IFERROR(INDEX($Y$8:$Y$47,$A17-GRAPH!I19),0)*GRAPH!I11+IFERROR(INDEX($Z$8:$Z$47,$A17-GRAPH!I20),0)*GRAPH!I12+SUMPRODUCT(($D$8:$D$16=REGIONS!$B$14)*($F$8:$F$16+$A$8:$A$16=$A17)*$E$8:$E$16)+SUMPRODUCT(($N$8:$N$16=REGIONS!$B$14)*($P$8:$P$16+$A$8:$A$16=$A17)*$O$8:$O$16) -> 0.1846 | AI17: =REGIONS!$F$7*(1+ASSUMPTIONS!$B$19*$A17) -> 0.848 | AJ17: =REGIONS!$F$8*(1+ASSUMPTIONS!$B$19*$A17) -> 0.954 | AK17: =REGIONS!$F$9*(1+ASSUMPTIONS!$B$19*$A17) -> 0.954 | AL17: =REGIONS!$F$10*(1+ASSUMPTIONS!$B$19*$A17) -> 0.742 | AM17: =REGIONS!$F$11*(1+ASSUMPTIONS!$B$19*$A17) -> 0.742 | AN17: =REGIONS!$F$12*(1+ASSUMPTIONS!$B$19*$A17) -> 1.166 | AO17: =REGIONS!$F$13*(1+ASSUMPTIONS!$B$19*$A17) -> 1.272 | AP17: =REGIONS!$F$14*(1+ASSUMPTIONS!$B$19*$A17) -> 1.272 | AQ17: =SUMPRODUCT(($D$8:$D$47=REGIONS!$B$7)*($A$8:$A$47<=$A17)*$L$8:$L$47)+SUMPRODUCT(($N$8:$N$47=REGIONS!$B$7)*($A$8:$A$47<=$A17)*$V$8:$V$47) -> 0 | AR17: =SUMPRODUCT(($D$8:$D$47=REGIONS!$B$8)*($A$8:$A$47<=$A17)*$L$8:$L$47)+SUMPRODUCT(($N$8:$N$47=REGIONS!$B$8)*($A$8:$A$47<=$A17)*$V$8:$V$47) -> 0 | AS17: =SUMPRODUCT(($D$8:$D$47=REGIONS!$B$9)*($A$8:$A$47<=$A17)*$L$8:$L$47)+SUMPRODUCT(($N$8:$N$47=REGIONS!$B$9)*($A$8:$A$47<=$A17)*$V$8:$V$47) -> 0 | AT17: =SUMPRODUCT(($D$8:$D$47=REGIONS!$B$10)*($A$8:$A$47<=$A17)*$L$8:$L$47)+SUMPRODUCT(($N$8:$N$47=REGIONS!$B$10)*($A$8:$A$47<=$A17)*$V$8:$V$47) -> 0 | AU17: =SUMPRODUCT(($D$8:$D$47=REGIONS!$B$11)*($A$8:$A$47<=$A17)*$L$8:$L$47)+SUMPRODUCT(($N$8:$N$47=REGIONS!$B$11)*($A$8:$A$47<=$A17)*$V$8:$V$47) -> 0 | AV17: =SUMPRODUCT(($D$8:$D$47=REGIONS!$B$12)*($A$8:$A$47<=$A17)*$L$8:$L$47)+SUMPRODUCT(($N$8:$N$47=REGIONS!$B$12)*($A$8:$A$47<=$A17)*$V$8:$V$47) -> 0 | AW17: =SUMPRODUCT(($D$8:$D$47=REGIONS!$B$13)*($A$8:$A$47<=$A17)*$L$8:$L$47)+SUMPRODUCT(($N$8:$N$47=REGIONS!$B$13)*($A$8:$A$47<=$A17)*$V$8:$V$47) -> 0 | AX17: =SUMPRODUCT(($D$8:$D$47=REGIONS!$B$14)*($A$8:$A$47<=$A17)*$L$8:$L$47)+SUMPRODUCT(($N$8:$N$47=REGIONS!$B$14)*($A$8:$A$47<=$A17)*$V$8:$V$47) -> 0 | AY17: =MAX(0,MIN(135,100-(MAX(0,-$AA17)*REGIONS!$E$7*ASSUMPTIONS!$B$7+MAX(0,$AA17-ASSUMPTIONS!$B$9)*REGIONS!$E$7*ASSUMPTIONS!$B$8)*(1-$AQ17/100))) -> 100 | AZ17: =MAX(0,MIN(135,100-(MAX(0,-$AB17)*REGIONS!$E$8*ASSUMPTIONS!$B$7+MAX(0,$AB17-ASSUMPTIONS!$B$9)*REGIONS!$E$8*ASSUMPTIONS!$B$8)*(1-$AR17/100))) -> 100 | BA17: =MAX(0,MIN(135,100-(MAX(0,-$AC17)*REGIONS!$E$9*ASSUMPTIONS!$B$7+MAX(0,$AC17-ASSUMPTIONS!$B$9)*REGIONS!$E$9*ASSUMPTIONS!$B$8)*(1-$AS17/100))) -> 96.696 | BB17: =MAX(0,MIN(135,100-(MAX(0,-$AD17)*REGIONS!$E$10*ASSUMPTIONS!$B$7+MAX(0,$AD17-ASSUMPTIONS!$B$9)*REGIONS!$E$10*ASSUMPTIONS!$B$8)*(1-$AT17/100))) -> 100 | BC17: =MAX(0,MIN(135,100-(MAX(0,-$AE17)*REGIONS!$E$11*ASSUMPTIONS!$B$7+MAX(0,$AE17-ASSUMPTIONS!$B$9)*REGIONS!$E$11*ASSUMPTIONS!$B$8)*(1-$AU17/100))) -> 98.33152 | BD17: =MAX(0,MIN(135,100-(MAX(0,-$AF17)*REGIONS!$E$12*ASSUMPTIONS!$B$7+MAX(0,$AF17-ASSUMPTIONS!$B$9)*REGIONS!$E$12*ASSUMPTIONS!$B$8)*(1-$AV17/100))) -> 99.12848 | BE17: =MAX(0,MIN(135,100-(MAX(0,-$AG17)*REGIONS!$E$13*ASSUMPTIONS!$B$7+MAX(0,$AG17-ASSUMPTIONS!$B$9)*REGIONS!$E$13*ASSUMPTIONS!$B$8)*(1-$AW17/100))) -> 100 | BF17: =MAX(0,MIN(135,100-(MAX(0,-$AH17)*REGIONS!$E$14*ASSUMPTIONS!$B$7+MAX(0,$AH17-ASSUMPTIONS!$B$9)*REGIONS!$E$14*ASSUMPTIONS!$B$8)*(1-$AX17/100))) -> 100 | BG17: =$AY17*REGIONS!$D$7/100+$AZ17*REGIONS!$D$8/100+$BA17*REGIONS!$D$9/100+$BB17*REGIONS!$D$10/100+$BC17*REGIONS!$D$11/100+$BD17*REGIONS!$D$12/100+$BE17*REGIONS!$D$13/100+$BF17*REGIONS!$D$14/100 -> 99.243176 | BH17: =100*(100/MAX(1,$BG17))^ASSUMPTIONS!$B$10 -> 101.37686 | BI17: =$AY17*$BH17/100*ASSUMPTIONS!$B$11 -> 86.170328 | BJ17: =MAX(0,ABS($AA17)-$AI17*ASSUMPTIONS!$B$24)*REGIONS!$D$7/100+MAX(0,ABS($AB17)-$AJ17*ASSUMPTIONS!$B$24)*REGIONS!$D$8/100+MAX(0,ABS($AC17)-$AK17*ASSUMPTIONS!$B$24)*REGIONS!$D$9/100+MAX(0,ABS($AD17)-$AL17*ASSUMPTIONS!$B$24)*REGIONS!$D$10/100+MAX(0,ABS($AE17)-$AM17*ASSUMPTIONS!$B$24)*REGIONS!$D$11/100+MAX(0,ABS($AF17)-$AN17*ASSUMPTIONS!$B$24)*REGIONS!$D$12/100+MAX(0,ABS($AG17)-$AO17*ASSUMPTIONS!$B$24)*REGIONS!$D$13/100+MAX(0,ABS($AH17)-$AP17*ASSUMPTIONS!$B$24)*REGIONS!$D$14/100 -> 0.242383 | BK17: =MIN(ASSUMPTIONS!$B$14,ASSUMPTIONS!$B$12+$BJ17*ASSUMPTIONS!$B$13) -> 38.180086 | BL17: =$H17+$R17 -> 0 | BM17: =PLAY!$H17 -> 0 | BN17: =$BI17*ASSUMPTIONS!$B$15+$BK17*ASSUMPTIONS!$B$16 -> 44.702517 | BO17: =$BO16+$BN17-$BL17-$BM17-ASSUMPTIONS!$B$23 -> 149.4067 | BP17: =(SUMPRODUCT(($F$8:$F$16+$A$8:$A$16=$A17)*($C$8:$C$16<>"NONE")*$G$8:$G$16)+SUMPRODUCT(($P$8:$P$16+$A$8:$A$16=$A17)*($M$8:$M$16<>"NONE")*$Q$8:$Q$16))*(1+ASSUMPTIONS!$B$22*(MAX(0,ABS($AA17)/$AI17-1)+MAX(0,ABS($AB17)/$AJ17-1)+MAX(0,ABS($AC17)/$AK17-1)+MAX(0,ABS($AD17)/$AL17-1)+MAX(0,ABS($AE17)/$AM17-1)+MAX(0,ABS($AF17)/$AN17-1)+MAX(0,ABS($AG17)/$AO17-1)+MAX(0,ABS($AH17)/$AP17-1))/8) -> 0 | BQ17: =MAX(0,$BQ16*(1-ASSUMPTIONS!$B$18)+$BP17-$BM17*ASSUMPTIONS!$B$17) -> 1.5235956
A18: 11 | B18: =CLIMATE!B18 -> 1948 | C18: =IFERROR(INDEX(CAPABILITIES!$B$7:$B$15,MATCH(PLAY!$D18,CAPABILITIES!$A$7:$A$15,0)),"NONE") -> NONE | D18: =IFERROR(IF(INDEX(CAPABILITIES!$B$7:$B$15,MATCH(PLAY!$D18,CAPABILITIES!$A$7:$A$15,0))="DRIVER",INDEX(CAPABILITIES!$C$7:$C$15,MATCH(PLAY!$D18,CAPABILITIES!$A$7:$A$15,0)),PLAY!$E18),"") -> 0 | E18: =IFERROR(INDEX(CAPABILITIES!$D$7:$D$15,MATCH(PLAY!$D18,CAPABILITIES!$A$7:$A$15,0))*IF(INDEX(CAPABILITIES!$K$7:$K$15,MATCH(PLAY!$D18,CAPABILITIES!$A$7:$A$15,0))="Y",IF(IFERROR(INDEX($AA17:$AH17,MATCH(PLAY!$E18,REGIONS!$B$7:$B$14,0)),0)<ASSUMPTIONS!$B$20,1,ASSUMPTIONS!$B$21),1),0) -> 0 | F18: =IFERROR(INDEX(CAPABILITIES!$E$7:$E$15,MATCH(PLAY!$D18,CAPABILITIES!$A$7:$A$15,0)),0) -> 0 | G18: =IFERROR(INDEX(CAPABILITIES!$F$7:$F$15,MATCH(PLAY!$D18,CAPABILITIES!$A$7:$A$15,0)),0) -> 0 | H18: =IFERROR(INDEX(CAPABILITIES!$G$7:$G$15,MATCH(PLAY!$D18,CAPABILITIES!$A$7:$A$15,0)),0) -> 0 | I18: =IFERROR(INDEX(CAPABILITIES!$H$7:$H$15,MATCH(PLAY!$D18,CAPABILITIES!$A$7:$A$15,0)),"") -> 0 | J18: =IFERROR(INDEX(CAPABILITIES!$D$7:$D$15,MATCH(PLAY!$D18,CAPABILITIES!$A$7:$A$15,0))*INDEX(CAPABILITIES!$I$7:$I$15,MATCH(PLAY!$D18,CAPABILITIES!$A$7:$A$15,0)),0) -> 0 | K18: =IFERROR(INDEX(CAPABILITIES!$E$7:$E$15,MATCH(PLAY!$D18,CAPABILITIES!$A$7:$A$15,0))+INDEX(CAPABILITIES!$J$7:$J$15,MATCH(PLAY!$D18,CAPABILITIES!$A$7:$A$15,0)),0) -> 0 | L18: =IFERROR(INDEX(CAPABILITIES!$L$7:$L$15,MATCH(PLAY!$D18,CAPABILITIES!$A$7:$A$15,0)),0) -> 0 | M18: =IFERROR(INDEX(CAPABILITIES!$B$7:$B$15,MATCH(PLAY!$F18,CAPABILITIES!$A$7:$A$15,0)),"NONE") -> NONE | N18: =IFERROR(IF(INDEX(CAPABILITIES!$B$7:$B$15,MATCH(PLAY!$F18,CAPABILITIES!$A$7:$A$15,0))="DRIVER",INDEX(CAPABILITIES!$C$7:$C$15,MATCH(PLAY!$F18,CAPABILITIES!$A$7:$A$15,0)),PLAY!$G18),"") -> 0 | O18: =IFERROR(INDEX(CAPABILITIES!$D$7:$D$15,MATCH(PLAY!$F18,CAPABILITIES!$A$7:$A$15,0))*IF(INDEX(CAPABILITIES!$K$7:$K$15,MATCH(PLAY!$F18,CAPABILITIES!$A$7:$A$15,0))="Y",IF(IFERROR(INDEX($AA17:$AH17,MATCH(PLAY!$G18,REGIONS!$B$7:$B$14,0)),0)<ASSUMPTIONS!$B$20,1,ASSUMPTIONS!$B$21),1),0) -> 0 | P18: =IFERROR(INDEX(CAPABILITIES!$E$7:$E$15,MATCH(PLAY!$F18,CAPABILITIES!$A$7:$A$15,0)),0) -> 0 | Q18: =IFERROR(INDEX(CAPABILITIES!$F$7:$F$15,MATCH(PLAY!$F18,CAPABILITIES!$A$7:$A$15,0)),0) -> 0 | R18: =IFERROR(INDEX(CAPABILITIES!$G$7:$G$15,MATCH(PLAY!$F18,CAPABILITIES!$A$7:$A$15,0)),0) -> 0 | S18: =IFERROR(INDEX(CAPABILITIES!$H$7:$H$15,MATCH(PLAY!$F18,CAPABILITIES!$A$7:$A$15,0)),"") -> 0 | T18: =IFERROR(INDEX(CAPABILITIES!$D$7:$D$15,MATCH(PLAY!$F18,CAPABILITIES!$A$7:$A$15,0))*INDEX(CAPABILITIES!$I$7:$I$15,MATCH(PLAY!$F18,CAPABILITIES!$A$7:$A$15,0)),0) -> 0 | U18: =IFERROR(INDEX(CAPABILITIES!$E$7:$E$15,MATCH(PLAY!$F18,CAPABILITIES!$A$7:$A$15,0))+INDEX(CAPABILITIES!$J$7:$J$15,MATCH(PLAY!$F18,CAPABILITIES!$A$7:$A$15,0)),0) -> 0 | V18: =IFERROR(INDEX(CAPABILITIES!$L$7:$L$15,MATCH(PLAY!$F18,CAPABILITIES!$A$7:$A$15,0)),0) -> 0 | W18: =CLIMATE!D18+SUMPRODUCT(($D$8:$D$17="ENSO")*($F$8:$F$17+$A$8:$A$17=$A18)*$E$8:$E$17)+SUMPRODUCT(($I$8:$I$17="ENSO")*($K$8:$K$17+$A$8:$A$17=$A18)*$J$8:$J$17)+SUMPRODUCT(($N$8:$N$17="ENSO")*($P$8:$P$17+$A$8:$A$17=$A18)*$O$8:$O$17)+SUMPRODUCT(($S$8:$S$17="ENSO")*($U$8:$U$17+$A$8:$A$17=$A18)*$T$8:$T$17) -> -0.472 | X18: =CLIMATE!E18+SUMPRODUCT(($D$8:$D$17="IOD")*($F$8:$F$17+$A$8:$A$17=$A18)*$E$8:$E$17)+SUMPRODUCT(($I$8:$I$17="IOD")*($K$8:$K$17+$A$8:$A$17=$A18)*$J$8:$J$17)+SUMPRODUCT(($N$8:$N$17="IOD")*($P$8:$P$17+$A$8:$A$17=$A18)*$O$8:$O$17)+SUMPRODUCT(($S$8:$S$17="IOD")*($U$8:$U$17+$A$8:$A$17=$A18)*$T$8:$T$17) -> -0.06 | Y18: =CLIMATE!F18+SUMPRODUCT(($D$8:$D$17="NATL")*($F$8:$F$17+$A$8:$A$17=$A18)*$E$8:$E$17)+SUMPRODUCT(($I$8:$I$17="NATL")*($K$8:$K$17+$A$8:$A$17=$A18)*$J$8:$J$17)+SUMPRODUCT(($N$8:$N$17="NATL")*($P$8:$P$17+$A$8:$A$17=$A18)*$O$8:$O$17)+SUMPRODUCT(($S$8:$S$17="NATL")*($U$8:$U$17+$A$8:$A$17=$A18)*$T$8:$T$17) -> 0.552 | Z18: =CLIMATE!G18+SUMPRODUCT(($D$8:$D$17="GLOBAL")*($F$8:$F$17+$A$8:$A$17=$A18)*$E$8:$E$17)+SUMPRODUCT(($I$8:$I$17="GLOBAL")*($K$8:$K$17+$A$8:$A$17=$A18)*$J$8:$J$17)+SUMPRODUCT(($N$8:$N$17="GLOBAL")*($P$8:$P$17+$A$8:$A$17=$A18)*$O$8:$O$17)+SUMPRODUCT(($S$8:$S$17="GLOBAL")*($U$8:$U$17+$A$8:$A$17=$A18)*$T$8:$T$17) -> 0 | AA18: =CLIMATE!H18+IFERROR(INDEX($W$8:$W$47,$A18-GRAPH!B17),0)*GRAPH!B9+IFERROR(INDEX($X$8:$X$47,$A18-GRAPH!B18),0)*GRAPH!B10+IFERROR(INDEX($Y$8:$Y$47,$A18-GRAPH!B19),0)*GRAPH!B11+IFERROR(INDEX($Z$8:$Z$47,$A18-GRAPH!B20),0)*GRAPH!B12+SUMPRODUCT(($D$8:$D$17=REGIONS!$B$7)*($F$8:$F$17+$A$8:$A$17=$A18)*$E$8:$E$17)+SUMPRODUCT(($N$8:$N$17=REGIONS!$B$7)*($P$8:$P$17+$A$8:$A$17=$A18)*$O$8:$O$17) -> -0.5072 | AB18: =CLIMATE!I18+IFERROR(INDEX($W$8:$W$47,$A18-GRAPH!C17),0)*GRAPH!C9+IFERROR(INDEX($X$8:$X$47,$A18-GRAPH!C18),0)*GRAPH!C10+IFERROR(INDEX($Y$8:$Y$47,$A18-GRAPH!C19),0)*GRAPH!C11+IFERROR(INDEX($Z$8:$Z$47,$A18-GRAPH!C20),0)*GRAPH!C12+SUMPRODUCT(($D$8:$D$17=REGIONS!$B$8)*($F$8:$F$17+$A$8:$A$17=$A18)*$E$8:$E$17)+SUMPRODUCT(($N$8:$N$17=REGIONS!$B$8)*($P$8:$P$17+$A$8:$A$17=$A18)*$O$8:$O$17) -> -0.0694 | AC18: =CLIMATE!J18+IFERROR(INDEX($W$8:$W$47,$A18-GRAPH!D17),0)*GRAPH!D9+IFERROR(INDEX($X$8:$X$47,$A18-GRAPH!D18),0)*GRAPH!D10+IFERROR(INDEX($Y$8:$Y$47,$A18-GRAPH!D19),0)*GRAPH!D11+IFERROR(INDEX($Z$8:$Z$47,$A18-GRAPH!D20),0)*GRAPH!D12+SUMPRODUCT(($D$8:$D$17=REGIONS!$B$9)*($F$8:$F$17+$A$8:$A$17=$A18)*$E$8:$E$17)+SUMPRODUCT(($N$8:$N$17=REGIONS!$B$9)*($P$8:$P$17+$A$8:$A$17=$A18)*$O$8:$O$17) -> -0.757 | AD18: =CLIMATE!K18+IFERROR(INDEX($W$8:$W$47,$A18-GRAPH!E17),0)*GRAPH!E9+IFERROR(INDEX($X$8:$X$47,$A18-GRAPH!E18),0)*GRAPH!E10+IFERROR(INDEX($Y$8:$Y$47,$A18-GRAPH!E19),0)*GRAPH!E11+IFERROR(INDEX($Z$8:$Z$47,$A18-GRAPH!E20),0)*GRAPH!E12+SUMPRODUCT(($D$8:$D$17=REGIONS!$B$10)*($F$8:$F$17+$A$8:$A$17=$A18)*$E$8:$E$17)+SUMPRODUCT(($N$8:$N$17=REGIONS!$B$10)*($P$8:$P$17+$A$8:$A$17=$A18)*$O$8:$O$17) -> 0.8805 | AE18: =CLIMATE!L18+IFERROR(INDEX($W$8:$W$47,$A18-GRAPH!F17),0)*GRAPH!F9+IFERROR(INDEX($X$8:$X$47,$A18-GRAPH!F18),0)*GRAPH!F10+IFERROR(INDEX($Y$8:$Y$47,$A18-GRAPH!F19),0)*GRAPH!F11+IFERROR(INDEX($Z$8:$Z$47,$A18-GRAPH!F20),0)*GRAPH!F12+SUMPRODUCT(($D$8:$D$17=REGIONS!$B$11)*($F$8:$F$17+$A$8:$A$17=$A18)*$E$8:$E$17)+SUMPRODUCT(($N$8:$N$17=REGIONS!$B$11)*($P$8:$P$17+$A$8:$A$17=$A18)*$O$8:$O$17) -> 0.7681 | AF18: =CLIMATE!M18+IFERROR(INDEX($W$8:$W$47,$A18-GRAPH!G17),0)*GRAPH!G9+IFERROR(INDEX($X$8:$X$47,$A18-GRAPH!G18),0)*GRAPH!G10+IFERROR(INDEX($Y$8:$Y$47,$A18-GRAPH!G19),0)*GRAPH!G11+IFERROR(INDEX($Z$8:$Z$47,$A18-GRAPH!G20),0)*GRAPH!G12+SUMPRODUCT(($D$8:$D$17=REGIONS!$B$12)*($F$8:$F$17+$A$8:$A$17=$A18)*$E$8:$E$17)+SUMPRODUCT(($N$8:$N$17=REGIONS!$B$12)*($P$8:$P$17+$A$8:$A$17=$A18)*$O$8:$O$17) -> 0.7589 | AG18: =CLIMATE!N18+IFERROR(INDEX($W$8:$W$47,$A18-GRAPH!H17),0)*GRAPH!H9+IFERROR(INDEX($X$8:$X$47,$A18-GRAPH!H18),0)*GRAPH!H10+IFERROR(INDEX($Y$8:$Y$47,$A18-GRAPH!H19),0)*GRAPH!H11+IFERROR(INDEX($Z$8:$Z$47,$A18-GRAPH!H20),0)*GRAPH!H12+SUMPRODUCT(($D$8:$D$17=REGIONS!$B$13)*($F$8:$F$17+$A$8:$A$17=$A18)*$E$8:$E$17)+SUMPRODUCT(($N$8:$N$17=REGIONS!$B$13)*($P$8:$P$17+$A$8:$A$17=$A18)*$O$8:$O$17) -> 0.8885 | AH18: =CLIMATE!O18+IFERROR(INDEX($W$8:$W$47,$A18-GRAPH!I17),0)*GRAPH!I9+IFERROR(INDEX($X$8:$X$47,$A18-GRAPH!I18),0)*GRAPH!I10+IFERROR(INDEX($Y$8:$Y$47,$A18-GRAPH!I19),0)*GRAPH!I11+IFERROR(INDEX($Z$8:$Z$47,$A18-GRAPH!I20),0)*GRAPH!I12+SUMPRODUCT(($D$8:$D$17=REGIONS!$B$14)*($F$8:$F$17+$A$8:$A$17=$A18)*$E$8:$E$17)+SUMPRODUCT(($N$8:$N$17=REGIONS!$B$14)*($P$8:$P$17+$A$8:$A$17=$A18)*$O$8:$O$17) -> -0.0764 | AI18: =REGIONS!$F$7*(1+ASSUMPTIONS!$B$19*$A18) -> 0.8528 | AJ18: =REGIONS!$F$8*(1+ASSUMPTIONS!$B$19*$A18) -> 0.9594 | AK18: =REGIONS!$F$9*(1+ASSUMPTIONS!$B$19*$A18) -> 0.9594 | AL18: =REGIONS!$F$10*(1+ASSUMPTIONS!$B$19*$A18) -> 0.7462 | AM18: =REGIONS!$F$11*(1+ASSUMPTIONS!$B$19*$A18) -> 0.7462 | AN18: =REGIONS!$F$12*(1+ASSUMPTIONS!$B$19*$A18) -> 1.1726 | AO18: =REGIONS!$F$13*(1+ASSUMPTIONS!$B$19*$A18) -> 1.2792 | AP18: =REGIONS!$F$14*(1+ASSUMPTIONS!$B$19*$A18) -> 1.2792 | AQ18: =SUMPRODUCT(($D$8:$D$47=REGIONS!$B$7)*($A$8:$A$47<=$A18)*$L$8:$L$47)+SUMPRODUCT(($N$8:$N$47=REGIONS!$B$7)*($A$8:$A$47<=$A18)*$V$8:$V$47) -> 0 | AR18: =SUMPRODUCT(($D$8:$D$47=REGIONS!$B$8)*($A$8:$A$47<=$A18)*$L$8:$L$47)+SUMPRODUCT(($N$8:$N$47=REGIONS!$B$8)*($A$8:$A$47<=$A18)*$V$8:$V$47) -> 0 | AS18: =SUMPRODUCT(($D$8:$D$47=REGIONS!$B$9)*($A$8:$A$47<=$A18)*$L$8:$L$47)+SUMPRODUCT(($N$8:$N$47=REGIONS!$B$9)*($A$8:$A$47<=$A18)*$V$8:$V$47) -> 0 | AT18: =SUMPRODUCT(($D$8:$D$47=REGIONS!$B$10)*($A$8:$A$47<=$A18)*$L$8:$L$47)+SUMPRODUCT(($N$8:$N$47=REGIONS!$B$10)*($A$8:$A$47<=$A18)*$V$8:$V$47) -> 0 | AU18: =SUMPRODUCT(($D$8:$D$47=REGIONS!$B$11)*($A$8:$A$47<=$A18)*$L$8:$L$47)+SUMPRODUCT(($N$8:$N$47=REGIONS!$B$11)*($A$8:$A$47<=$A18)*$V$8:$V$47) -> 0 | AV18: =SUMPRODUCT(($D$8:$D$47=REGIONS!$B$12)*($A$8:$A$47<=$A18)*$L$8:$L$47)+SUMPRODUCT(($N$8:$N$47=REGIONS!$B$12)*($A$8:$A$47<=$A18)*$V$8:$V$47) -> 0 | AW18: =SUMPRODUCT(($D$8:$D$47=REGIONS!$B$13)*($A$8:$A$47<=$A18)*$L$8:$L$47)+SUMPRODUCT(($N$8:$N$47=REGIONS!$B$13)*($A$8:$A$47<=$A18)*$V$8:$V$47) -> 0 | AX18: =SUMPRODUCT(($D$8:$D$47=REGIONS!$B$14)*($A$8:$A$47<=$A18)*$L$8:$L$47)+SUMPRODUCT(($N$8:$N$47=REGIONS!$B$14)*($A$8:$A$47<=$A18)*$V$8:$V$47) -> 0 | AY18: =MAX(0,MIN(135,100-(MAX(0,-$AA18)*REGIONS!$E$7*ASSUMPTIONS!$B$7+MAX(0,$AA18-ASSUMPTIONS!$B$9)*REGIONS!$E$7*ASSUMPTIONS!$B$8)*(1-$AQ18/100))) -> 92.8992 | AZ18: =MAX(0,MIN(135,100-(MAX(0,-$AB18)*REGIONS!$E$8*ASSUMPTIONS!$B$7+MAX(0,$AB18-ASSUMPTIONS!$B$9)*REGIONS!$E$8*ASSUMPTIONS!$B$8)*(1-$AR18/100))) -> 98.93124 | BA18: =MAX(0,MIN(135,100-(MAX(0,-$AC18)*REGIONS!$E$9*ASSUMPTIONS!$B$7+MAX(0,$AC18-ASSUMPTIONS!$B$9)*REGIONS!$E$9*ASSUMPTIONS!$B$8)*(1-$AS18/100))) -> 89.402 | BB18: =MAX(0,MIN(135,100-(MAX(0,-$AD18)*REGIONS!$E$10*ASSUMPTIONS!$B$7+MAX(0,$AD18-ASSUMPTIONS!$B$9)*REGIONS!$E$10*ASSUMPTIONS!$B$8)*(1-$AT18/100))) -> 100 | BC18: =MAX(0,MIN(135,100-(MAX(0,-$AE18)*REGIONS!$E$11*ASSUMPTIONS!$B$7+MAX(0,$AE18-ASSUMPTIONS!$B$9)*REGIONS!$E$11*ASSUMPTIONS!$B$8)*(1-$AU18/100))) -> 100 | BD18: =MAX(0,MIN(135,100-(MAX(0,-$AF18)*REGIONS!$E$12*ASSUMPTIONS!$B$7+MAX(0,$AF18-ASSUMPTIONS!$B$9)*REGIONS!$E$12*ASSUMPTIONS!$B$8)*(1-$AV18/100))) -> 100 | BE18: =MAX(0,MIN(135,100-(MAX(0,-$AG18)*REGIONS!$E$13*ASSUMPTIONS!$B$7+MAX(0,$AG18-ASSUMPTIONS!$B$9)*REGIONS!$E$13*ASSUMPTIONS!$B$8)*(1-$AW18/100))) -> 100 | BF18: =MAX(0,MIN(135,100-(MAX(0,-$AH18)*REGIONS!$E$14*ASSUMPTIONS!$B$7+MAX(0,$AH18-ASSUMPTIONS!$B$9)*REGIONS!$E$14*ASSUMPTIONS!$B$8)*(1-$AX18/100))) -> 98.50256 | BG18: =$AY18*REGIONS!$D$7/100+$AZ18*REGIONS!$D$8/100+$BA18*REGIONS!$D$9/100+$BB18*REGIONS!$D$10/100+$BC18*REGIONS!$D$11/100+$BD18*REGIONS!$D$12/100+$BE18*REGIONS!$D$13/100+$BF18*REGIONS!$D$14/100 -> 96.729292 | BH18: =100*(100/MAX(1,$BG18))^ASSUMPTIONS!$B$10 -> 106.16848 | BI18: =$AY18*$BH18/100*ASSUMPTIONS!$B$11 -> 83.835215 | BJ18: =MAX(0,ABS($AA18)-$AI18*ASSUMPTIONS!$B$24)*REGIONS!$D$7/100+MAX(0,ABS($AB18)-$AJ18*ASSUMPTIONS!$B$24)*REGIONS!$D$8/100+MAX(0,ABS($AC18)-$AK18*ASSUMPTIONS!$B$24)*REGIONS!$D$9/100+MAX(0,ABS($AD18)-$AL18*ASSUMPTIONS!$B$24)*REGIONS!$D$10/100+MAX(0,ABS($AE18)-$AM18*ASSUMPTIONS!$B$24)*REGIONS!$D$11/100+MAX(0,ABS($AF18)-$AN18*ASSUMPTIONS!$B$24)*REGIONS!$D$12/100+MAX(0,ABS($AG18)-$AO18*ASSUMPTIONS!$B$24)*REGIONS!$D$13/100+MAX(0,ABS($AH18)-$AP18*ASSUMPTIONS!$B$24)*REGIONS!$D$14/100 -> 0.0883845 | BK18: =MIN(ASSUMPTIONS!$B$14,ASSUMPTIONS!$B$12+$BJ18*ASSUMPTIONS!$B$13) -> 31.712149 | BL18: =$H18+$R18 -> 0 | BM18: =PLAY!$H18 -> 0 | BN18: =$BI18*ASSUMPTIONS!$B$15+$BK18*ASSUMPTIONS!$B$16 -> 38.60116 | BO18: =$BO17+$BN18-$BL18-$BM18-ASSUMPTIONS!$B$23 -> 156.00786 | BP18: =(SUMPRODUCT(($F$8:$F$17+$A$8:$A$17=$A18)*($C$8:$C$17<>"NONE")*$G$8:$G$17)+SUMPRODUCT(($P$8:$P$17+$A$8:$A$17=$A18)*($M$8:$M$17<>"NONE")*$Q$8:$Q$17))*(1+ASSUMPTIONS!$B$22*(MAX(0,ABS($AA18)/$AI18-1)+MAX(0,ABS($AB18)/$AJ18-1)+MAX(0,ABS($AC18)/$AK18-1)+MAX(0,ABS($AD18)/$AL18-1)+MAX(0,ABS($AE18)/$AM18-1)+MAX(0,ABS($AF18)/$AN18-1)+MAX(0,ABS($AG18)/$AO18-1)+MAX(0,ABS($AH18)/$AP18-1))/8) -> 0 | BQ18: =MAX(0,$BQ17*(1-ASSUMPTIONS!$B$18)+$BP18-$BM18*ASSUMPTIONS!$B$17) -> 1.4626518
A19: 12 | B19: =CLIMATE!B19 -> 1948 | C19: =IFERROR(INDEX(CAPABILITIES!$B$7:$B$15,MATCH(PLAY!$D19,CAPABILITIES!$A$7:$A$15,0)),"NONE") -> NONE | D19: =IFERROR(IF(INDEX(CAPABILITIES!$B$7:$B$15,MATCH(PLAY!$D19,CAPABILITIES!$A$7:$A$15,0))="DRIVER",INDEX(CAPABILITIES!$C$7:$C$15,MATCH(PLAY!$D19,CAPABILITIES!$A$7:$A$15,0)),PLAY!$E19),"") -> 0 | E19: =IFERROR(INDEX(CAPABILITIES!$D$7:$D$15,MATCH(PLAY!$D19,CAPABILITIES!$A$7:$A$15,0))*IF(INDEX(CAPABILITIES!$K$7:$K$15,MATCH(PLAY!$D19,CAPABILITIES!$A$7:$A$15,0))="Y",IF(IFERROR(INDEX($AA18:$AH18,MATCH(PLAY!$E19,REGIONS!$B$7:$B$14,0)),0)<ASSUMPTIONS!$B$20,1,ASSUMPTIONS!$B$21),1),0) -> 0 | F19: =IFERROR(INDEX(CAPABILITIES!$E$7:$E$15,MATCH(PLAY!$D19,CAPABILITIES!$A$7:$A$15,0)),0) -> 0 | G19: =IFERROR(INDEX(CAPABILITIES!$F$7:$F$15,MATCH(PLAY!$D19,CAPABILITIES!$A$7:$A$15,0)),0) -> 0 | H19: =IFERROR(INDEX(CAPABILITIES!$G$7:$G$15,MATCH(PLAY!$D19,CAPABILITIES!$A$7:$A$15,0)),0) -> 0 | I19: =IFERROR(INDEX(CAPABILITIES!$H$7:$H$15,MATCH(PLAY!$D19,CAPABILITIES!$A$7:$A$15,0)),"") -> 0 | J19: =IFERROR(INDEX(CAPABILITIES!$D$7:$D$15,MATCH(PLAY!$D19,CAPABILITIES!$A$7:$A$15,0))*INDEX(CAPABILITIES!$I$7:$I$15,MATCH(PLAY!$D19,CAPABILITIES!$A$7:$A$15,0)),0) -> 0 | K19: =IFERROR(INDEX(CAPABILITIES!$E$7:$E$15,MATCH(PLAY!$D19,CAPABILITIES!$A$7:$A$15,0))+INDEX(CAPABILITIES!$J$7:$J$15,MATCH(PLAY!$D19,CAPABILITIES!$A$7:$A$15,0)),0) -> 0 | L19: =IFERROR(INDEX(CAPABILITIES!$L$7:$L$15,MATCH(PLAY!$D19,CAPABILITIES!$A$7:$A$15,0)),0) -> 0 | M19: =IFERROR(INDEX(CAPABILITIES!$B$7:$B$15,MATCH(PLAY!$F19,CAPABILITIES!$A$7:$A$15,0)),"NONE") -> NONE | N19: =IFERROR(IF(INDEX(CAPABILITIES!$B$7:$B$15,MATCH(PLAY!$F19,CAPABILITIES!$A$7:$A$15,0))="DRIVER",INDEX(CAPABILITIES!$C$7:$C$15,MATCH(PLAY!$F19,CAPABILITIES!$A$7:$A$15,0)),PLAY!$G19),"") -> 0 | O19: =IFERROR(INDEX(CAPABILITIES!$D$7:$D$15,MATCH(PLAY!$F19,CAPABILITIES!$A$7:$A$15,0))*IF(INDEX(CAPABILITIES!$K$7:$K$15,MATCH(PLAY!$F19,CAPABILITIES!$A$7:$A$15,0))="Y",IF(IFERROR(INDEX($AA18:$AH18,MATCH(PLAY!$G19,REGIONS!$B$7:$B$14,0)),0)<ASSUMPTIONS!$B$20,1,ASSUMPTIONS!$B$21),1),0) -> 0 | P19: =IFERROR(INDEX(CAPABILITIES!$E$7:$E$15,MATCH(PLAY!$F19,CAPABILITIES!$A$7:$A$15,0)),0) -> 0 | Q19: =IFERROR(INDEX(CAPABILITIES!$F$7:$F$15,MATCH(PLAY!$F19,CAPABILITIES!$A$7:$A$15,0)),0) -> 0 | R19: =IFERROR(INDEX(CAPABILITIES!$G$7:$G$15,MATCH(PLAY!$F19,CAPABILITIES!$A$7:$A$15,0)),0) -> 0 | S19: =IFERROR(INDEX(CAPABILITIES!$H$7:$H$15,MATCH(PLAY!$F19,CAPABILITIES!$A$7:$A$15,0)),"") -> 0 | T19: =IFERROR(INDEX(CAPABILITIES!$D$7:$D$15,MATCH(PLAY!$F19,CAPABILITIES!$A$7:$A$15,0))*INDEX(CAPABILITIES!$I$7:$I$15,MATCH(PLAY!$F19,CAPABILITIES!$A$7:$A$15,0)),0) -> 0 | U19: =IFERROR(INDEX(CAPABILITIES!$E$7:$E$15,MATCH(PLAY!$F19,CAPABILITIES!$A$7:$A$15,0))+INDEX(CAPABILITIES!$J$7:$J$15,MATCH(PLAY!$F19,CAPABILITIES!$A$7:$A$15,0)),0) -> 0 | V19: =IFERROR(INDEX(CAPABILITIES!$L$7:$L$15,MATCH(PLAY!$F19,CAPABILITIES!$A$7:$A$15,0)),0) -> 0 | W19: =CLIMATE!D19+SUMPRODUCT(($D$8:$D$18="ENSO")*($F$8:$F$18+$A$8:$A$18=$A19)*$E$8:$E$18)+SUMPRODUCT(($I$8:$I$18="ENSO")*($K$8:$K$18+$A$8:$A$18=$A19)*$J$8:$J$18)+SUMPRODUCT(($N$8:$N$18="ENSO")*($P$8:$P$18+$A$8:$A$18=$A19)*$O$8:$O$18)+SUMPRODUCT(($S$8:$S$18="ENSO")*($U$8:$U$18+$A$8:$A$18=$A19)*$T$8:$T$18) -> -0.054 | X19: =CLIMATE!E19+SUMPRODUCT(($D$8:$D$18="IOD")*($F$8:$F$18+$A$8:$A$18=$A19)*$E$8:$E$18)+SUMPRODUCT(($I$8:$I$18="IOD")*($K$8:$K$18+$A$8:$A$18=$A19)*$J$8:$J$18)+SUMPRODUCT(($N$8:$N$18="IOD")*($P$8:$P$18+$A$8:$A$18=$A19)*$O$8:$O$18)+SUMPRODUCT(($S$8:$S$18="IOD")*($U$8:$U$18+$A$8:$A$18=$A19)*$T$8:$T$18) -> -0.885 | Y19: =CLIMATE!F19+SUMPRODUCT(($D$8:$D$18="NATL")*($F$8:$F$18+$A$8:$A$18=$A19)*$E$8:$E$18)+SUMPRODUCT(($I$8:$I$18="NATL")*($K$8:$K$18+$A$8:$A$18=$A19)*$J$8:$J$18)+SUMPRODUCT(($N$8:$N$18="NATL")*($P$8:$P$18+$A$8:$A$18=$A19)*$O$8:$O$18)+SUMPRODUCT(($S$8:$S$18="NATL")*($U$8:$U$18+$A$8:$A$18=$A19)*$T$8:$T$18) -> 0.401 | Z19: =CLIMATE!G19+SUMPRODUCT(($D$8:$D$18="GLOBAL")*($F$8:$F$18+$A$8:$A$18=$A19)*$E$8:$E$18)+SUMPRODUCT(($I$8:$I$18="GLOBAL")*($K$8:$K$18+$A$8:$A$18=$A19)*$J$8:$J$18)+SUMPRODUCT(($N$8:$N$18="GLOBAL")*($P$8:$P$18+$A$8:$A$18=$A19)*$O$8:$O$18)+SUMPRODUCT(($S$8:$S$18="GLOBAL")*($U$8:$U$18+$A$8:$A$18=$A19)*$T$8:$T$18) -> 0 | AA19: =CLIMATE!H19+IFERROR(INDEX($W$8:$W$47,$A19-GRAPH!B17),0)*GRAPH!B9+IFERROR(INDEX($X$8:$X$47,$A19-GRAPH!B18),0)*GRAPH!B10+IFERROR(INDEX($Y$8:$Y$47,$A19-GRAPH!B19),0)*GRAPH!B11+IFERROR(INDEX($Z$8:$Z$47,$A19-GRAPH!B20),0)*GRAPH!B12+SUMPRODUCT(($D$8:$D$18=REGIONS!$B$7)*($F$8:$F$18+$A$8:$A$18=$A19)*$E$8:$E$18)+SUMPRODUCT(($N$8:$N$18=REGIONS!$B$7)*($P$8:$P$18+$A$8:$A$18=$A19)*$O$8:$O$18) -> -0.2675 | AB19: =CLIMATE!I19+IFERROR(INDEX($W$8:$W$47,$A19-GRAPH!C17),0)*GRAPH!C9+IFERROR(INDEX($X$8:$X$47,$A19-GRAPH!C18),0)*GRAPH!C10+IFERROR(INDEX($Y$8:$Y$47,$A19-GRAPH!C19),0)*GRAPH!C11+IFERROR(INDEX($Z$8:$Z$47,$A19-GRAPH!C20),0)*GRAPH!C12+SUMPRODUCT(($D$8:$D$18=REGIONS!$B$8)*($F$8:$F$18+$A$8:$A$18=$A19)*$E$8:$E$18)+SUMPRODUCT(($N$8:$N$18=REGIONS!$B$8)*($P$8:$P$18+$A$8:$A$18=$A19)*$O$8:$O$18) -> 0.0572 | AC19: =CLIMATE!J19+IFERROR(INDEX($W$8:$W$47,$A19-GRAPH!D17),0)*GRAPH!D9+IFERROR(INDEX($X$8:$X$47,$A19-GRAPH!D18),0)*GRAPH!D10+IFERROR(INDEX($Y$8:$Y$47,$A19-GRAPH!D19),0)*GRAPH!D11+IFERROR(INDEX($Z$8:$Z$47,$A19-GRAPH!D20),0)*GRAPH!D12+SUMPRODUCT(($D$8:$D$18=REGIONS!$B$9)*($F$8:$F$18+$A$8:$A$18=$A19)*$E$8:$E$18)+SUMPRODUCT(($N$8:$N$18=REGIONS!$B$9)*($P$8:$P$18+$A$8:$A$18=$A19)*$O$8:$O$18) -> -0.2415 | AD19: =CLIMATE!K19+IFERROR(INDEX($W$8:$W$47,$A19-GRAPH!E17),0)*GRAPH!E9+IFERROR(INDEX($X$8:$X$47,$A19-GRAPH!E18),0)*GRAPH!E10+IFERROR(INDEX($Y$8:$Y$47,$A19-GRAPH!E19),0)*GRAPH!E11+IFERROR(INDEX($Z$8:$Z$47,$A19-GRAPH!E20),0)*GRAPH!E12+SUMPRODUCT(($D$8:$D$18=REGIONS!$B$10)*($F$8:$F$18+$A$8:$A$18=$A19)*$E$8:$E$18)+SUMPRODUCT(($N$8:$N$18=REGIONS!$B$10)*($P$8:$P$18+$A$8:$A$18=$A19)*$O$8:$O$18) -> 0.4444 | AE19: =CLIMATE!L19+IFERROR(INDEX($W$8:$W$47,$A19-GRAPH!F17),0)*GRAPH!F9+IFERROR(INDEX($X$8:$X$47,$A19-GRAPH!F18),0)*GRAPH!F10+IFERROR(INDEX($Y$8:$Y$47,$A19-GRAPH!F19),0)*GRAPH!F11+IFERROR(INDEX($Z$8:$Z$47,$A19-GRAPH!F20),0)*GRAPH!F12+SUMPRODUCT(($D$8:$D$18=REGIONS!$B$11)*($F$8:$F$18+$A$8:$A$18=$A19)*$E$8:$E$18)+SUMPRODUCT(($N$8:$N$18=REGIONS!$B$11)*($P$8:$P$18+$A$8:$A$18=$A19)*$O$8:$O$18) -> 0.3344 | AF19: =CLIMATE!M19+IFERROR(INDEX($W$8:$W$47,$A19-GRAPH!G17),0)*GRAPH!G9+IFERROR(INDEX($X$8:$X$47,$A19-GRAPH!G18),0)*GRAPH!G10+IFERROR(INDEX($Y$8:$Y$47,$A19-GRAPH!G19),0)*GRAPH!G11+IFERROR(INDEX($Z$8:$Z$47,$A19-GRAPH!G20),0)*GRAPH!G12+SUMPRODUCT(($D$8:$D$18=REGIONS!$B$12)*($F$8:$F$18+$A$8:$A$18=$A19)*$E$8:$E$18)+SUMPRODUCT(($N$8:$N$18=REGIONS!$B$12)*($P$8:$P$18+$A$8:$A$18=$A19)*$O$8:$O$18) -> 0.7718 | AG19: =CLIMATE!N19+IFERROR(INDEX($W$8:$W$47,$A19-GRAPH!H17),0)*GRAPH!H9+IFERROR(INDEX($X$8:$X$47,$A19-GRAPH!H18),0)*GRAPH!H10+IFERROR(INDEX($Y$8:$Y$47,$A19-GRAPH!H19),0)*GRAPH!H11+IFERROR(INDEX($Z$8:$Z$47,$A19-GRAPH!H20),0)*GRAPH!H12+SUMPRODUCT(($D$8:$D$18=REGIONS!$B$13)*($F$8:$F$18+$A$8:$A$18=$A19)*$E$8:$E$18)+SUMPRODUCT(($N$8:$N$18=REGIONS!$B$13)*($P$8:$P$18+$A$8:$A$18=$A19)*$O$8:$O$18) -> 0.7484 | AH19: =CLIMATE!O19+IFERROR(INDEX($W$8:$W$47,$A19-GRAPH!I17),0)*GRAPH!I9+IFERROR(INDEX($X$8:$X$47,$A19-GRAPH!I18),0)*GRAPH!I10+IFERROR(INDEX($Y$8:$Y$47,$A19-GRAPH!I19),0)*GRAPH!I11+IFERROR(INDEX($Z$8:$Z$47,$A19-GRAPH!I20),0)*GRAPH!I12+SUMPRODUCT(($D$8:$D$18=REGIONS!$B$14)*($F$8:$F$18+$A$8:$A$18=$A19)*$E$8:$E$18)+SUMPRODUCT(($N$8:$N$18=REGIONS!$B$14)*($P$8:$P$18+$A$8:$A$18=$A19)*$O$8:$O$18) -> -0.2454 | AI19: =REGIONS!$F$7*(1+ASSUMPTIONS!$B$19*$A19) -> 0.8576 | AJ19: =REGIONS!$F$8*(1+ASSUMPTIONS!$B$19*$A19) -> 0.9648 | AK19: =REGIONS!$F$9*(1+ASSUMPTIONS!$B$19*$A19) -> 0.9648 | AL19: =REGIONS!$F$10*(1+ASSUMPTIONS!$B$19*$A19) -> 0.7504 | AM19: =REGIONS!$F$11*(1+ASSUMPTIONS!$B$19*$A19) -> 0.7504 | AN19: =REGIONS!$F$12*(1+ASSUMPTIONS!$B$19*$A19) -> 1.1792 | AO19: =REGIONS!$F$13*(1+ASSUMPTIONS!$B$19*$A19) -> 1.2864 | AP19: =REGIONS!$F$14*(1+ASSUMPTIONS!$B$19*$A19) -> 1.2864 | AQ19: =SUMPRODUCT(($D$8:$D$47=REGIONS!$B$7)*($A$8:$A$47<=$A19)*$L$8:$L$47)+SUMPRODUCT(($N$8:$N$47=REGIONS!$B$7)*($A$8:$A$47<=$A19)*$V$8:$V$47) -> 0 | AR19: =SUMPRODUCT(($D$8:$D$47=REGIONS!$B$8)*($A$8:$A$47<=$A19)*$L$8:$L$47)+SUMPRODUCT(($N$8:$N$47=REGIONS!$B$8)*($A$8:$A$47<=$A19)*$V$8:$V$47) -> 0 | AS19: =SUMPRODUCT(($D$8:$D$47=REGIONS!$B$9)*($A$8:$A$47<=$A19)*$L$8:$L$47)+SUMPRODUCT(($N$8:$N$47=REGIONS!$B$9)*($A$8:$A$47<=$A19)*$V$8:$V$47) -> 0 | AT19: =SUMPRODUCT(($D$8:$D$47=REGIONS!$B$10)*($A$8:$A$47<=$A19)*$L$8:$L$47)+SUMPRODUCT(($N$8:$N$47=REGIONS!$B$10)*($A$8:$A$47<=$A19)*$V$8:$V$47) -> 0 | AU19: =SUMPRODUCT(($D$8:$D$47=REGIONS!$B$11)*($A$8:$A$47<=$A19)*$L$8:$L$47)+SUMPRODUCT(($N$8:$N$47=REGIONS!$B$11)*($A$8:$A$47<=$A19)*$V$8:$V$47) -> 0 | AV19: =SUMPRODUCT(($D$8:$D$47=REGIONS!$B$12)*($A$8:$A$47<=$A19)*$L$8:$L$47)+SUMPRODUCT(($N$8:$N$47=REGIONS!$B$12)*($A$8:$A$47<=$A19)*$V$8:$V$47) -> 0 | AW19: =SUMPRODUCT(($D$8:$D$47=REGIONS!$B$13)*($A$8:$A$47<=$A19)*$L$8:$L$47)+SUMPRODUCT(($N$8:$N$47=REGIONS!$B$13)*($A$8:$A$47<=$A19)*$V$8:$V$47) -> 0 | AX19: =SUMPRODUCT(($D$8:$D$47=REGIONS!$B$14)*($A$8:$A$47<=$A19)*$L$8:$L$47)+SUMPRODUCT(($N$8:$N$47=REGIONS!$B$14)*($A$8:$A$47<=$A19)*$V$8:$V$47) -> 0 | AY19: =MAX(0,MIN(135,100-(MAX(0,-$AA19)*REGIONS!$E$7*ASSUMPTIONS!$B$7+MAX(0,$AA19-ASSUMPTIONS!$B$9)*REGIONS!$E$7*ASSUMPTIONS!$B$8)*(1-$AQ19/100))) -> 96.255 | AZ19: =MAX(0,MIN(135,100-(MAX(0,-$AB19)*REGIONS!$E$8*ASSUMPTIONS!$B$7+MAX(0,$AB19-ASSUMPTIONS!$B$9)*REGIONS!$E$8*ASSUMPTIONS!$B$8)*(1-$AR19/100))) -> 100 | BA19: =MAX(0,MIN(135,100-(MAX(0,-$AC19)*REGIONS!$E$9*ASSUMPTIONS!$B$7+MAX(0,$AC19-ASSUMPTIONS!$B$9)*REGIONS!$E$9*ASSUMPTIONS!$B$8)*(1-$AS19/100))) -> 96.619 | BB19: =MAX(0,MIN(135,100-(MAX(0,-$AD19)*REGIONS!$E$10*ASSUMPTIONS!$B$7+MAX(0,$AD19-ASSUMPTIONS!$B$9)*REGIONS!$E$10*ASSUMPTIONS!$B$8)*(1-$AT19/100))) -> 100 | BC19: =MAX(0,MIN(135,100-(MAX(0,-$AE19)*REGIONS!$E$11*ASSUMPTIONS!$B$7+MAX(0,$AE19-ASSUMPTIONS!$B$9)*REGIONS!$E$11*ASSUMPTIONS!$B$8)*(1-$AU19/100))) -> 100 | BD19: =MAX(0,MIN(135,100-(MAX(0,-$AF19)*REGIONS!$E$12*ASSUMPTIONS!$B$7+MAX(0,$AF19-ASSUMPTIONS!$B$9)*REGIONS!$E$12*ASSUMPTIONS!$B$8)*(1-$AV19/100))) -> 100 | BE19: =MAX(0,MIN(135,100-(MAX(0,-$AG19)*REGIONS!$E$13*ASSUMPTIONS!$B$7+MAX(0,$AG19-ASSUMPTIONS!$B$9)*REGIONS!$E$13*ASSUMPTIONS!$B$8)*(1-$AW19/100))) -> 100 | BF19: =MAX(0,MIN(135,100-(MAX(0,-$AH19)*REGIONS!$E$14*ASSUMPTIONS!$B$7+MAX(0,$AH19-ASSUMPTIONS!$B$9)*REGIONS!$E$14*ASSUMPTIONS!$B$8)*(1-$AX19/100))) -> 95.19016 | BG19: =$AY19*REGIONS!$D$7/100+$AZ19*REGIONS!$D$8/100+$BA19*REGIONS!$D$9/100+$BB19*REGIONS!$D$10/100+$BC19*REGIONS!$D$11/100+$BD19*REGIONS!$D$12/100+$BE19*REGIONS!$D$13/100+$BF19*REGIONS!$D$14/100 -> 98.45526 | BH19: =100*(100/MAX(1,$BG19))^ASSUMPTIONS!$B$10 -> 102.84186 | BI19: =$AY19*$BH19/100*ASSUMPTIONS!$B$11 -> 84.141871 | BJ19: =MAX(0,ABS($AA19)-$AI19*ASSUMPTIONS!$B$24)*REGIONS!$D$7/100+MAX(0,ABS($AB19)-$AJ19*ASSUMPTIONS!$B$24)*REGIONS!$D$8/100+MAX(0,ABS($AC19)-$AK19*ASSUMPTIONS!$B$24)*REGIONS!$D$9/100+MAX(0,ABS($AD19)-$AL19*ASSUMPTIONS!$B$24)*REGIONS!$D$10/100+MAX(0,ABS($AE19)-$AM19*ASSUMPTIONS!$B$24)*REGIONS!$D$11/100+MAX(0,ABS($AF19)-$AN19*ASSUMPTIONS!$B$24)*REGIONS!$D$12/100+MAX(0,ABS($AG19)-$AO19*ASSUMPTIONS!$B$24)*REGIONS!$D$13/100+MAX(0,ABS($AH19)-$AP19*ASSUMPTIONS!$B$24)*REGIONS!$D$14/100 -> 0 | BK19: =MIN(ASSUMPTIONS!$B$14,ASSUMPTIONS!$B$12+$BJ19*ASSUMPTIONS!$B$13) -> 28 | BL19: =$H19+$R19 -> 0 | BM19: =PLAY!$H19 -> 0 | BN19: =$BI19*ASSUMPTIONS!$B$15+$BK19*ASSUMPTIONS!$B$16 -> 35.297025 | BO19: =$BO18+$BN19-$BL19-$BM19-ASSUMPTIONS!$B$23 -> 159.30489 | BP19: =(SUMPRODUCT(($F$8:$F$18+$A$8:$A$18=$A19)*($C$8:$C$18<>"NONE")*$G$8:$G$18)+SUMPRODUCT(($P$8:$P$18+$A$8:$A$18=$A19)*($M$8:$M$18<>"NONE")*$Q$8:$Q$18))*(1+ASSUMPTIONS!$B$22*(MAX(0,ABS($AA19)/$AI19-1)+MAX(0,ABS($AB19)/$AJ19-1)+MAX(0,ABS($AC19)/$AK19-1)+MAX(0,ABS($AD19)/$AL19-1)+MAX(0,ABS($AE19)/$AM19-1)+MAX(0,ABS($AF19)/$AN19-1)+MAX(0,ABS($AG19)/$AO19-1)+MAX(0,ABS($AH19)/$AP19-1))/8) -> 0 | BQ19: =MAX(0,$BQ18*(1-ASSUMPTIONS!$B$18)+$BP19-$BM19*ASSUMPTIONS!$B$17) -> 1.4041457
A20: 13 | B20: =CLIMATE!B20 -> 1949 | C20: =IFERROR(INDEX(CAPABILITIES!$B$7:$B$15,MATCH(PLAY!$D20,CAPABILITIES!$A$7:$A$15,0)),"NONE") -> NONE | D20: =IFERROR(IF(INDEX(CAPABILITIES!$B$7:$B$15,MATCH(PLAY!$D20,CAPABILITIES!$A$7:$A$15,0))="DRIVER",INDEX(CAPABILITIES!$C$7:$C$15,MATCH(PLAY!$D20,CAPABILITIES!$A$7:$A$15,0)),PLAY!$E20),"") -> 0 | E20: =IFERROR(INDEX(CAPABILITIES!$D$7:$D$15,MATCH(PLAY!$D20,CAPABILITIES!$A$7:$A$15,0))*IF(INDEX(CAPABILITIES!$K$7:$K$15,MATCH(PLAY!$D20,CAPABILITIES!$A$7:$A$15,0))="Y",IF(IFERROR(INDEX($AA19:$AH19,MATCH(PLAY!$E20,REGIONS!$B$7:$B$14,0)),0)<ASSUMPTIONS!$B$20,1,ASSUMPTIONS!$B$21),1),0) -> 0 | F20: =IFERROR(INDEX(CAPABILITIES!$E$7:$E$15,MATCH(PLAY!$D20,CAPABILITIES!$A$7:$A$15,0)),0) -> 0 | G20: =IFERROR(INDEX(CAPABILITIES!$F$7:$F$15,MATCH(PLAY!$D20,CAPABILITIES!$A$7:$A$15,0)),0) -> 0 | H20: =IFERROR(INDEX(CAPABILITIES!$G$7:$G$15,MATCH(PLAY!$D20,CAPABILITIES!$A$7:$A$15,0)),0) -> 0 | I20: =IFERROR(INDEX(CAPABILITIES!$H$7:$H$15,MATCH(PLAY!$D20,CAPABILITIES!$A$7:$A$15,0)),"") -> 0 | J20: =IFERROR(INDEX(CAPABILITIES!$D$7:$D$15,MATCH(PLAY!$D20,CAPABILITIES!$A$7:$A$15,0))*INDEX(CAPABILITIES!$I$7:$I$15,MATCH(PLAY!$D20,CAPABILITIES!$A$7:$A$15,0)),0) -> 0 | K20: =IFERROR(INDEX(CAPABILITIES!$E$7:$E$15,MATCH(PLAY!$D20,CAPABILITIES!$A$7:$A$15,0))+INDEX(CAPABILITIES!$J$7:$J$15,MATCH(PLAY!$D20,CAPABILITIES!$A$7:$A$15,0)),0) -> 0 | L20: =IFERROR(INDEX(CAPABILITIES!$L$7:$L$15,MATCH(PLAY!$D20,CAPABILITIES!$A$7:$A$15,0)),0) -> 0 | M20: =IFERROR(INDEX(CAPABILITIES!$B$7:$B$15,MATCH(PLAY!$F20,CAPABILITIES!$A$7:$A$15,0)),"NONE") -> NONE | N20: =IFERROR(IF(INDEX(CAPABILITIES!$B$7:$B$15,MATCH(PLAY!$F20,CAPABILITIES!$A$7:$A$15,0))="DRIVER",INDEX(CAPABILITIES!$C$7:$C$15,MATCH(PLAY!$F20,CAPABILITIES!$A$7:$A$15,0)),PLAY!$G20),"") -> 0 | O20: =IFERROR(INDEX(CAPABILITIES!$D$7:$D$15,MATCH(PLAY!$F20,CAPABILITIES!$A$7:$A$15,0))*IF(INDEX(CAPABILITIES!$K$7:$K$15,MATCH(PLAY!$F20,CAPABILITIES!$A$7:$A$15,0))="Y",IF(IFERROR(INDEX($AA19:$AH19,MATCH(PLAY!$G20,REGIONS!$B$7:$B$14,0)),0)<ASSUMPTIONS!$B$20,1,ASSUMPTIONS!$B$21),1),0) -> 0 | P20: =IFERROR(INDEX(CAPABILITIES!$E$7:$E$15,MATCH(PLAY!$F20,CAPABILITIES!$A$7:$A$15,0)),0) -> 0 | Q20: =IFERROR(INDEX(CAPABILITIES!$F$7:$F$15,MATCH(PLAY!$F20,CAPABILITIES!$A$7:$A$15,0)),0) -> 0 | R20: =IFERROR(INDEX(CAPABILITIES!$G$7:$G$15,MATCH(PLAY!$F20,CAPABILITIES!$A$7:$A$15,0)),0) -> 0 | S20: =IFERROR(INDEX(CAPABILITIES!$H$7:$H$15,MATCH(PLAY!$F20,CAPABILITIES!$A$7:$A$15,0)),"") -> 0 | T20: =IFERROR(INDEX(CAPABILITIES!$D$7:$D$15,MATCH(PLAY!$F20,CAPABILITIES!$A$7:$A$15,0))*INDEX(CAPABILITIES!$I$7:$I$15,MATCH(PLAY!$F20,CAPABILITIES!$A$7:$A$15,0)),0) -> 0 | U20: =IFERROR(INDEX(CAPABILITIES!$E$7:$E$15,MATCH(PLAY!$F20,CAPABILITIES!$A$7:$A$15,0))+INDEX(CAPABILITIES!$J$7:$J$15,MATCH(PLAY!$F20,CAPABILITIES!$A$7:$A$15,0)),0) -> 0 | V20: =IFERROR(INDEX(CAPABILITIES!$L$7:$L$15,MATCH(PLAY!$F20,CAPABILITIES!$A$7:$A$15,0)),0) -> 0 | W20: =CLIMATE!D20+SUMPRODUCT(($D$8:$D$19="ENSO")*($F$8:$F$19+$A$8:$A$19=$A20)*$E$8:$E$19)+SUMPRODUCT(($I$8:$I$19="ENSO")*($K$8:$K$19+$A$8:$A$19=$A20)*$J$8:$J$19)+SUMPRODUCT(($N$8:$N$19="ENSO")*($P$8:$P$19+$A$8:$A$19=$A20)*$O$8:$O$19)+SUMPRODUCT(($S$8:$S$19="ENSO")*($U$8:$U$19+$A$8:$A$19=$A20)*$T$8:$T$19) -> -0.062 | X20: =CLIMATE!E20+SUMPRODUCT(($D$8:$D$19="IOD")*($F$8:$F$19+$A$8:$A$19=$A20)*$E$8:$E$19)+SUMPRODUCT(($I$8:$I$19="IOD")*($K$8:$K$19+$A$8:$A$19=$A20)*$J$8:$J$19)+SUMPRODUCT(($N$8:$N$19="IOD")*($P$8:$P$19+$A$8:$A$19=$A20)*$O$8:$O$19)+SUMPRODUCT(($S$8:$S$19="IOD")*($U$8:$U$19+$A$8:$A$19=$A20)*$T$8:$T$19) -> -0.86 | Y20: =CLIMATE!F20+SUMPRODUCT(($D$8:$D$19="NATL")*($F$8:$F$19+$A$8:$A$19=$A20)*$E$8:$E$19)+SUMPRODUCT(($I$8:$I$19="NATL")*($K$8:$K$19+$A$8:$A$19=$A20)*$J$8:$J$19)+SUMPRODUCT(($N$8:$N$19="NATL")*($P$8:$P$19+$A$8:$A$19=$A20)*$O$8:$O$19)+SUMPRODUCT(($S$8:$S$19="NATL")*($U$8:$U$19+$A$8:$A$19=$A20)*$T$8:$T$19) -> 0.1 | Z20: =CLIMATE!G20+SUMPRODUCT(($D$8:$D$19="GLOBAL")*($F$8:$F$19+$A$8:$A$19=$A20)*$E$8:$E$19)+SUMPRODUCT(($I$8:$I$19="GLOBAL")*($K$8:$K$19+$A$8:$A$19=$A20)*$J$8:$J$19)+SUMPRODUCT(($N$8:$N$19="GLOBAL")*($P$8:$P$19+$A$8:$A$19=$A20)*$O$8:$O$19)+SUMPRODUCT(($S$8:$S$19="GLOBAL")*($U$8:$U$19+$A$8:$A$19=$A20)*$T$8:$T$19) -> 0 | AA20: =CLIMATE!H20+IFERROR(INDEX($W$8:$W$47,$A20-GRAPH!B17),0)*GRAPH!B9+IFERROR(INDEX($X$8:$X$47,$A20-GRAPH!B18),0)*GRAPH!B10+IFERROR(INDEX($Y$8:$Y$47,$A20-GRAPH!B19),0)*GRAPH!B11+IFERROR(INDEX($Z$8:$Z$47,$A20-GRAPH!B20),0)*GRAPH!B12+SUMPRODUCT(($D$8:$D$19=REGIONS!$B$7)*($F$8:$F$19+$A$8:$A$19=$A20)*$E$8:$E$19)+SUMPRODUCT(($N$8:$N$19=REGIONS!$B$7)*($P$8:$P$19+$A$8:$A$19=$A20)*$O$8:$O$19) -> -0.361 | AB20: =CLIMATE!I20+IFERROR(INDEX($W$8:$W$47,$A20-GRAPH!C17),0)*GRAPH!C9+IFERROR(INDEX($X$8:$X$47,$A20-GRAPH!C18),0)*GRAPH!C10+IFERROR(INDEX($Y$8:$Y$47,$A20-GRAPH!C19),0)*GRAPH!C11+IFERROR(INDEX($Z$8:$Z$47,$A20-GRAPH!C20),0)*GRAPH!C12+SUMPRODUCT(($D$8:$D$19=REGIONS!$B$8)*($F$8:$F$19+$A$8:$A$19=$A20)*$E$8:$E$19)+SUMPRODUCT(($N$8:$N$19=REGIONS!$B$8)*($P$8:$P$19+$A$8:$A$19=$A20)*$O$8:$O$19) -> -0.1077 | AC20: =CLIMATE!J20+IFERROR(INDEX($W$8:$W$47,$A20-GRAPH!D17),0)*GRAPH!D9+IFERROR(INDEX($X$8:$X$47,$A20-GRAPH!D18),0)*GRAPH!D10+IFERROR(INDEX($Y$8:$Y$47,$A20-GRAPH!D19),0)*GRAPH!D11+IFERROR(INDEX($Z$8:$Z$47,$A20-GRAPH!D20),0)*GRAPH!D12+SUMPRODUCT(($D$8:$D$19=REGIONS!$B$9)*($F$8:$F$19+$A$8:$A$19=$A20)*$E$8:$E$19)+SUMPRODUCT(($N$8:$N$19=REGIONS!$B$9)*($P$8:$P$19+$A$8:$A$19=$A20)*$O$8:$O$19) -> -0.421 | AD20: =CLIMATE!K20+IFERROR(INDEX($W$8:$W$47,$A20-GRAPH!E17),0)*GRAPH!E9+IFERROR(INDEX($X$8:$X$47,$A20-GRAPH!E18),0)*GRAPH!E10+IFERROR(INDEX($Y$8:$Y$47,$A20-GRAPH!E19),0)*GRAPH!E11+IFERROR(INDEX($Z$8:$Z$47,$A20-GRAPH!E20),0)*GRAPH!E12+SUMPRODUCT(($D$8:$D$19=REGIONS!$B$10)*($F$8:$F$19+$A$8:$A$19=$A20)*$E$8:$E$19)+SUMPRODUCT(($N$8:$N$19=REGIONS!$B$10)*($P$8:$P$19+$A$8:$A$19=$A20)*$O$8:$O$19) -> -0.3491 | AE20: =CLIMATE!L20+IFERROR(INDEX($W$8:$W$47,$A20-GRAPH!F17),0)*GRAPH!F9+IFERROR(INDEX($X$8:$X$47,$A20-GRAPH!F18),0)*GRAPH!F10+IFERROR(INDEX($Y$8:$Y$47,$A20-GRAPH!F19),0)*GRAPH!F11+IFERROR(INDEX($Z$8:$Z$47,$A20-GRAPH!F20),0)*GRAPH!F12+SUMPRODUCT(($D$8:$D$19=REGIONS!$B$11)*($F$8:$F$19+$A$8:$A$19=$A20)*$E$8:$E$19)+SUMPRODUCT(($N$8:$N$19=REGIONS!$B$11)*($P$8:$P$19+$A$8:$A$19=$A20)*$O$8:$O$19) -> 0.4438 | AF20: =CLIMATE!M20+IFERROR(INDEX($W$8:$W$47,$A20-GRAPH!G17),0)*GRAPH!G9+IFERROR(INDEX($X$8:$X$47,$A20-GRAPH!G18),0)*GRAPH!G10+IFERROR(INDEX($Y$8:$Y$47,$A20-GRAPH!G19),0)*GRAPH!G11+IFERROR(INDEX($Z$8:$Z$47,$A20-GRAPH!G20),0)*GRAPH!G12+SUMPRODUCT(($D$8:$D$19=REGIONS!$B$12)*($F$8:$F$19+$A$8:$A$19=$A20)*$E$8:$E$19)+SUMPRODUCT(($N$8:$N$19=REGIONS!$B$12)*($P$8:$P$19+$A$8:$A$19=$A20)*$O$8:$O$19) -> 0.7446 | AG20: =CLIMATE!N20+IFERROR(INDEX($W$8:$W$47,$A20-GRAPH!H17),0)*GRAPH!H9+IFERROR(INDEX($X$8:$X$47,$A20-GRAPH!H18),0)*GRAPH!H10+IFERROR(INDEX($Y$8:$Y$47,$A20-GRAPH!H19),0)*GRAPH!H11+IFERROR(INDEX($Z$8:$Z$47,$A20-GRAPH!H20),0)*GRAPH!H12+SUMPRODUCT(($D$8:$D$19=REGIONS!$B$13)*($F$8:$F$19+$A$8:$A$19=$A20)*$E$8:$E$19)+SUMPRODUCT(($N$8:$N$19=REGIONS!$B$13)*($P$8:$P$19+$A$8:$A$19=$A20)*$O$8:$O$19) -> 0.612 | AH20: =CLIMATE!O20+IFERROR(INDEX($W$8:$W$47,$A20-GRAPH!I17),0)*GRAPH!I9+IFERROR(INDEX($X$8:$X$47,$A20-GRAPH!I18),0)*GRAPH!I10+IFERROR(INDEX($Y$8:$Y$47,$A20-GRAPH!I19),0)*GRAPH!I11+IFERROR(INDEX($Z$8:$Z$47,$A20-GRAPH!I20),0)*GRAPH!I12+SUMPRODUCT(($D$8:$D$19=REGIONS!$B$14)*($F$8:$F$19+$A$8:$A$19=$A20)*$E$8:$E$19)+SUMPRODUCT(($N$8:$N$19=REGIONS!$B$14)*($P$8:$P$19+$A$8:$A$19=$A20)*$O$8:$O$19) -> -0.9218 | AI20: =REGIONS!$F$7*(1+ASSUMPTIONS!$B$19*$A20) -> 0.8624 | AJ20: =REGIONS!$F$8*(1+ASSUMPTIONS!$B$19*$A20) -> 0.9702 | AK20: =REGIONS!$F$9*(1+ASSUMPTIONS!$B$19*$A20) -> 0.9702 | AL20: =REGIONS!$F$10*(1+ASSUMPTIONS!$B$19*$A20) -> 0.7546 | AM20: =REGIONS!$F$11*(1+ASSUMPTIONS!$B$19*$A20) -> 0.7546 | AN20: =REGIONS!$F$12*(1+ASSUMPTIONS!$B$19*$A20) -> 1.1858 | AO20: =REGIONS!$F$13*(1+ASSUMPTIONS!$B$19*$A20) -> 1.2936 | AP20: =REGIONS!$F$14*(1+ASSUMPTIONS!$B$19*$A20) -> 1.2936 | AQ20: =SUMPRODUCT(($D$8:$D$47=REGIONS!$B$7)*($A$8:$A$47<=$A20)*$L$8:$L$47)+SUMPRODUCT(($N$8:$N$47=REGIONS!$B$7)*($A$8:$A$47<=$A20)*$V$8:$V$47) -> 0 | AR20: =SUMPRODUCT(($D$8:$D$47=REGIONS!$B$8)*($A$8:$A$47<=$A20)*$L$8:$L$47)+SUMPRODUCT(($N$8:$N$47=REGIONS!$B$8)*($A$8:$A$47<=$A20)*$V$8:$V$47) -> 0 | AS20: =SUMPRODUCT(($D$8:$D$47=REGIONS!$B$9)*($A$8:$A$47<=$A20)*$L$8:$L$47)+SUMPRODUCT(($N$8:$N$47=REGIONS!$B$9)*($A$8:$A$47<=$A20)*$V$8:$V$47) -> 0 | AT20: =SUMPRODUCT(($D$8:$D$47=REGIONS!$B$10)*($A$8:$A$47<=$A20)*$L$8:$L$47)+SUMPRODUCT(($N$8:$N$47=REGIONS!$B$10)*($A$8:$A$47<=$A20)*$V$8:$V$47) -> 0 | AU20: =SUMPRODUCT(($D$8:$D$47=REGIONS!$B$11)*($A$8:$A$47<=$A20)*$L$8:$L$47)+SUMPRODUCT(($N$8:$N$47=REGIONS!$B$11)*($A$8:$A$47<=$A20)*$V$8:$V$47) -> 0 | AV20: =SUMPRODUCT(($D$8:$D$47=REGIONS!$B$12)*($A$8:$A$47<=$A20)*$L$8:$L$47)+SUMPRODUCT(($N$8:$N$47=REGIONS!$B$12)*($A$8:$A$47<=$A20)*$V$8:$V$47) -> 0 | AW20: =SUMPRODUCT(($D$8:$D$47=REGIONS!$B$13)*($A$8:$A$47<=$A20)*$L$8:$L$47)+SUMPRODUCT(($N$8:$N$47=REGIONS!$B$13)*($A$8:$A$47<=$A20)*$V$8:$V$47) -> 0 | AX20: =SUMPRODUCT(($D$8:$D$47=REGIONS!$B$14)*($A$8:$A$47<=$A20)*$L$8:$L$47)+SUMPRODUCT(($N$8:$N$47=REGIONS!$B$14)*($A$8:$A$47<=$A20)*$V$8:$V$47) -> 0 | AY20: =MAX(0,MIN(135,100-(MAX(0,-$AA20)*REGIONS!$E$7*ASSUMPTIONS!$B$7+MAX(0,$AA20-ASSUMPTIONS!$B$9)*REGIONS!$E$7*ASSUMPTIONS!$B$8)*(1-$AQ20/100))) -> 94.946 | AZ20: =MAX(0,MIN(135,100-(MAX(0,-$AB20)*REGIONS!$E$8*ASSUMPTIONS!$B$7+MAX(0,$AB20-ASSUMPTIONS!$B$9)*REGIONS!$E$8*ASSUMPTIONS!$B$8)*(1-$AR20/100))) -> 98.34142 | BA20: =MAX(0,MIN(135,100-(MAX(0,-$AC20)*REGIONS!$E$9*ASSUMPTIONS!$B$7+MAX(0,$AC20-ASSUMPTIONS!$B$9)*REGIONS!$E$9*ASSUMPTIONS!$B$8)*(1-$AS20/100))) -> 94.106 | BB20: =MAX(0,MIN(135,100-(MAX(0,-$AD20)*REGIONS!$E$10*ASSUMPTIONS!$B$7+MAX(0,$AD20-ASSUMPTIONS!$B$9)*REGIONS!$E$10*ASSUMPTIONS!$B$8)*(1-$AT20/100))) -> 94.13512 | BC20: =MAX(0,MIN(135,100-(MAX(0,-$AE20)*REGIONS!$E$11*ASSUMPTIONS!$B$7+MAX(0,$AE20-ASSUMPTIONS!$B$9)*REGIONS!$E$11*ASSUMPTIONS!$B$8)*(1-$AU20/100))) -> 100 | BD20: =MAX(0,MIN(135,100-(MAX(0,-$AF20)*REGIONS!$E$12*ASSUMPTIONS!$B$7+MAX(0,$AF20-ASSUMPTIONS!$B$9)*REGIONS!$E$12*ASSUMPTIONS!$B$8)*(1-$AV20/100))) -> 100 | BE20: =MAX(0,MIN(135,100-(MAX(0,-$AG20)*REGIONS!$E$13*ASSUMPTIONS!$B$7+MAX(0,$AG20-ASSUMPTIONS!$B$9)*REGIONS!$E$13*ASSUMPTIONS!$B$8)*(1-$AW20/100))) -> 100 | BF20: =MAX(0,MIN(135,100-(MAX(0,-$AH20)*REGIONS!$E$14*ASSUMPTIONS!$B$7+MAX(0,$AH20-ASSUMPTIONS!$B$9)*REGIONS!$E$14*ASSUMPTIONS!$B$8)*(1-$AX20/100))) -> 81.93272 | BG20: =$AY20*REGIONS!$D$7/100+$AZ20*REGIONS!$D$8/100+$BA20*REGIONS!$D$9/100+$BB20*REGIONS!$D$10/100+$BC20*REGIONS!$D$11/100+$BD20*REGIONS!$D$12/100+$BE20*REGIONS!$D$13/100+$BF20*REGIONS!$D$14/100 -> 95.700012 | BH20: =100*(100/MAX(1,$BG20))^ASSUMPTIONS!$B$10 -> 108.23268 | BI20: =$AY20*$BH20/100*ASSUMPTIONS!$B$11 -> 87.348211 | BJ20: =MAX(0,ABS($AA20)-$AI20*ASSUMPTIONS!$B$24)*REGIONS!$D$7/100+MAX(0,ABS($AB20)-$AJ20*ASSUMPTIONS!$B$24)*REGIONS!$D$8/100+MAX(0,ABS($AC20)-$AK20*ASSUMPTIONS!$B$24)*REGIONS!$D$9/100+MAX(0,ABS($AD20)-$AL20*ASSUMPTIONS!$B$24)*REGIONS!$D$10/100+MAX(0,ABS($AE20)-$AM20*ASSUMPTIONS!$B$24)*REGIONS!$D$11/100+MAX(0,ABS($AF20)-$AN20*ASSUMPTIONS!$B$24)*REGIONS!$D$12/100+MAX(0,ABS($AG20)-$AO20*ASSUMPTIONS!$B$24)*REGIONS!$D$13/100+MAX(0,ABS($AH20)-$AP20*ASSUMPTIONS!$B$24)*REGIONS!$D$14/100 -> 0 | BK20: =MIN(ASSUMPTIONS!$B$14,ASSUMPTIONS!$B$12+$BJ20*ASSUMPTIONS!$B$13) -> 28 | BL20: =$H20+$R20 -> 0 | BM20: =PLAY!$H20 -> 0 | BN20: =$BI20*ASSUMPTIONS!$B$15+$BK20*ASSUMPTIONS!$B$16 -> 35.681785 | BO20: =$BO19+$BN20-$BL20-$BM20-ASSUMPTIONS!$B$23 -> 162.98667 | BP20: =(SUMPRODUCT(($F$8:$F$19+$A$8:$A$19=$A20)*($C$8:$C$19<>"NONE")*$G$8:$G$19)+SUMPRODUCT(($P$8:$P$19+$A$8:$A$19=$A20)*($M$8:$M$19<>"NONE")*$Q$8:$Q$19))*(1+ASSUMPTIONS!$B$22*(MAX(0,ABS($AA20)/$AI20-1)+MAX(0,ABS($AB20)/$AJ20-1)+MAX(0,ABS($AC20)/$AK20-1)+MAX(0,ABS($AD20)/$AL20-1)+MAX(0,ABS($AE20)/$AM20-1)+MAX(0,ABS($AF20)/$AN20-1)+MAX(0,ABS($AG20)/$AO20-1)+MAX(0,ABS($AH20)/$AP20-1))/8) -> 0 | BQ20: =MAX(0,$BQ19*(1-ASSUMPTIONS!$B$18)+$BP20-$BM20*ASSUMPTIONS!$B$17) -> 1.3479799
A21: 14 | B21: =CLIMATE!B21 -> 1949 | C21: =IFERROR(INDEX(CAPABILITIES!$B$7:$B$15,MATCH(PLAY!$D21,CAPABILITIES!$A$7:$A$15,0)),"NONE") -> NONE | D21: =IFERROR(IF(INDEX(CAPABILITIES!$B$7:$B$15,MATCH(PLAY!$D21,CAPABILITIES!$A$7:$A$15,0))="DRIVER",INDEX(CAPABILITIES!$C$7:$C$15,MATCH(PLAY!$D21,CAPABILITIES!$A$7:$A$15,0)),PLAY!$E21),"") -> 0 | E21: =IFERROR(INDEX(CAPABILITIES!$D$7:$D$15,MATCH(PLAY!$D21,CAPABILITIES!$A$7:$A$15,0))*IF(INDEX(CAPABILITIES!$K$7:$K$15,MATCH(PLAY!$D21,CAPABILITIES!$A$7:$A$15,0))="Y",IF(IFERROR(INDEX($AA20:$AH20,MATCH(PLAY!$E21,REGIONS!$B$7:$B$14,0)),0)<ASSUMPTIONS!$B$20,1,ASSUMPTIONS!$B$21),1),0) -> 0 | F21: =IFERROR(INDEX(CAPABILITIES!$E$7:$E$15,MATCH(PLAY!$D21,CAPABILITIES!$A$7:$A$15,0)),0) -> 0 | G21: =IFERROR(INDEX(CAPABILITIES!$F$7:$F$15,MATCH(PLAY!$D21,CAPABILITIES!$A$7:$A$15,0)),0) -> 0 | H21: =IFERROR(INDEX(CAPABILITIES!$G$7:$G$15,MATCH(PLAY!$D21,CAPABILITIES!$A$7:$A$15,0)),0) -> 0 | I21: =IFERROR(INDEX(CAPABILITIES!$H$7:$H$15,MATCH(PLAY!$D21,CAPABILITIES!$A$7:$A$15,0)),"") -> 0 | J21: =IFERROR(INDEX(CAPABILITIES!$D$7:$D$15,MATCH(PLAY!$D21,CAPABILITIES!$A$7:$A$15,0))*INDEX(CAPABILITIES!$I$7:$I$15,MATCH(PLAY!$D21,CAPABILITIES!$A$7:$A$15,0)),0) -> 0 | K21: =IFERROR(INDEX(CAPABILITIES!$E$7:$E$15,MATCH(PLAY!$D21,CAPABILITIES!$A$7:$A$15,0))+INDEX(CAPABILITIES!$J$7:$J$15,MATCH(PLAY!$D21,CAPABILITIES!$A$7:$A$15,0)),0) -> 0 | L21: =IFERROR(INDEX(CAPABILITIES!$L$7:$L$15,MATCH(PLAY!$D21,CAPABILITIES!$A$7:$A$15,0)),0) -> 0 | M21: =IFERROR(INDEX(CAPABILITIES!$B$7:$B$15,MATCH(PLAY!$F21,CAPABILITIES!$A$7:$A$15,0)),"NONE") -> NONE | N21: =IFERROR(IF(INDEX(CAPABILITIES!$B$7:$B$15,MATCH(PLAY!$F21,CAPABILITIES!$A$7:$A$15,0))="DRIVER",INDEX(CAPABILITIES!$C$7:$C$15,MATCH(PLAY!$F21,CAPABILITIES!$A$7:$A$15,0)),PLAY!$G21),"") -> 0 | O21: =IFERROR(INDEX(CAPABILITIES!$D$7:$D$15,MATCH(PLAY!$F21,CAPABILITIES!$A$7:$A$15,0))*IF(INDEX(CAPABILITIES!$K$7:$K$15,MATCH(PLAY!$F21,CAPABILITIES!$A$7:$A$15,0))="Y",IF(IFERROR(INDEX($AA20:$AH20,MATCH(PLAY!$G21,REGIONS!$B$7:$B$14,0)),0)<ASSUMPTIONS!$B$20,1,ASSUMPTIONS!$B$21),1),0) -> 0 | P21: =IFERROR(INDEX(CAPABILITIES!$E$7:$E$15,MATCH(PLAY!$F21,CAPABILITIES!$A$7:$A$15,0)),0) -> 0 | Q21: =IFERROR(INDEX(CAPABILITIES!$F$7:$F$15,MATCH(PLAY!$F21,CAPABILITIES!$A$7:$A$15,0)),0) -> 0 | R21: =IFERROR(INDEX(CAPABILITIES!$G$7:$G$15,MATCH(PLAY!$F21,CAPABILITIES!$A$7:$A$15,0)),0) -> 0 | S21: =IFERROR(INDEX(CAPABILITIES!$H$7:$H$15,MATCH(PLAY!$F21,CAPABILITIES!$A$7:$A$15,0)),"") -> 0 | T21: =IFERROR(INDEX(CAPABILITIES!$D$7:$D$15,MATCH(PLAY!$F21,CAPABILITIES!$A$7:$A$15,0))*INDEX(CAPABILITIES!$I$7:$I$15,MATCH(PLAY!$F21,CAPABILITIES!$A$7:$A$15,0)),0) -> 0 | U21: =IFERROR(INDEX(CAPABILITIES!$E$7:$E$15,MATCH(PLAY!$F21,CAPABILITIES!$A$7:$A$15,0))+INDEX(CAPABILITIES!$J$7:$J$15,MATCH(PLAY!$F21,CAPABILITIES!$A$7:$A$15,0)),0) -> 0 | V21: =IFERROR(INDEX(CAPABILITIES!$L$7:$L$15,MATCH(PLAY!$F21,CAPABILITIES!$A$7:$A$15,0)),0) -> 0 | W21: =CLIMATE!D21+SUMPRODUCT(($D$8:$D$20="ENSO")*($F$8:$F$20+$A$8:$A$20=$A21)*$E$8:$E$20)+SUMPRODUCT(($I$8:$I$20="ENSO")*($K$8:$K$20+$A$8:$A$20=$A21)*$J$8:$J$20)+SUMPRODUCT(($N$8:$N$20="ENSO")*($P$8:$P$20+$A$8:$A$20=$A21)*$O$8:$O$20)+SUMPRODUCT(($S$8:$S$20="ENSO")*($U$8:$U$20+$A$8:$A$20=$A21)*$T$8:$T$20) -> 0.172 | X21: =CLIMATE!E21+SUMPRODUCT(($D$8:$D$20="IOD")*($F$8:$F$20+$A$8:$A$20=$A21)*$E$8:$E$20)+SUMPRODUCT(($I$8:$I$20="IOD")*($K$8:$K$20+$A$8:$A$20=$A21)*$J$8:$J$20)+SUMPRODUCT(($N$8:$N$20="IOD")*($P$8:$P$20+$A$8:$A$20=$A21)*$O$8:$O$20)+SUMPRODUCT(($S$8:$S$20="IOD")*($U$8:$U$20+$A$8:$A$20=$A21)*$T$8:$T$20) -> -0.084 | Y21: =CLIMATE!F21+SUMPRODUCT(($D$8:$D$20="NATL")*($F$8:$F$20+$A$8:$A$20=$A21)*$E$8:$E$20)+SUMPRODUCT(($I$8:$I$20="NATL")*($K$8:$K$20+$A$8:$A$20=$A21)*$J$8:$J$20)+SUMPRODUCT(($N$8:$N$20="NATL")*($P$8:$P$20+$A$8:$A$20=$A21)*$O$8:$O$20)+SUMPRODUCT(($S$8:$S$20="NATL")*($U$8:$U$20+$A$8:$A$20=$A21)*$T$8:$T$20) -> -0.229 | Z21: =CLIMATE!G21+SUMPRODUCT(($D$8:$D$20="GLOBAL")*($F$8:$F$20+$A$8:$A$20=$A21)*$E$8:$E$20)+SUMPRODUCT(($I$8:$I$20="GLOBAL")*($K$8:$K$20+$A$8:$A$20=$A21)*$J$8:$J$20)+SUMPRODUCT(($N$8:$N$20="GLOBAL")*($P$8:$P$20+$A$8:$A$20=$A21)*$O$8:$O$20)+SUMPRODUCT(($S$8:$S$20="GLOBAL")*($U$8:$U$20+$A$8:$A$20=$A21)*$T$8:$T$20) -> 0 | AA21: =CLIMATE!H21+IFERROR(INDEX($W$8:$W$47,$A21-GRAPH!B17),0)*GRAPH!B9+IFERROR(INDEX($X$8:$X$47,$A21-GRAPH!B18),0)*GRAPH!B10+IFERROR(INDEX($Y$8:$Y$47,$A21-GRAPH!B19),0)*GRAPH!B11+IFERROR(INDEX($Z$8:$Z$47,$A21-GRAPH!B20),0)*GRAPH!B12+SUMPRODUCT(($D$8:$D$20=REGIONS!$B$7)*($F$8:$F$20+$A$8:$A$20=$A21)*$E$8:$E$20)+SUMPRODUCT(($N$8:$N$20=REGIONS!$B$7)*($P$8:$P$20+$A$8:$A$20=$A21)*$O$8:$O$20) -> -0.3561 | AB21: =CLIMATE!I21+IFERROR(INDEX($W$8:$W$47,$A21-GRAPH!C17),0)*GRAPH!C9+IFERROR(INDEX($X$8:$X$47,$A21-GRAPH!C18),0)*GRAPH!C10+IFERROR(INDEX($Y$8:$Y$47,$A21-GRAPH!C19),0)*GRAPH!C11+IFERROR(INDEX($Z$8:$Z$47,$A21-GRAPH!C20),0)*GRAPH!C12+SUMPRODUCT(($D$8:$D$20=REGIONS!$B$8)*($F$8:$F$20+$A$8:$A$20=$A21)*$E$8:$E$20)+SUMPRODUCT(($N$8:$N$20=REGIONS!$B$8)*($P$8:$P$20+$A$8:$A$20=$A21)*$O$8:$O$20) -> -0.2392 | AC21: =CLIMATE!J21+IFERROR(INDEX($W$8:$W$47,$A21-GRAPH!D17),0)*GRAPH!D9+IFERROR(INDEX($X$8:$X$47,$A21-GRAPH!D18),0)*GRAPH!D10+IFERROR(INDEX($Y$8:$Y$47,$A21-GRAPH!D19),0)*GRAPH!D11+IFERROR(INDEX($Z$8:$Z$47,$A21-GRAPH!D20),0)*GRAPH!D12+SUMPRODUCT(($D$8:$D$20=REGIONS!$B$9)*($F$8:$F$20+$A$8:$A$20=$A21)*$E$8:$E$20)+SUMPRODUCT(($N$8:$N$20=REGIONS!$B$9)*($P$8:$P$20+$A$8:$A$20=$A21)*$O$8:$O$20) -> -0.076 | AD21: =CLIMATE!K21+IFERROR(INDEX($W$8:$W$47,$A21-GRAPH!E17),0)*GRAPH!E9+IFERROR(INDEX($X$8:$X$47,$A21-GRAPH!E18),0)*GRAPH!E10+IFERROR(INDEX($Y$8:$Y$47,$A21-GRAPH!E19),0)*GRAPH!E11+IFERROR(INDEX($Z$8:$Z$47,$A21-GRAPH!E20),0)*GRAPH!E12+SUMPRODUCT(($D$8:$D$20=REGIONS!$B$10)*($F$8:$F$20+$A$8:$A$20=$A21)*$E$8:$E$20)+SUMPRODUCT(($N$8:$N$20=REGIONS!$B$10)*($P$8:$P$20+$A$8:$A$20=$A21)*$O$8:$O$20) -> -0.0378 | AE21: =CLIMATE!L21+IFERROR(INDEX($W$8:$W$47,$A21-GRAPH!F17),0)*GRAPH!F9+IFERROR(INDEX($X$8:$X$47,$A21-GRAPH!F18),0)*GRAPH!F10+IFERROR(INDEX($Y$8:$Y$47,$A21-GRAPH!F19),0)*GRAPH!F11+IFERROR(INDEX($Z$8:$Z$47,$A21-GRAPH!F20),0)*GRAPH!F12+SUMPRODUCT(($D$8:$D$20=REGIONS!$B$11)*($F$8:$F$20+$A$8:$A$20=$A21)*$E$8:$E$20)+SUMPRODUCT(($N$8:$N$20=REGIONS!$B$11)*($P$8:$P$20+$A$8:$A$20=$A21)*$O$8:$O$20) -> -0.0106 | AF21: =CLIMATE!M21+IFERROR(INDEX($W$8:$W$47,$A21-GRAPH!G17),0)*GRAPH!G9+IFERROR(INDEX($X$8:$X$47,$A21-GRAPH!G18),0)*GRAPH!G10+IFERROR(INDEX($Y$8:$Y$47,$A21-GRAPH!G19),0)*GRAPH!G11+IFERROR(INDEX($Z$8:$Z$47,$A21-GRAPH!G20),0)*GRAPH!G12+SUMPRODUCT(($D$8:$D$20=REGIONS!$B$12)*($F$8:$F$20+$A$8:$A$20=$A21)*$E$8:$E$20)+SUMPRODUCT(($N$8:$N$20=REGIONS!$B$12)*($P$8:$P$20+$A$8:$A$20=$A21)*$O$8:$O$20) -> 0.5048 | AG21: =CLIMATE!N21+IFERROR(INDEX($W$8:$W$47,$A21-GRAPH!H17),0)*GRAPH!H9+IFERROR(INDEX($X$8:$X$47,$A21-GRAPH!H18),0)*GRAPH!H10+IFERROR(INDEX($Y$8:$Y$47,$A21-GRAPH!H19),0)*GRAPH!H11+IFERROR(INDEX($Z$8:$Z$47,$A21-GRAPH!H20),0)*GRAPH!H12+SUMPRODUCT(($D$8:$D$20=REGIONS!$B$13)*($F$8:$F$20+$A$8:$A$20=$A21)*$E$8:$E$20)+SUMPRODUCT(($N$8:$N$20=REGIONS!$B$13)*($P$8:$P$20+$A$8:$A$20=$A21)*$O$8:$O$20) -> 0.2914 | AH21: =CLIMATE!O21+IFERROR(INDEX($W$8:$W$47,$A21-GRAPH!I17),0)*GRAPH!I9+IFERROR(INDEX($X$8:$X$47,$A21-GRAPH!I18),0)*GRAPH!I10+IFERROR(INDEX($Y$8:$Y$47,$A21-GRAPH!I19),0)*GRAPH!I11+IFERROR(INDEX($Z$8:$Z$47,$A21-GRAPH!I20),0)*GRAPH!I12+SUMPRODUCT(($D$8:$D$20=REGIONS!$B$14)*($F$8:$F$20+$A$8:$A$20=$A21)*$E$8:$E$20)+SUMPRODUCT(($N$8:$N$20=REGIONS!$B$14)*($P$8:$P$20+$A$8:$A$20=$A21)*$O$8:$O$20) -> -0.387 | AI21: =REGIONS!$F$7*(1+ASSUMPTIONS!$B$19*$A21) -> 0.8672 | AJ21: =REGIONS!$F$8*(1+ASSUMPTIONS!$B$19*$A21) -> 0.9756 | AK21: =REGIONS!$F$9*(1+ASSUMPTIONS!$B$19*$A21) -> 0.9756 | AL21: =REGIONS!$F$10*(1+ASSUMPTIONS!$B$19*$A21) -> 0.7588 | AM21: =REGIONS!$F$11*(1+ASSUMPTIONS!$B$19*$A21) -> 0.7588 | AN21: =REGIONS!$F$12*(1+ASSUMPTIONS!$B$19*$A21) -> 1.1924 | AO21: =REGIONS!$F$13*(1+ASSUMPTIONS!$B$19*$A21) -> 1.3008 | AP21: =REGIONS!$F$14*(1+ASSUMPTIONS!$B$19*$A21) -> 1.3008 | AQ21: =SUMPRODUCT(($D$8:$D$47=REGIONS!$B$7)*($A$8:$A$47<=$A21)*$L$8:$L$47)+SUMPRODUCT(($N$8:$N$47=REGIONS!$B$7)*($A$8:$A$47<=$A21)*$V$8:$V$47) -> 0 | AR21: =SUMPRODUCT(($D$8:$D$47=REGIONS!$B$8)*($A$8:$A$47<=$A21)*$L$8:$L$47)+SUMPRODUCT(($N$8:$N$47=REGIONS!$B$8)*($A$8:$A$47<=$A21)*$V$8:$V$47) -> 0 | AS21: =SUMPRODUCT(($D$8:$D$47=REGIONS!$B$9)*($A$8:$A$47<=$A21)*$L$8:$L$47)+SUMPRODUCT(($N$8:$N$47=REGIONS!$B$9)*($A$8:$A$47<=$A21)*$V$8:$V$47) -> 0 | AT21: =SUMPRODUCT(($D$8:$D$47=REGIONS!$B$10)*($A$8:$A$47<=$A21)*$L$8:$L$47)+SUMPRODUCT(($N$8:$N$47=REGIONS!$B$10)*($A$8:$A$47<=$A21)*$V$8:$V$47) -> 0 | AU21: =SUMPRODUCT(($D$8:$D$47=REGIONS!$B$11)*($A$8:$A$47<=$A21)*$L$8:$L$47)+SUMPRODUCT(($N$8:$N$47=REGIONS!$B$11)*($A$8:$A$47<=$A21)*$V$8:$V$47) -> 0 | AV21: =SUMPRODUCT(($D$8:$D$47=REGIONS!$B$12)*($A$8:$A$47<=$A21)*$L$8:$L$47)+SUMPRODUCT(($N$8:$N$47=REGIONS!$B$12)*($A$8:$A$47<=$A21)*$V$8:$V$47) -> 0 | AW21: =SUMPRODUCT(($D$8:$D$47=REGIONS!$B$13)*($A$8:$A$47<=$A21)*$L$8:$L$47)+SUMPRODUCT(($N$8:$N$47=REGIONS!$B$13)*($A$8:$A$47<=$A21)*$V$8:$V$47) -> 0 | AX21: =SUMPRODUCT(($D$8:$D$47=REGIONS!$B$14)*($A$8:$A$47<=$A21)*$L$8:$L$47)+SUMPRODUCT(($N$8:$N$47=REGIONS!$B$14)*($A$8:$A$47<=$A21)*$V$8:$V$47) -> 0 | AY21: =MAX(0,MIN(135,100-(MAX(0,-$AA21)*REGIONS!$E$7*ASSUMPTIONS!$B$7+MAX(0,$AA21-ASSUMPTIONS!$B$9)*REGIONS!$E$7*ASSUMPTIONS!$B$8)*(1-$AQ21/100))) -> 95.0146 | AZ21: =MAX(0,MIN(135,100-(MAX(0,-$AB21)*REGIONS!$E$8*ASSUMPTIONS!$B$7+MAX(0,$AB21-ASSUMPTIONS!$B$9)*REGIONS!$E$8*ASSUMPTIONS!$B$8)*(1-$AR21/100))) -> 96.31632 | BA21: =MAX(0,MIN(135,100-(MAX(0,-$AC21)*REGIONS!$E$9*ASSUMPTIONS!$B$7+MAX(0,$AC21-ASSUMPTIONS!$B$9)*REGIONS!$E$9*ASSUMPTIONS!$B$8)*(1-$AS21/100))) -> 98.936 | BB21: =MAX(0,MIN(135,100-(MAX(0,-$AD21)*REGIONS!$E$10*ASSUMPTIONS!$B$7+MAX(0,$AD21-ASSUMPTIONS!$B$9)*REGIONS!$E$10*ASSUMPTIONS!$B$8)*(1-$AT21/100))) -> 99.36496 | BC21: =MAX(0,MIN(135,100-(MAX(0,-$AE21)*REGIONS!$E$11*ASSUMPTIONS!$B$7+MAX(0,$AE21-ASSUMPTIONS!$B$9)*REGIONS!$E$11*ASSUMPTIONS!$B$8)*(1-$AU21/100))) -> 99.83676 | BD21: =MAX(0,MIN(135,100-(MAX(0,-$AF21)*REGIONS!$E$12*ASSUMPTIONS!$B$7+MAX(0,$AF21-ASSUMPTIONS!$B$9)*REGIONS!$E$12*ASSUMPTIONS!$B$8)*(1-$AV21/100))) -> 100 | BE21: =MAX(0,MIN(135,100-(MAX(0,-$AG21)*REGIONS!$E$13*ASSUMPTIONS!$B$7+MAX(0,$AG21-ASSUMPTIONS!$B$9)*REGIONS!$E$13*ASSUMPTIONS!$B$8)*(1-$AW21/100))) -> 100 | BF21: =MAX(0,MIN(135,100-(MAX(0,-$AH21)*REGIONS!$E$14*ASSUMPTIONS!$B$7+MAX(0,$AH21-ASSUMPTIONS!$B$9)*REGIONS!$E$14*ASSUMPTIONS!$B$8)*(1-$AX21/100))) -> 92.4148 | BG21: =$AY21*REGIONS!$D$7/100+$AZ21*REGIONS!$D$8/100+$BA21*REGIONS!$D$9/100+$BB21*REGIONS!$D$10/100+$BC21*REGIONS!$D$11/100+$BD21*REGIONS!$D$12/100+$BE21*REGIONS!$D$13/100+$BF21*REGIONS!$D$14/100 -> 97.664923 | BH21: =100*(100/MAX(1,$BG21))^ASSUMPTIONS!$B$10 -> 104.34472 | BI21: =$AY21*$BH21/100*ASSUMPTIONS!$B$11 -> 84.271314 | BJ21: =MAX(0,ABS($AA21)-$AI21*ASSUMPTIONS!$B$24)*REGIONS!$D$7/100+MAX(0,ABS($AB21)-$AJ21*ASSUMPTIONS!$B$24)*REGIONS!$D$8/100+MAX(0,ABS($AC21)-$AK21*ASSUMPTIONS!$B$24)*REGIONS!$D$9/100+MAX(0,ABS($AD21)-$AL21*ASSUMPTIONS!$B$24)*REGIONS!$D$10/100+MAX(0,ABS($AE21)-$AM21*ASSUMPTIONS!$B$24)*REGIONS!$D$11/100+MAX(0,ABS($AF21)-$AN21*ASSUMPTIONS!$B$24)*REGIONS!$D$12/100+MAX(0,ABS($AG21)-$AO21*ASSUMPTIONS!$B$24)*REGIONS!$D$13/100+MAX(0,ABS($AH21)-$AP21*ASSUMPTIONS!$B$24)*REGIONS!$D$14/100 -> 0 | BK21: =MIN(ASSUMPTIONS!$B$14,ASSUMPTIONS!$B$12+$BJ21*ASSUMPTIONS!$B$13) -> 28 | BL21: =$H21+$R21 -> 0 | BM21: =PLAY!$H21 -> 0 | BN21: =$BI21*ASSUMPTIONS!$B$15+$BK21*ASSUMPTIONS!$B$16 -> 35.312558 | BO21: =$BO20+$BN21-$BL21-$BM21-ASSUMPTIONS!$B$23 -> 166.29923 | BP21: =(SUMPRODUCT(($F$8:$F$20+$A$8:$A$20=$A21)*($C$8:$C$20<>"NONE")*$G$8:$G$20)+SUMPRODUCT(($P$8:$P$20+$A$8:$A$20=$A21)*($M$8:$M$20<>"NONE")*$Q$8:$Q$20))*(1+ASSUMPTIONS!$B$22*(MAX(0,ABS($AA21)/$AI21-1)+MAX(0,ABS($AB21)/$AJ21-1)+MAX(0,ABS($AC21)/$AK21-1)+MAX(0,ABS($AD21)/$AL21-1)+MAX(0,ABS($AE21)/$AM21-1)+MAX(0,ABS($AF21)/$AN21-1)+MAX(0,ABS($AG21)/$AO21-1)+MAX(0,ABS($AH21)/$AP21-1))/8) -> 0 | BQ21: =MAX(0,$BQ20*(1-ASSUMPTIONS!$B$18)+$BP21-$BM21*ASSUMPTIONS!$B$17) -> 1.2940607
